password_lock_system/rtl/lock_controller.v
`timescale 1ns/1ps

// 密码锁主控制器（有限状态机 FSM）。
// 组合逻辑只计算 next_state；时序逻辑在时钟沿更新状态、计时、输入缓存和单周期控制脉冲。
// state 编码同时送往数码管和测试平台，因此修改编码时必须同步修改显示/仿真中的状态定义。
module lock_controller #(
    parameter integer CLOCK_HZ         = 50_000_000,
    parameter integer LOCK_TIMEOUT_S   = 8,
    parameter integer OPEN_TIMEOUT_S   = 16,
    parameter integer ERROR_DISPLAY_MS = 1000
) (
    input  wire        clk,
    input  wire        rst,
    input  wire        flash_init_done,
    input  wire [15:0] stored_password,
    input  wire        flash_fault,
    input  wire        sw1_event,
    input  wire        admin_event,
    input  wire        alarm_clear_event,
    input  wire        temporary_event,
    input  wire [15:0] temporary_password,
    input  wire        temporary_valid,
    input  wire        key_valid,
    input  wire [3:0]  key_code,
    input  wire        save_done,
    input  wire        save_success,
    output reg         save_request,
    output reg [15:0]  save_password,
    output reg         capture_start,
    output reg         unlocked,
    output reg         alarm_active,
    output reg [3:0]   state,
    output reg [15:0]  entry_digits,
    output reg [2:0]   entry_count,
    output reg [2:0]   error_count,
    output reg         display_fault
);
    // 状态含义：上电初始化、等待、用户输入、错误提示、开锁、管理员输入、保存、报警、临时密码。
    localparam [3:0] ST_BOOT  = 4'd0,
                     ST_WAIT  = 4'd1,
                     ST_USER  = 4'd2,
                     ST_ERROR = 4'd3,
                     ST_OPEN  = 4'd4,
                     ST_ADMIN = 4'd5,
                     ST_SAVE  = 4'd6,
                     ST_ALARM = 4'd7,
                     ST_TEMP  = 4'd8;
    localparam integer LOCK_TICKS  = CLOCK_HZ * LOCK_TIMEOUT_S;
    localparam integer OPEN_TICKS  = CLOCK_HZ * OPEN_TIMEOUT_S;
    localparam integer ERROR_TICKS = (CLOCK_HZ / 1000) * ERROR_DISPLAY_MS;
    localparam integer MAX_TICKS = (OPEN_TICKS > LOCK_TICKS) ? OPEN_TICKS : LOCK_TICKS;
    localparam integer MAX_TICKS2 = (MAX_TICKS > ERROR_TICKS) ? MAX_TICKS : ERROR_TICKS;
    localparam integer TW = (MAX_TICKS2 <= 2) ? 1 : $clog2(MAX_TICKS2 + 1);

    reg [3:0] next_state;
    reg [TW-1:0] timer_count;
    // 键盘码 0~9 是数字；A=确认，B=退格，C=取消。有效操作会重新开始超时计时。
    wire is_digit = (key_code <= 4'd9);
    wire activity = key_valid && (is_digit || key_code == 4'hA ||
                                  key_code == 4'hB || key_code == 4'hC);

    // 下一状态判定。错误计数表示已经发生的错误次数：第 4 次错误直接进入报警态。
    always @(*) begin
        next_state = state;
        case (state)
            ST_BOOT:  if (flash_init_done) next_state = ST_WAIT;
            ST_WAIT:  if (temporary_event) next_state = ST_TEMP;
                      else if (admin_event) next_state = ST_ADMIN;
                      else if (sw1_event) next_state = ST_USER;
            ST_USER:  if (key_valid && key_code == 4'hC) next_state = ST_WAIT;
                      else if ((timer_count >= LOCK_TICKS-1) && !activity) next_state = ST_WAIT;
                      else if (key_valid && key_code == 4'hA && entry_count == 3'd4) begin
                          if (entry_digits == stored_password ||
                              (temporary_valid && entry_digits == temporary_password))
                              next_state = ST_OPEN;
                          else if (error_count == 3'd3) next_state = ST_ALARM;
                          else next_state = ST_ERROR;
                      end
            ST_ERROR: if (timer_count >= ERROR_TICKS-1) next_state = ST_USER;
            ST_OPEN:  if ((key_valid && key_code == 4'hA) ||
                          (timer_count >= OPEN_TICKS-1)) next_state = ST_WAIT;
                      else if (admin_event) next_state = ST_ADMIN;
            ST_ADMIN: if (key_valid && key_code == 4'hC) next_state = ST_WAIT;
                      else if ((timer_count >= LOCK_TICKS-1) && !activity) next_state = ST_WAIT;
                      else if (key_valid && key_code == 4'hA && entry_count == 3'd4)
                          next_state = ST_SAVE;
            ST_SAVE:  if (save_done) next_state = ST_WAIT;
            // 临时密码重新生成的优先级最高，使新密码至少完整显示一个超时时间。
            ST_TEMP:  if (temporary_event) next_state = ST_TEMP;
                      else if (sw1_event) next_state = ST_USER;
                      else if (key_valid && (key_code == 4'hA || key_code == 4'hC))
                          next_state = ST_WAIT;
                      else if (timer_count >= LOCK_TICKS-1) next_state = ST_WAIT;
            // 报警态只能由 KEY2 的 alarm_clear_event 解除，解除后直接进入新的用户输入会话。
            ST_ALARM: if (alarm_clear_event) next_state = ST_USER;
            default: next_state = ST_BOOT;
        endcase
    end

    // 状态寄存器及动作逻辑。save_request、capture_start 默认每拍清零，故都是单周期脉冲。
    always @(posedge clk) begin
        if (rst) begin
            state          <= ST_BOOT;
            timer_count    <= {TW{1'b0}};
            entry_digits   <= 16'h0000;
            entry_count    <= 3'd0;
            error_count    <= 3'd0;
            save_request   <= 1'b0;
            save_password  <= 16'h1234;
            capture_start  <= 1'b0;
            display_fault  <= 1'b0;
        end else begin
            state         <= next_state;
            save_request  <= 1'b0;
            capture_start <= 1'b0;

            // 发生状态转移时统一清计时器，并执行相应“进入状态”动作。
            if (state != next_state) begin
                timer_count <= {TW{1'b0}};
                if (next_state == ST_USER || next_state == ST_ADMIN ||
                    next_state == ST_WAIT) begin
                    entry_digits <= 16'h0000;
                    entry_count  <= 3'd0;
                end
                if (next_state == ST_OPEN)
                    error_count <= 3'd0;
                if (next_state == ST_ERROR)
                    error_count <= error_count + 1'b1;
                if (next_state == ST_ALARM) begin
                    error_count   <= 3'd4;
                    capture_start <= 1'b1;
                end
                // 管理员解除报警后把错误次数清零，重新获得四次尝试机会。
                if (state == ST_ALARM && alarm_clear_event)
                    error_count <= 3'd0;
                // 进入保存态时锁存新密码，并向 Flash 模块发出一个时钟周期的写请求。
                if (next_state == ST_SAVE) begin
                    save_password <= entry_digits;
                    save_request  <= 1'b1;
                end
                if (state == ST_SAVE && next_state == ST_WAIT)
                    display_fault <= ~save_success;
            end else begin
                // 状态未改变时累计超时；数字/A/B/C 或重新生成临时密码会清零计时。
                if ((activity || temporary_event) &&
                    (state == ST_USER || state == ST_ADMIN || state == ST_OPEN || state == ST_TEMP))
                    timer_count <= {TW{1'b0}};
                else if (state == ST_USER || state == ST_ADMIN || state == ST_OPEN ||
                         state == ST_ERROR || state == ST_TEMP)
                    timer_count <= timer_count + 1'b1;

                // 4 位 BCD 输入左移追加；B 键右移删除最后一位。超过 4 位的数字被忽略。
                if ((state == ST_USER || state == ST_ADMIN) && key_valid) begin
                    if (is_digit && entry_count < 3'd4) begin
                        entry_digits <= {entry_digits[11:0], key_code};
                        entry_count  <= entry_count + 1'b1;
                    end else if (key_code == 4'hB && entry_count != 0) begin
                        entry_digits <= {4'h0, entry_digits[15:4]};
                        entry_count  <= entry_count - 1'b1;
                    end
                end
            end

            // 新操作可清除上次保存失败提示；Flash 当前故障则始终置位显示故障。
            if (display_fault && (sw1_event || admin_event || temporary_event))
                display_fault <= 1'b0;
            if (flash_fault)
                display_fault <= 1'b1;
        end
    end

    // 两个输出直接由状态译码，避免在各分支重复赋值。
    always @(*) begin
        unlocked     = (state == ST_OPEN);
        alarm_active = (state == ST_ALARM);
    end
endmodule

password_lock_system/sim/tb_lock_controller.sv
`timescale 1ns/1ps
// 主状态机综合回归：覆盖固定/临时密码、替换优先级、管理员保存、四次错误报警和超时。
module tb_lock_controller;
    reg test_pass=0;
    reg clk=0,rst=1,init_done=0,flash_fault=0,sw1=0,admin=0,clear=0,temp_event=0,key_valid=0;
    reg [3:0] key_code=0;
    reg [15:0] stored_password=16'h1234;
    reg [15:0] temporary_password=16'h0000;
    reg temporary_valid=0;
    reg save_done=0,save_success=0;
    wire save_request,capture_start,unlocked,alarm_active,display_fault;
    wire [15:0] save_password,entry_digits;
    wire [3:0] state;
    wire [2:0] entry_count,error_count;
    always #5 clk=~clk;
    lock_controller #(.CLOCK_HZ(1000),.LOCK_TIMEOUT_S(1),.OPEN_TIMEOUT_S(2),.ERROR_DISPLAY_MS(2)) dut(
        .clk(clk),.rst(rst),.flash_init_done(init_done),.stored_password(stored_password),
        .flash_fault(flash_fault),.sw1_event(sw1),.admin_event(admin),.alarm_clear_event(clear),
        .temporary_event(temp_event),.temporary_password(temporary_password),.temporary_valid(temporary_valid),
        .key_valid(key_valid),.key_code(key_code),.save_done(save_done),.save_success(save_success),
        .save_request(save_request),.save_password(save_password),.capture_start(capture_start),
        .unlocked(unlocked),.alarm_active(alarm_active),.state(state),.entry_digits(entry_digits),
        .entry_count(entry_count),.error_count(error_count),.display_fault(display_fault));
    // pulse(0/1/2/3)=SW1/管理员/解除报警/临时密码；key 模拟键盘单周期有效码。
    task pulse(input integer which);
      begin @(negedge clk); if(which==0)sw1=1; if(which==1)admin=1; if(which==2)clear=1;
            if(which==3)temp_event=1;
            @(negedge clk); sw1=0;admin=0;clear=0;temp_event=0; end
    endtask
    task key(input [3:0] code);
      begin @(negedge clk);key_code=code;key_valid=1;@(negedge clk);key_valid=0; end
    endtask
    task digits(input [15:0] value);
      begin key(value[15:12]);key(value[11:8]);key(value[7:4]);key(value[3:0]); end
    endtask
    task check(input bit condition,input string message);
      if(!condition) $fatal(1,"FAIL: %s state=%0d",message,state);
    endtask
    integer n;
    // 此测试串行走完主要状态路径，任一 check 失败都会报告当时的 state 编码。
    initial begin
      repeat(4) @(negedge clk); rst=0; init_done=1; repeat(2) @(negedge clk);
      check(state==1,"boot to wait");
      pulse(0); digits(16'h1234); key(4'hA); repeat(2) @(negedge clk);
      check(unlocked,"correct password unlocks");
      key(4'hA); repeat(2) @(negedge clk); check(state==1,"A locks immediately");
      temporary_password=16'h2468;temporary_valid=1;pulse(3);repeat(2)@(negedge clk);
      check(state==8,"KEY3 displays temporary password");
      pulse(0);digits(16'h2468);key(4'hA);repeat(2)@(negedge clk);
      check(unlocked,"temporary password unlocks");
      key(4'hA);repeat(2)@(negedge clk);
      pulse(3);temporary_password=16'h1357;
      @(negedge clk);temp_event=1;sw1=1;
      @(negedge clk);temp_event=0;sw1=0;repeat(2)@(negedge clk);
      check(state==8,"replacement request wins over simultaneous SW1");
      pulse(0);digits(16'h2468);key(4'hA);
      check(state==3,"old temporary password is rejected");
      repeat(4)@(negedge clk);digits(16'h1357);key(4'hA);repeat(2)@(negedge clk);
      check(unlocked,"replacement temporary password unlocks");
      key(4'hA);repeat(2)@(negedge clk);
      pulse(0);digits(16'h1234);key(4'hA);repeat(2)@(negedge clk);
      check(unlocked,"fixed password remains valid with temporary password enabled");
      key(4'hA);repeat(2)@(negedge clk);
      pulse(1); digits(16'h5678); key(4'hA);
      check(state==6 && save_password==16'h5678,"admin save request");
      stored_password=16'h5678; save_success=1; save_done=1;
      @(negedge clk);save_done=0;save_success=0;repeat(2)@(negedge clk);
      check(state==1,"save returns wait");
      pulse(0);
      for(n=0;n<4;n=n+1) begin
        digits(16'h1111);key(4'hA);repeat(4)@(negedge clk);
      end
      check(alarm_active,"fourth error alarms");
      pulse(3);repeat(2)@(negedge clk);check(alarm_active,"KEY3 cannot bypass alarm");
      pulse(1);repeat(2)@(negedge clk);check(alarm_active,"admin entry key cannot clear alarm");
      key(4'hA);repeat(2)@(negedge clk);check(alarm_active,"keypad cannot clear alarm");
      pulse(2);repeat(2)@(negedge clk);
      check(!alarm_active && state==2,"KEY2 starts a fresh input session");
      check(error_count==0,"KEY2 resets the four-attempt window");
      digits(16'h1111);key(4'hA);
      check(state==3 && error_count==1,"first post-alarm error is Err1");
      repeat(4)@(negedge clk);key(4'hC);repeat(2)@(negedge clk);
      check(state==1,"cancel returns wait");
      pulse(0);repeat(1005)@(negedge clk);check(state==1,"locked input timeout");
      test_pass=1;$display("PASS tb_lock_controller");$finish;
    end
endmodule

simulation_waveforms/11_integrated_controller_regression/tb_lock_controller.vcd
$date
   Sun Sep 13 16:25:20 2026
$end

$version
  2023.2
$end

$timescale
  1ps
$end

$scope module tb_lock_controller $end
$var reg 1 U test_pass $end
$var reg 1 V clk $end
$var reg 1 W rst $end
$var reg 1 X init_done $end
$var reg 1 Y flash_fault $end
$var reg 1 Z sw1 $end
$var reg 1 [ admin $end
$var reg 1 \ clear $end
$var reg 1 ] temp_event $end
$var reg 1 ^ key_valid $end
$var reg 4 _ key_code [3:0] $end
$var reg 16 ` stored_password [15:0] $end
$var reg 16 a temporary_password [15:0] $end
$var reg 1 b temporary_valid $end
$var reg 1 c save_done $end
$var reg 1 d save_success $end
$var wire 1 e save_request $end
$var wire 1 f capture_start $end
$var wire 1 g unlocked $end
$var wire 1 h alarm_active $end
$var wire 1 i display_fault $end
$var wire 16 j save_password [15:0] $end
$var wire 16 k entry_digits [15:0] $end
$var wire 4 l state [3:0] $end
$var wire 3 m entry_count [2:0] $end
$var wire 3 n error_count [2:0] $end
$var integer 32 o n [31:0] $end
$scope module dut $end
$var wire 1 ! clk $end
$var wire 1 " rst $end
$var wire 1 # flash_init_done $end
$var wire 16 $ stored_password [15:0] $end
$var wire 1 % flash_fault $end
$var wire 1 & sw1_event $end
$var wire 1 ' admin_event $end
$var wire 1 ( alarm_clear_event $end
$var wire 1 ) temporary_event $end
$var wire 16 * temporary_password [15:0] $end
$var wire 1 + temporary_valid $end
$var wire 1 , key_valid $end
$var wire 4 - key_code [3:0] $end
$var wire 1 . save_done $end
$var wire 1 / save_success $end
$var reg 1 0 save_request $end
$var reg 16 1 save_password [15:0] $end
$var reg 1 2 capture_start $end
$var reg 1 3 unlocked $end
$var reg 1 4 alarm_active $end
$var reg 4 5 state [3:0] $end
$var reg 16 6 entry_digits [15:0] $end
$var reg 3 7 entry_count [2:0] $end
$var reg 3 8 error_count [2:0] $end
$var reg 1 9 display_fault $end
$var reg 4 : next_state [3:0] $end
$var reg 11 ; timer_count [10:0] $end
$var wire 1 < is_digit $end
$var wire 1 = activity $end
$var parameter 0 > CLOCK_HZ [31:0] $end
$var parameter 0 ? LOCK_TIMEOUT_S [31:0] $end
$var parameter 0 @ OPEN_TIMEOUT_S [31:0] $end
$var parameter 0 A ERROR_DISPLAY_MS [31:0] $end
$var parameter 4 B ST_BOOT [3:0] $end
$var parameter 4 C ST_WAIT [3:0] $end
$var parameter 4 D ST_USER [3:0] $end
$var parameter 4 E ST_ERROR [3:0] $end
$var parameter 4 F ST_OPEN [3:0] $end
$var parameter 4 G ST_ADMIN [3:0] $end
$var parameter 4 H ST_SAVE [3:0] $end
$var parameter 4 I ST_ALARM [3:0] $end
$var parameter 4 J ST_TEMP [3:0] $end
$var parameter 0 K LOCK_TICKS [31:0] $end
$var parameter 0 L OPEN_TICKS [31:0] $end
$var parameter 0 M ERROR_TICKS [31:0] $end
$var parameter 0 N MAX_TICKS [31:0] $end
$var parameter 0 O MAX_TICKS2 [31:0] $end
$var parameter 0 P TW [31:0] $end
$upscope $end
$scope task pulse $end
$var integer 32 Q which [31:0] $end
$upscope $end
$scope task key $end
$var reg 4 R code [3:0] $end
$upscope $end
$scope task digits $end
$var reg 16 S value [15:0] $end
$upscope $end
$scope task check $end
$var reg 1 T condition $end
$upscope $end
$upscope $end
$enddefinitions $end

#0
$dumpvars
0!
1"
0#
b1001000110100 $
0%
0&
0'
0(
0)
b0 *
0+
0,
b0 -
0.
0/
x0
bx 1
x2
x3
x4
bx 5
bx 6
bx 7
bx 8
x9
b0 :
bx ;
1<
0=
b1111101000 >
b1 ?
b10 @
b10 A
b0 B
b1 C
b10 D
b11 E
b100 F
b101 G
b110 H
b111 I
b1000 J
b1111101000 K
b11111010000 L
b10 M
b11111010000 N
b11111010000 O
b1011 P
bx Q
bx R
bx S
0T
0U
0V
1W
0X
0Y
0Z
0[
0\
0]
0^
b0 _
b1001000110100 `
b0 a
0b
0c
0d
xe
xf
xg
xh
xi
bx j
bx k
bx l
bx m
bx n
bx o
$end

#5000
1!
00
b1001000110100 1
02
03
04
b0 5
b0 6
b0 7
b0 8
09
b0 ;
1V
0e
0f
0g
0h
0i
b1001000110100 j
b0 k
b0 l
b0 m
b0 n

#10000
0!
0V

#15000
1!
1V

#20000
0!
0V

#25000
1!
1V

#30000
0!
0V

#35000
1!
1V

#40000
0!
0"
1#
b1 :
0V
0W
1X

#45000
1!
b1 5
1V
b1 l

#50000
0!
0V

#55000
1!
1V

#60000
0!
b0 Q
1T
0V

#65000
1!
1V

#70000
0!
1&
b10 :
0V
1Z

#75000
1!
b10 5
1V
b10 l

#80000
0!
0&
b1 R
b1001000110100 S
0V
0Z

#85000
1!
b1 ;
1V

#90000
0!
1,
b1 -
1=
0V
1^
b1 _

#95000
1!
b1 6
b1 7
b0 ;
1V
b1 k
b1 m

#100000
0!
0,
0=
b10 R
0V
0^

#105000
1!
b1 ;
1V

#110000
0!
1,
b10 -
1=
0V
1^
b10 _

#115000
1!
b10010 6
b10 7
b0 ;
1V
b10010 k
b10 m

#120000
0!
0,
0=
b11 R
0V
0^

#125000
1!
b1 ;
1V

#130000
0!
1,
b11 -
1=
0V
1^
b11 _

#135000
1!
b100100011 6
b11 7
b0 ;
1V
b100100011 k
b11 m

#140000
0!
0,
0=
b100 R
0V
0^

#145000
1!
b1 ;
1V

#150000
0!
1,
b100 -
1=
0V
1^
b100 _

#155000
1!
b1001000110100 6
b100 7
b0 ;
1V
b1001000110100 k
b100 m

#160000
0!
0,
0=
b1010 R
0V
0^

#165000
1!
b1 ;
1V

#170000
0!
1,
b1010 -
b100 :
0<
1=
0V
1^
b1010 _

#175000
1!
13
b100 5
b1 :
b0 ;
1V
1g
b100 l

#180000
0!
0,
b100 :
0=
0V
0^

#185000
1!
b1 ;
1V

#190000
0!
0V

#195000
1!
b10 ;
1V

#200000
0!
0V

#205000
1!
b11 ;
1V

#210000
0!
1,
b1 :
1=
0V
1^

#215000
1!
03
b1 5
b0 6
b0 7
b0 ;
1V
0g
b0 k
b1 l
b0 m

#220000
0!
0,
0=
0V
0^

#225000
1!
1V

#230000
0!
0V

#235000
1!
1V

#240000
0!
b10010001101000 *
1+
b11 Q
0V
b10010001101000 a
1b

#245000
1!
1V

#250000
0!
1)
b1000 :
0V
1]

#255000
1!
b1000 5
1V
b1000 l

#260000
0!
0)
0V
0]

#265000
1!
b1 ;
1V

#270000
0!
0V

#275000
1!
b10 ;
1V

#280000
0!
b0 Q
0V

#285000
1!
b11 ;
1V

#290000
0!
1&
b10 :
0V
1Z

#295000
1!
b10 5
b0 ;
1V
b10 l

#300000
0!
0&
b10 R
b10010001101000 S
0V
0Z

#305000
1!
b1 ;
1V

#310000
0!
1,
b10 -
1<
1=
0V
1^
b10 _

#315000
1!
b10 6
b1 7
b0 ;
1V
b10 k
b1 m

#320000
0!
0,
0=
b100 R
0V
0^

#325000
1!
b1 ;
1V

#330000
0!
1,
b100 -
1=
0V
1^
b100 _

#335000
1!
b100100 6
b10 7
b0 ;
1V
b100100 k
b10 m

#340000
0!
0,
0=
b110 R
0V
0^

#345000
1!
b1 ;
1V

#350000
0!
1,
b110 -
1=
0V
1^
b110 _

#355000
1!
b1001000110 6
b11 7
b0 ;
1V
b1001000110 k
b11 m

#360000
0!
0,
0=
b1000 R
0V
0^

#365000
1!
b1 ;
1V

#370000
0!
1,
b1000 -
1=
0V
1^
b1000 _

#375000
1!
b10010001101000 6
b100 7
b0 ;
1V
b10010001101000 k
b100 m

#380000
0!
0,
0=
b1010 R
0V
0^

#385000
1!
b1 ;
1V

#390000
0!
1,
b1010 -
b100 :
0<
1=
0V
1^
b1010 _

#395000
1!
13
b100 5
b1 :
b0 ;
1V
1g
b100 l

#400000
0!
0,
b100 :
0=
0V
0^

#405000
1!
b1 ;
1V

#410000
0!
0V

#415000
1!
b10 ;
1V

#420000
0!
0V

#425000
1!
b11 ;
1V

#430000
0!
1,
b1 :
1=
0V
1^

#435000
1!
03
b1 5
b0 6
b0 7
b0 ;
1V
0g
b0 k
b1 l
b0 m

#440000
0!
0,
0=
0V
0^

#445000
1!
1V

#450000
0!
0V

#455000
1!
1V

#460000
0!
b11 Q
0V

#465000
1!
1V

#470000
0!
1)
b1000 :
0V
1]

#475000
1!
b1000 5
1V
b1000 l

#480000
0!
0)
b1001101010111 *
0V
0]
b1001101010111 a

#485000
1!
b1 ;
1V

#490000
0!
1&
1)
0V
1Z
1]

#495000
1!
b0 ;
1V

#500000
0!
0&
0)
0V
0Z
0]

#505000
1!
b1 ;
1V

#510000
0!
0V

#515000
1!
b10 ;
1V

#520000
0!
b0 Q
0V

#525000
1!
b11 ;
1V

#530000
0!
1&
b10 :
0V
1Z

#535000
1!
b10 5
b0 ;
1V
b10 l

#540000
0!
0&
b10 R
0V
0Z

#545000
1!
b1 ;
1V

#550000
0!
1,
b10 -
1<
1=
0V
1^
b10 _

#555000
1!
b10 6
b1 7
b0 ;
1V
b10 k
b1 m

#560000
0!
0,
0=
b100 R
0V
0^

#565000
1!
b1 ;
1V

#570000
0!
1,
b100 -
1=
0V
1^
b100 _

#575000
1!
b100100 6
b10 7
b0 ;
1V
b100100 k
b10 m

#580000
0!
0,
0=
b110 R
0V
0^

#585000
1!
b1 ;
1V

#590000
0!
1,
b110 -
1=
0V
1^
b110 _

#595000
1!
b1001000110 6
b11 7
b0 ;
1V
b1001000110 k
b11 m

#600000
0!
0,
0=
b1000 R
0V
0^

#605000
1!
b1 ;
1V

#610000
0!
1,
b1000 -
1=
0V
1^
b1000 _

#615000
1!
b10010001101000 6
b100 7
b0 ;
1V
b10010001101000 k
b100 m

#620000
0!
0,
0=
b1010 R
0V
0^

#625000
1!
b1 ;
1V

#630000
0!
1,
b1010 -
b11 :
0<
1=
0V
1^
b1010 _

#635000
1!
b11 5
b1 8
b0 ;
1V
b11 l
b1 n

#640000
0!
0,
0=
0V
0^

#645000
1!
b10 :
b1 ;
1V

#650000
0!
0V

#655000
1!
b10 5
b0 6
b0 7
b0 ;
1V
b0 k
b10 l
b0 m

#660000
0!
0V

#665000
1!
b1 ;
1V

#670000
0!
0V

#675000
1!
b10 ;
1V

#680000
0!
b1 R
b1001101010111 S
0V

#685000
1!
b11 ;
1V

#690000
0!
1,
b1 -
1<
1=
0V
1^
b1 _

#695000
1!
b1 6
b1 7
b0 ;
1V
b1 k
b1 m

#700000
0!
0,
0=
b11 R
0V
0^

#705000
1!
b1 ;
1V

#710000
0!
1,
b11 -
1=
0V
1^
b11 _

#715000
1!
b10011 6
b10 7
b0 ;
1V
b10011 k
b10 m

#720000
0!
0,
0=
b101 R
0V
0^

#725000
1!
b1 ;
1V

#730000
0!
1,
b101 -
1=
0V
1^
b101 _

#735000
1!
b100110101 6
b11 7
b0 ;
1V
b100110101 k
b11 m

#740000
0!
0,
0=
b111 R
0V
0^

#745000
1!
b1 ;
1V

#750000
0!
1,
b111 -
1=
0V
1^
b111 _

#755000
1!
b1001101010111 6
b100 7
b0 ;
1V
b1001101010111 k
b100 m

#760000
0!
0,
0=
b1010 R
0V
0^

#765000
1!
b1 ;
1V

#770000
0!
1,
b1010 -
b100 :
0<
1=
0V
1^
b1010 _

#775000
1!
13
b100 5
b0 8
b1 :
b0 ;
1V
1g
b100 l
b0 n

#780000
0!
0,
b100 :
0=
0V
0^

#785000
1!
b1 ;
1V

#790000
0!
0V

#795000
1!
b10 ;
1V

#800000
0!
0V

#805000
1!
b11 ;
1V

#810000
0!
1,
b1 :
1=
0V
1^

#815000
1!
03
b1 5
b0 6
b0 7
b0 ;
1V
0g
b0 k
b1 l
b0 m

#820000
0!
0,
0=
0V
0^

#825000
1!
1V

#830000
0!
0V

#835000
1!
1V

#840000
0!
0V

#845000
1!
1V

#850000
0!
1&
b10 :
0V
1Z

#855000
1!
b10 5
1V
b10 l

#860000
0!
0&
b1 R
b1001000110100 S
0V
0Z

#865000
1!
b1 ;
1V

#870000
0!
1,
b1 -
1<
1=
0V
1^
b1 _

#875000
1!
b1 6
b1 7
b0 ;
1V
b1 k
b1 m

#880000
0!
0,
0=
b10 R
0V
0^

#885000
1!
b1 ;
1V

#890000
0!
1,
b10 -
1=
0V
1^
b10 _

#895000
1!
b10010 6
b10 7
b0 ;
1V
b10010 k
b10 m

#900000
0!
0,
0=
b11 R
0V
0^

#905000
1!
b1 ;
1V

#910000
0!
1,
b11 -
1=
0V
1^
b11 _

#915000
1!
b100100011 6
b11 7
b0 ;
1V
b100100011 k
b11 m

#920000
0!
0,
0=
b100 R
0V
0^

#925000
1!
b1 ;
1V

#930000
0!
1,
b100 -
1=
0V
1^
b100 _

#935000
1!
b1001000110100 6
b100 7
b0 ;
1V
b1001000110100 k
b100 m

#940000
0!
0,
0=
b1010 R
0V
0^

#945000
1!
b1 ;
1V

#950000
0!
1,
b1010 -
b100 :
0<
1=
0V
1^
b1010 _

#955000
1!
13
b100 5
b1 :
b0 ;
1V
1g
b100 l

#960000
0!
0,
b100 :
0=
0V
0^

#965000
1!
b1 ;
1V

#970000
0!
0V

#975000
1!
b10 ;
1V

#980000
0!
0V

#985000
1!
b11 ;
1V

#990000
0!
1,
b1 :
1=
0V
1^

#995000
1!
03
b1 5
b0 6
b0 7
b0 ;
1V
0g
b0 k
b1 l
b0 m

#1000000
0!
0,
0=
0V
0^

#1005000
1!
1V

#1010000
0!
0V

#1015000
1!
1V

#1020000
0!
b1 Q
0V

#1025000
1!
1V

#1030000
0!
1'
b101 :
0V
1[

#1035000
1!
b101 5
1V
b101 l

#1040000
0!
0'
b101 R
b101011001111000 S
0V
0[

#1045000
1!
b1 ;
1V

#1050000
0!
1,
b101 -
1<
1=
0V
1^
b101 _

#1055000
1!
b101 6
b1 7
b0 ;
1V
b101 k
b1 m

#1060000
0!
0,
0=
b110 R
0V
0^

#1065000
1!
b1 ;
1V

#1070000
0!
1,
b110 -
1=
0V
1^
b110 _

#1075000
1!
b1010110 6
b10 7
b0 ;
1V
b1010110 k
b10 m

#1080000
0!
0,
0=
b111 R
0V
0^

#1085000
1!
b1 ;
1V

#1090000
0!
1,
b111 -
1=
0V
1^
b111 _

#1095000
1!
b10101100111 6
b11 7
b0 ;
1V
b10101100111 k
b11 m

#1100000
0!
0,
0=
b1000 R
0V
0^

#1105000
1!
b1 ;
1V

#1110000
0!
1,
b1000 -
1=
0V
1^
b1000 _

#1115000
1!
b101011001111000 6
b100 7
b0 ;
1V
b101011001111000 k
b100 m

#1120000
0!
0,
0=
b1010 R
0V
0^

#1125000
1!
b1 ;
1V

#1130000
0!
1,
b1010 -
b110 :
0<
1=
0V
1^
b1010 _

#1135000
1!
10
b101011001111000 1
b110 5
b0 ;
1V
1e
b101011001111000 j
b110 l

#1140000
0!
b101011001111000 $
0,
1.
1/
b1 :
0=
0V
0^
b101011001111000 `
1c
1d

#1145000
1!
00
b1 5
b0 6
b0 7
1V
0e
b0 k
b1 l
b0 m

#1150000
0!
0.
0/
0V
0c
0d

#1155000
1!
1V

#1160000
0!
0V

#1165000
1!
1V

#1170000
0!
b0 Q
0V

#1175000
1!
1V

#1180000
0!
1&
b10 :
0V
1Z

#1185000
1!
b10 5
1V
b10 l

#1190000
0!
0&
b1 R
b1000100010001 S
0V
0Z
b0 o

#1195000
1!
b1 ;
1V

#1200000
0!
1,
b1 -
1<
1=
0V
1^
b1 _

#1205000
1!
b1 6
b1 7
b0 ;
1V
b1 k
b1 m

#1210000
0!
0,
0=
0V
0^

#1215000
1!
b1 ;
1V

#1220000
0!
1,
1=
0V
1^

#1225000
1!
b10001 6
b10 7
b0 ;
1V
b10001 k
b10 m

#1230000
0!
0,
0=
0V
0^

#1235000
1!
b1 ;
1V

#1240000
0!
1,
1=
0V
1^

#1245000
1!
b100010001 6
b11 7
b0 ;
1V
b100010001 k
b11 m

#1250000
0!
0,
0=
0V
0^

#1255000
1!
b1 ;
1V

#1260000
0!
1,
1=
0V
1^

#1265000
1!
b1000100010001 6
b100 7
b0 ;
1V
b1000100010001 k
b100 m

#1270000
0!
0,
0=
b1010 R
0V
0^

#1275000
1!
b1 ;
1V

#1280000
0!
1,
b1010 -
b11 :
0<
1=
0V
1^
b1010 _

#1285000
1!
b11 5
b1 8
b0 ;
1V
b11 l
b1 n

#1290000
0!
0,
0=
0V
0^

#1295000
1!
b10 :
b1 ;
1V

#1300000
0!
0V

#1305000
1!
b10 5
b0 6
b0 7
b0 ;
1V
b0 k
b10 l
b0 m

#1310000
0!
0V

#1315000
1!
b1 ;
1V

#1320000
0!
0V

#1325000
1!
b10 ;
1V

#1330000
0!
b1 R
0V
b1 o

#1335000
1!
b11 ;
1V

#1340000
0!
1,
b1 -
1<
1=
0V
1^
b1 _

#1345000
1!
b1 6
b1 7
b0 ;
1V
b1 k
b1 m

#1350000
0!
0,
0=
0V
0^

#1355000
1!
b1 ;
1V

#1360000
0!
1,
1=
0V
1^

#1365000
1!
b10001 6
b10 7
b0 ;
1V
b10001 k
b10 m

#1370000
0!
0,
0=
0V
0^

#1375000
1!
b1 ;
1V

#1380000
0!
1,
1=
0V
1^

#1385000
1!
b100010001 6
b11 7
b0 ;
1V
b100010001 k
b11 m

#1390000
0!
0,
0=
0V
0^

#1395000
1!
b1 ;
1V

#1400000
0!
1,
1=
0V
1^

#1405000
1!
b1000100010001 6
b100 7
b0 ;
1V
b1000100010001 k
b100 m

#1410000
0!
0,
0=
b1010 R
0V
0^

#1415000
1!
b1 ;
1V

#1420000
0!
1,
b1010 -
b11 :
0<
1=
0V
1^
b1010 _

#1425000
1!
b11 5
b10 8
b0 ;
1V
b11 l
b10 n

#1430000
0!
0,
0=
0V
0^

#1435000
1!
b10 :
b1 ;
1V

#1440000
0!
0V

#1445000
1!
b10 5
b0 6
b0 7
b0 ;
1V
b0 k
b10 l
b0 m

#1450000
0!
0V

#1455000
1!
b1 ;
1V

#1460000
0!
0V

#1465000
1!
b10 ;
1V

#1470000
0!
b1 R
0V
b10 o

#1475000
1!
b11 ;
1V

#1480000
0!
1,
b1 -
1<
1=
0V
1^
b1 _

#1485000
1!
b1 6
b1 7
b0 ;
1V
b1 k
b1 m

#1490000
0!
0,
0=
0V
0^

