password_lock_system/rtl/lock_controller.v
`timescale 1ns/1ps

module lock_controller #(
    parameter integer CLOCK_HZ         = 50_000_000,
    parameter integer LOCK_TIMEOUT_S   = 8,
    parameter integer OPEN_TIMEOUT_S   = 16,
    parameter integer ERROR_DISPLAY_MS = 1000
) (
    input  wire        clk,
    input  wire        rst,
    input  wire        flash_init_done,
    input  wire [15:0] stored_password,
    input  wire        flash_fault,
    input  wire        sw1_event,
    input  wire        admin_event,
    input  wire        alarm_clear_event,
    input  wire        temporary_event,
    input  wire [15:0] temporary_password,
    input  wire        temporary_valid,
    input  wire        key_valid,
    input  wire [3:0]  key_code,
    input  wire        save_done,
    input  wire        save_success,
    output reg         save_request,
    output reg [15:0]  save_password,
    output reg         capture_start,
    output reg         unlocked,
    output reg         alarm_active,
    output reg [3:0]   state,
    output reg [15:0]  entry_digits,
    output reg [2:0]   entry_count,
    output reg [2:0]   error_count,
    output reg         display_fault
);
    localparam [3:0] ST_BOOT  = 4'd0,
                     ST_WAIT  = 4'd1,
                     ST_USER  = 4'd2,
                     ST_ERROR = 4'd3,
                     ST_OPEN  = 4'd4,
                     ST_ADMIN = 4'd5,
                     ST_SAVE  = 4'd6,
                     ST_ALARM = 4'd7,
                     ST_TEMP  = 4'd8;
    localparam integer LOCK_TICKS  = CLOCK_HZ * LOCK_TIMEOUT_S;
    localparam integer OPEN_TICKS  = CLOCK_HZ * OPEN_TIMEOUT_S;
    localparam integer ERROR_TICKS = (CLOCK_HZ / 1000) * ERROR_DISPLAY_MS;
    localparam integer MAX_TICKS = (OPEN_TICKS > LOCK_TICKS) ? OPEN_TICKS : LOCK_TICKS;
    localparam integer MAX_TICKS2 = (MAX_TICKS > ERROR_TICKS) ? MAX_TICKS : ERROR_TICKS;
    localparam integer TW = (MAX_TICKS2 <= 2) ? 1 : $clog2(MAX_TICKS2 + 1);

    reg [3:0] next_state;
    reg [TW-1:0] timer_count;
    wire is_digit = (key_code <= 4'd9);
    wire activity = key_valid && (is_digit || key_code == 4'hA ||
                                  key_code == 4'hB || key_code == 4'hC);

    always @(*) begin
        next_state = state;
        case (state)
            ST_BOOT:  if (flash_init_done) next_state = ST_WAIT;
            ST_WAIT:  if (temporary_event) next_state = ST_TEMP;
                      else if (admin_event) next_state = ST_ADMIN;
                      else if (sw1_event) next_state = ST_USER;
            ST_USER:  if (key_valid && key_code == 4'hC) next_state = ST_WAIT;
                      else if ((timer_count >= LOCK_TICKS-1) && !activity) next_state = ST_WAIT;
                      else if (key_valid && key_code == 4'hA && entry_count == 3'd4) begin
                          if (entry_digits == stored_password ||
                              (temporary_valid && entry_digits == temporary_password))
                              next_state = ST_OPEN;
                          else if (error_count == 3'd3) next_state = ST_ALARM;
                          else next_state = ST_ERROR;
                      end
            ST_ERROR: if (timer_count >= ERROR_TICKS-1) next_state = ST_USER;
            ST_OPEN:  if ((key_valid && key_code == 4'hA) ||
                          (timer_count >= OPEN_TICKS-1)) next_state = ST_WAIT;
                      else if (admin_event) next_state = ST_ADMIN;
            ST_ADMIN: if (key_valid && key_code == 4'hC) next_state = ST_WAIT;
                      else if ((timer_count >= LOCK_TICKS-1) && !activity) next_state = ST_WAIT;
                      else if (key_valid && key_code == 4'hA && entry_count == 3'd4)
                          next_state = ST_SAVE;
            ST_SAVE:  if (save_done) next_state = ST_WAIT;
            // A replacement request wins over timeout or simultaneous input,
            // so the new password always remains visible for a full interval.
            ST_TEMP:  if (temporary_event) next_state = ST_TEMP;
                      else if (sw1_event) next_state = ST_USER;
                      else if (key_valid && (key_code == 4'hA || key_code == 4'hC))
                          next_state = ST_WAIT;
                      else if (timer_count >= LOCK_TICKS-1) next_state = ST_WAIT;
            // KEY2 completes the administrator's alarm handling and starts a
            // clean input session.  No SW1 toggle is required afterward.
            ST_ALARM: if (alarm_clear_event) next_state = ST_USER;
            default: next_state = ST_BOOT;
        endcase
    end

    always @(posedge clk) begin
        if (rst) begin
            state          <= ST_BOOT;
            timer_count    <= {TW{1'b0}};
            entry_digits   <= 16'h0000;
            entry_count    <= 3'd0;
            error_count    <= 3'd0;
            save_request   <= 1'b0;
            save_password  <= 16'h1234;
            capture_start  <= 1'b0;
            display_fault  <= 1'b0;
        end else begin
            state         <= next_state;
            save_request  <= 1'b0;
            capture_start <= 1'b0;

            if (state != next_state) begin
                timer_count <= {TW{1'b0}};
                if (next_state == ST_USER || next_state == ST_ADMIN ||
                    next_state == ST_WAIT) begin
                    entry_digits <= 16'h0000;
                    entry_count  <= 3'd0;
                end
                if (next_state == ST_OPEN)
                    error_count <= 3'd0;
                if (next_state == ST_ERROR)
                    error_count <= error_count + 1'b1;
                if (next_state == ST_ALARM) begin
                    error_count   <= 3'd4;
                    capture_start <= 1'b1;
                end
                // An acknowledged alarm starts a new four-attempt window.
                // Without this reset the three-bit counter would display
                // Err5..Err7 and wrap, which is not a valid attempt policy.
                if (state == ST_ALARM && alarm_clear_event)
                    error_count <= 3'd0;
                if (next_state == ST_SAVE) begin
                    save_password <= entry_digits;
                    save_request  <= 1'b1;
                end
                if (state == ST_SAVE && next_state == ST_WAIT)
                    display_fault <= ~save_success;
            end else begin
                if ((activity || temporary_event) &&
                    (state == ST_USER || state == ST_ADMIN || state == ST_OPEN || state == ST_TEMP))
                    timer_count <= {TW{1'b0}};
                else if (state == ST_USER || state == ST_ADMIN || state == ST_OPEN ||
                         state == ST_ERROR || state == ST_TEMP)
                    timer_count <= timer_count + 1'b1;

                if ((state == ST_USER || state == ST_ADMIN) && key_valid) begin
                    if (is_digit && entry_count < 3'd4) begin
                        entry_digits <= {entry_digits[11:0], key_code};
                        entry_count  <= entry_count + 1'b1;
                    end else if (key_code == 4'hB && entry_count != 0) begin
                        entry_digits <= {4'h0, entry_digits[15:4]};
                        entry_count  <= entry_count - 1'b1;
                    end
                end
            end

            // Starting a new user/admin/temporary-password operation clears a
            // previous save-error indication even when that same event also
            // causes a state transition on this clock edge.
            if (display_fault && (sw1_event || admin_event || temporary_event))
                display_fault <= 1'b0;
            if (flash_fault)
                display_fault <= 1'b1;
        end
    end

    always @(*) begin
        unlocked     = (state == ST_OPEN);
        alarm_active = (state == ST_ALARM);
    end
endmodule

password_lock_system/sim/tb_basic_entry_timeout.sv
`timescale 1ns/1ps

module tb_basic_entry_timeout;
    localparam [3:0] ST_WAIT=4'd1, ST_USER=4'd2, ST_OPEN=4'd4;
    reg test_pass=0;
    reg clk=0,rst=1,init_done=0,sw1=0,key_valid=0;
    reg [3:0] key_code=0;
    reg [7:0] scenario=0;
    wire unlocked,alarm_active;
    wire [3:0] state;
    wire [15:0] entry_digits;
    wire [2:0] entry_count,error_count;

    always #5 clk=~clk;
    lock_controller #(.CLOCK_HZ(1000),.LOCK_TIMEOUT_S(1),.OPEN_TIMEOUT_S(2),.ERROR_DISPLAY_MS(2)) dut(
        .clk(clk),.rst(rst),.flash_init_done(init_done),.stored_password(16'h1234),
        .flash_fault(1'b0),.sw1_event(sw1),.admin_event(1'b0),.alarm_clear_event(1'b0),
        .temporary_event(1'b0),.temporary_password(16'h0000),.temporary_valid(1'b0),
        .key_valid(key_valid),.key_code(key_code),.save_done(1'b0),.save_success(1'b0),
        .save_request(),.save_password(),.capture_start(),.unlocked(unlocked),
        .alarm_active(alarm_active),.state(state),.entry_digits(entry_digits),
        .entry_count(entry_count),.error_count(error_count),.display_fault());

    task pulse_sw1; begin @(negedge clk);sw1=1;@(negedge clk);sw1=0;end endtask
    task key(input [3:0] code); begin
        @(negedge clk);key_code=code;key_valid=1;
        @(negedge clk);key_valid=0;
    end endtask
    task digits(input [15:0] value); begin
        key(value[15:12]);key(value[11:8]);key(value[7:4]);key(value[3:0]);
    end endtask
    task check(input bit ok,input string message); if(!ok)$fatal(1,"FAIL: %s",message); endtask

    initial begin
        scenario=1; repeat(4)@(negedge clk);rst=0;init_done=1;repeat(2)@(negedge clk);
        check(state==ST_WAIT,"boot/init did not reach PASS wait state");

        scenario=2; pulse_sw1();key(1);key(2);key(4'hA);
        check(state==ST_USER && entry_count==2,"incomplete confirm must be ignored");
        key(4'hB);check(entry_count==1 && entry_digits==16'h0001,"backspace failed");
        key(2);key(3);key(4);key(9);
        check(entry_count==4 && entry_digits==16'h1234,"four-digit limit failed");

        scenario=3;key(4'hA);repeat(2)@(negedge clk);
        check(state==ST_OPEN && unlocked,"1234 did not unlock");
        repeat(2005)@(negedge clk);
        check(state==ST_WAIT && !unlocked,"16-second-equivalent open timeout failed");

        scenario=4;pulse_sw1();repeat(1005)@(negedge clk);
        check(state==ST_WAIT,"8-second-equivalent input timeout failed");

        scenario=5;pulse_sw1();digits(16'h1234);key(4'hA);repeat(2)@(negedge clk);
        key(4'hA);repeat(2)@(negedge clk);
        check(state==ST_WAIT,"A did not lock immediately from OPEN");
        test_pass=1;$display("PASS tb_basic_entry_timeout");$finish;
    end
endmodule

simulation_waveforms/01_basic_entry_timeout/tb_basic_entry_timeout.vcd
$date
   Tue Sep  8 16:52:40 2026
$end

$version
  2023.2
$end

$timescale
  1ps
$end

$scope module tb_basic_entry_timeout $end
$var reg 1 N test_pass $end
$var reg 1 O clk $end
$var reg 1 P rst $end
$var reg 1 Q init_done $end
$var reg 1 R sw1 $end
$var reg 1 S key_valid $end
$var reg 4 T key_code [3:0] $end
$var reg 8 U scenario [7:0] $end
$var wire 1 V unlocked $end
$var wire 1 W alarm_active $end
$var wire 4 X state [3:0] $end
$var wire 16 Y entry_digits [15:0] $end
$var wire 3 Z entry_count [2:0] $end
$var wire 3 [ error_count [2:0] $end
$var parameter 4 \ ST_WAIT [3:0] $end
$var parameter 4 ] ST_USER [3:0] $end
$var parameter 4 ^ ST_OPEN [3:0] $end
$scope module dut $end
$var wire 1 ! clk $end
$var wire 1 " rst $end
$var wire 1 # flash_init_done $end
$var wire 16 $ stored_password [15:0] $end
$var wire 1 % flash_fault $end
$var wire 1 & sw1_event $end
$var wire 1 % admin_event $end
$var wire 1 % alarm_clear_event $end
$var wire 1 % temporary_event $end
$var wire 16 ' temporary_password [15:0] $end
$var wire 1 % temporary_valid $end
$var wire 1 ( key_valid $end
$var wire 4 ) key_code [3:0] $end
$var wire 1 % save_done $end
$var wire 1 % save_success $end
$var reg 1 * save_request $end
$var reg 16 + save_password [15:0] $end
$var reg 1 , capture_start $end
$var reg 1 - unlocked $end
$var reg 1 . alarm_active $end
$var reg 4 / state [3:0] $end
$var reg 16 0 entry_digits [15:0] $end
$var reg 3 1 entry_count [2:0] $end
$var reg 3 2 error_count [2:0] $end
$var reg 1 3 display_fault $end
$var reg 4 4 next_state [3:0] $end
$var reg 11 5 timer_count [10:0] $end
$var wire 1 6 is_digit $end
$var wire 1 7 activity $end
$var parameter 0 8 CLOCK_HZ [31:0] $end
$var parameter 0 9 LOCK_TIMEOUT_S [31:0] $end
$var parameter 0 : OPEN_TIMEOUT_S [31:0] $end
$var parameter 0 ; ERROR_DISPLAY_MS [31:0] $end
$var parameter 4 < ST_BOOT [3:0] $end
$var parameter 4 = ST_WAIT [3:0] $end
$var parameter 4 > ST_USER [3:0] $end
$var parameter 4 ? ST_ERROR [3:0] $end
$var parameter 4 @ ST_OPEN [3:0] $end
$var parameter 4 A ST_ADMIN [3:0] $end
$var parameter 4 B ST_SAVE [3:0] $end
$var parameter 4 C ST_ALARM [3:0] $end
$var parameter 4 D ST_TEMP [3:0] $end
$var parameter 0 E LOCK_TICKS [31:0] $end
$var parameter 0 F OPEN_TICKS [31:0] $end
$var parameter 0 G ERROR_TICKS [31:0] $end
$var parameter 0 H MAX_TICKS [31:0] $end
$var parameter 0 I MAX_TICKS2 [31:0] $end
$var parameter 0 J TW [31:0] $end
$upscope $end
$scope task key $end
$var reg 4 K code [3:0] $end
$upscope $end
$scope task digits $end
$var reg 16 L value [15:0] $end
$upscope $end
$scope task check $end
$var reg 1 M ok $end
$upscope $end
$upscope $end
$enddefinitions $end

#0
$dumpvars
0!
1"
0#
b1001000110100 $
0%
0&
b0 '
0(
b0 )
x*
bx +
x,
x-
x.
bx /
bx 0
bx 1
bx 2
x3
b0 4
bx 5
16
07
b1111101000 8
b1 9
b10 :
b10 ;
b0 <
b1 =
b10 >
b11 ?
b100 @
b101 A
b110 B
b111 C
b1000 D
b1111101000 E
b11111010000 F
b10 G
b11111010000 H
b11111010000 I
b1011 J
bx K
bx L
0M
0N
0O
1P
0Q
0R
0S
b0 T
b1 U
xV
xW
bx X
bx Y
bx Z
bx [
b1 \
b10 ]
b100 ^
$end

#5000
1!
0*
b1001000110100 +
0,
0-
0.
b0 /
b0 0
b0 1
b0 2
03
b0 5
1O
0V
0W
b0 X
b0 Y
b0 Z
b0 [

#10000
0!
0O

#15000
1!
1O

#20000
0!
0O

#25000
1!
1O

#30000
0!
0O

#35000
1!
1O

#40000
0!
0"
1#
b1 4
0O
0P
1Q

#45000
1!
b1 /
1O
b1 X

#50000
0!
0O

#55000
1!
1O

#60000
0!
1M
0O
b10 U

#65000
1!
1O

#70000
0!
1&
b10 4
0O
1R

#75000
1!
b10 /
1O
b10 X

#80000
0!
0&
b1 K
0O
0R

#85000
1!
b1 5
1O

#90000
0!
1(
b1 )
17
0O
1S
b1 T

#95000
1!
b1 0
b1 1
b0 5
1O
b1 Y
b1 Z

#100000
0!
0(
07
b10 K
0O
0S

#105000
1!
b1 5
1O

#110000
0!
1(
b10 )
17
0O
1S
b10 T

#115000
1!
b10010 0
b10 1
b0 5
1O
b10010 Y
b10 Z

#120000
0!
0(
07
b1010 K
0O
0S

#125000
1!
b1 5
1O

#130000
0!
1(
b1010 )
06
17
0O
1S
b1010 T

#135000
1!
b0 5
1O

#140000
0!
0(
07
b1011 K
0O
0S

#145000
1!
b1 5
1O

#150000
0!
1(
b1011 )
17
0O
1S
b1011 T

#155000
1!
b1 0
b1 1
b0 5
1O
b1 Y
b1 Z

#160000
0!
0(
07
b10 K
0O
0S

#165000
1!
b1 5
1O

#170000
0!
1(
b10 )
16
17
0O
1S
b10 T

#175000
1!
b10010 0
b10 1
b0 5
1O
b10010 Y
b10 Z

#180000
0!
0(
07
b11 K
0O
0S

#185000
1!
b1 5
1O

#190000
0!
1(
b11 )
17
0O
1S
b11 T

#195000
1!
b100100011 0
b11 1
b0 5
1O
b100100011 Y
b11 Z

#200000
0!
0(
07
b100 K
0O
0S

#205000
1!
b1 5
1O

#210000
0!
1(
b100 )
17
0O
1S
b100 T

#215000
1!
b1001000110100 0
b100 1
b0 5
1O
b1001000110100 Y
b100 Z

#220000
0!
0(
07
b1001 K
0O
0S

#225000
1!
b1 5
1O

#230000
0!
1(
b1001 )
17
0O
1S
b1001 T

#235000
1!
b0 5
1O

#240000
0!
0(
07
b1010 K
0O
0S
b11 U

#245000
1!
b1 5
1O

#250000
0!
1(
b1010 )
b100 4
06
17
0O
1S
b1010 T

#255000
1!
1-
b100 /
b1 4
b0 5
1O
1V
b100 X

#260000
0!
0(
b100 4
07
0O
0S

#265000
1!
b1 5
1O

#270000
0!
0O

#275000
1!
b10 5
1O

#280000
0!
0O

#285000
1!
b11 5
1O

#290000
0!
0O

#295000
1!
b100 5
1O

#300000
0!
0O

#305000
1!
b101 5
1O

#310000
0!
0O

#315000
1!
b110 5
1O

#320000
0!
0O

#325000
1!
b111 5
1O

#330000
0!
0O

#335000
1!
b1000 5
1O

#340000
0!
0O

#345000
1!
b1001 5
1O

#350000
0!
0O

#355000
1!
b1010 5
1O

#360000
0!
0O

#365000
1!
b1011 5
1O

#370000
0!
0O

#375000
1!
b1100 5
1O

#380000
0!
0O

#385000
1!
b1101 5
1O

#390000
0!
0O

#395000
1!
b1110 5
1O

#400000
0!
0O

#405000
1!
b1111 5
1O

#410000
0!
0O

#415000
1!
b10000 5
1O

#420000
0!
0O

#425000
1!
b10001 5
1O

#430000
0!
0O

#435000
1!
b10010 5
1O

#440000
0!
0O

#445000
1!
b10011 5
1O

#450000
0!
0O

#455000
1!
b10100 5
1O

#460000
0!
0O

#465000
1!
b10101 5
1O

#470000
0!
0O

#475000
1!
b10110 5
1O

#480000
0!
0O

#485000
1!
b10111 5
1O

#490000
0!
0O

#495000
1!
b11000 5
1O

#500000
0!
0O

#505000
1!
b11001 5
1O

#510000
0!
0O

#515000
1!
b11010 5
1O

#520000
0!
0O

#525000
1!
b11011 5
1O

#530000
0!
0O

#535000
1!
b11100 5
1O

#540000
0!
0O

#545000
1!
b11101 5
1O

#550000
0!
0O

#555000
1!
b11110 5
1O

#560000
0!
0O

#565000
1!
b11111 5
1O

#570000
0!
0O

#575000
1!
b100000 5
1O

#580000
0!
0O

#585000
1!
b100001 5
1O

#590000
0!
0O

#595000
1!
b100010 5
1O

#600000
0!
0O

#605000
1!
b100011 5
1O

#610000
0!
0O

#615000
1!
b100100 5
1O

#620000
0!
0O

#625000
1!
b100101 5
1O

#630000
0!
0O

#635000
1!
b100110 5
1O

#640000
0!
0O

#645000
1!
b100111 5
1O

#650000
0!
0O

#655000
1!
b101000 5
1O

#660000
0!
0O

#665000
1!
b101001 5
1O

#670000
0!
0O

#675000
1!
b101010 5
1O

#680000
0!
0O

#685000
1!
b101011 5
1O

#690000
0!
0O

#695000
1!
b101100 5
1O

#700000
0!
0O

#705000
1!
b101101 5
1O

#710000
0!
0O

#715000
1!
b101110 5
1O

#720000
0!
0O

#725000
1!
b101111 5
1O

#730000
0!
0O

#735000
1!
b110000 5
1O

#740000
0!
0O

#745000
1!
b110001 5
1O

#750000
0!
0O

#755000
1!
b110010 5
1O

#760000
0!
0O

#765000
1!
b110011 5
1O

#770000
0!
0O

#775000
1!
b110100 5
1O

#780000
0!
0O

#785000
1!
b110101 5
1O

#790000
0!
0O

#795000
1!
b110110 5
1O

#800000
0!
0O

#805000
1!
b110111 5
1O

#810000
0!
0O

#815000
1!
b111000 5
1O

#820000
0!
0O

#825000
1!
b111001 5
1O

#830000
0!
0O

#835000
1!
b111010 5
1O

#840000
0!
0O

#845000
1!
b111011 5
1O

#850000
0!
0O

#855000
1!
b111100 5
1O

#860000
0!
0O

#865000
1!
b111101 5
1O

#870000
0!
0O

#875000
1!
b111110 5
1O

#880000
0!
0O

#885000
1!
b111111 5
1O

#890000
0!
0O

#895000
1!
b1000000 5
1O

#900000
0!
0O

#905000
1!
b1000001 5
1O

#910000
0!
0O

#915000
1!
b1000010 5
1O

#920000
0!
0O

#925000
1!
b1000011 5
1O

#930000
0!
0O

#935000
1!
b1000100 5
1O

#940000
0!
0O

#945000
1!
b1000101 5
1O

#950000
0!
0O

#955000
1!
b1000110 5
1O

#960000
0!
0O

#965000
1!
b1000111 5
1O

#970000
0!
0O

#975000
1!
b1001000 5
1O

#980000
0!
0O

#985000
1!
b1001001 5
1O

#990000
0!
0O

#995000
1!
b1001010 5
1O

#1000000
0!
0O

#1005000
1!
b1001011 5
1O

#1010000
0!
0O

#1015000
1!
b1001100 5
1O

#1020000
0!
0O

#1025000
1!
b1001101 5
1O

#1030000
0!
0O

#1035000
1!
b1001110 5
1O

#1040000
0!
0O

#1045000
1!
b1001111 5
1O

#1050000
0!
0O

#1055000
1!
b1010000 5
1O

#1060000
0!
0O

#1065000
1!
b1010001 5
1O

#1070000
0!
0O

#1075000
1!
b1010010 5
1O

#1080000
0!
0O

#1085000
1!
b1010011 5
1O

#1090000
0!
0O

#1095000
1!
b1010100 5
1O

#1100000
0!
0O

#1105000
1!
b1010101 5
1O

#1110000
0!
0O

#1115000
1!
b1010110 5
1O

#1120000
0!
0O

#1125000
1!
b1010111 5
1O

#1130000
0!
0O

#1135000
1!
b1011000 5
1O

#1140000
0!
0O

#1145000
1!
b1011001 5
1O

#1150000
0!
0O

#1155000
1!
b1011010 5
1O

#1160000
0!
0O

#1165000
1!
b1011011 5
1O

#1170000
0!
0O

#1175000
1!
b1011100 5
1O

#1180000
0!
0O

#1185000
1!
b1011101 5
1O

#1190000
0!
0O

#1195000
1!
b1011110 5
1O

#1200000
0!
0O

#1205000
1!
b1011111 5
1O

#1210000
0!
0O

#1215000
1!
b1100000 5
1O

#1220000
0!
0O

#1225000
1!
b1100001 5
1O

#1230000
0!
0O

#1235000
1!
b1100010 5
1O

#1240000
0!
0O

#1245000
1!
b1100011 5
1O

#1250000
0!
0O

#1255000
1!
b1100100 5
1O

#1260000
0!
0O

#1265000
1!
b1100101 5
1O

#1270000
0!
0O

#1275000
1!
b1100110 5
1O

#1280000
0!
0O

#1285000
1!
b1100111 5
1O

#1290000
0!
0O

#1295000
1!
b1101000 5
1O

#1300000
0!
0O

#1305000
1!
b1101001 5
1O

#1310000
0!
0O

#1315000
1!
b1101010 5
1O

#1320000
0!
0O

#1325000
1!
b1101011 5
1O

#1330000
0!
0O

#1335000
1!
b1101100 5
1O

#1340000
0!
0O

#1345000
1!
b1101101 5
1O

#1350000
0!
0O

#1355000
1!
b1101110 5
1O

#1360000
0!
0O

#1365000
1!
b1101111 5
1O

#1370000
0!
0O

#1375000
1!
b1110000 5
1O

#1380000
0!
0O

#1385000
1!
b1110001 5
1O

#1390000
0!
0O

#1395000
1!
b1110010 5
1O

#1400000
0!
0O

#1405000
1!
b1110011 5
1O

#1410000
0!
0O

#1415000
1!
b1110100 5
1O

#1420000
0!
0O

#1425000
1!
b1110101 5
1O

#1430000
0!
0O

#1435000
1!
b1110110 5
1O

#1440000
0!
0O

#1445000
1!
b1110111 5
1O

#1450000
0!
0O

#1455000
1!
b1111000 5
1O

#1460000
0!
0O

#1465000
1!
b1111001 5
1O

#1470000
0!
0O

#1475000
1!
b1111010 5
1O

#1480000
0!
0O

#1485000
1!
b1111011 5
1O

#1490000
0!
0O

#1495000
1!
b1111100 5
1O

#1500000
0!
0O

#1505000
1!
b1111101 5
1O

#1510000
0!
0O

#1515000
1!
b1111110 5
1O

#1520000
0!
0O

#1525000
1!
b1111111 5
1O

#1530000
0!
0O

#1535000
1!
b10000000 5
1O

#1540000
0!
0O

#1545000
1!
b10000001 5
1O

#1550000
0!
0O

#1555000
1!
b10000010 5
1O

#1560000
0!
0O

#1565000
1!
b10000011 5
1O

#1570000
0!
0O

#1575000
1!
b10000100 5
1O

#1580000
0!
0O

#1585000
1!
b10000101 5
1O

#1590000
0!
0O

#1595000
1!
b10000110 5
1O

#1600000
0!
0O

#1605000
1!
b10000111 5
1O

#1610000
0!
0O

#1615000
1!
b10001000 5
1O

#1620000
0!
0O

#1625000
1!
b10001001 5
1O

#1630000
0!
0O

#1635000
1!
b10001010 5
1O

#1640000
0!
0O

#1645000
1!
b10001011 5
1O

#1650000
0!
0O

#1655000
1!
b10001100 5
1O

#1660000
0!
0O

#1665000
1!
b10001101 5
1O

#1670000
0!
0O

#1675000
1!
b10001110 5
1O

#1680000
0!
0O

#1685000
1!
b10001111 5
1O

#1690000
0!
0O

#1695000
1!
b10010000 5
1O

#1700000
0!
0O

#1705000
1!
b10010001 5
1O

#1710000
0!
0O

#1715000
1!
b10010010 5
1O

#1720000
0!
0O

#1725000
1!
b10010011 5
1O

#1730000
0!
0O

#1735000
1!
b10010100 5
1O

#1740000
0!
0O

#1745000
1!
b10010101 5
1O

#1750000
0!
0O

#1755000
1!
b10010110 5
1O

#1760000
0!
0O

#1765000
1!
b10010111 5
1O

#1770000
0!
0O

#1775000
1!
b10011000 5
1O

#1780000
0!
0O

#1785000
1!
b10011001 5
1O

#1790000
0!
0O

#1795000
1!
b10011010 5
1O

#1800000
0!
0O

#1805000
1!
b10011011 5
1O

#1810000
0!
0O

#1815000
1!
b10011100 5
1O

#1820000
0!
0O

#1825000
1!
b10011101 5
1O

#1830000
0!
0O

#1835000
1!
b10011110 5
1O

#1840000
0!
0O

#1845000
1!
b10011111 5
1O

#1850000
0!
0O

#1855000
1!
b10100000 5
1O

#1860000
0!
0O

#1865000
1!
b10100001 5
1O

#1870000
0!
0O

#1875000
1!
b10100010 5
1O

#1880000
0!
0O

#1885000
1!
b10100011 5
1O

#1890000
0!
0O

#1895000
1!
b10100100 5
1O

#1900000
0!
0O

#1905000
1!
b10100101 5
1O

#1910000
0!
0O

#1915000
1!
b10100110 5
1O

#1920000
0!
0O

#1925000
1!
b10100111 5
1O

#1930000
0!
0O

#1935000
1!
b10101000 5
1O

#1940000
0!
0O

#1945000
1!
b10101001 5
1O

#1950000
0!
0O

#1955000
1!
b10101010 5
1O

#1960000
0!
0O

#1965000
1!
b10101011 5
1O

#1970000
0!
0O

#1975000
1!
b10101100 5
1O

#1980000
0!
0O

#1985000
1!
b10101101 5
1O

#1990000
0!
0O

#1995000
1!
b10101110 5
1O

#2000000
0!
0O

#2005000
1!
b10101111 5
1O

#2010000
0!
0O

#2015000
1!
b10110000 5
1O

#2020000
0!
0O

#2025000
1!
b10110001 5
1O

#2030000
0!
0O

#2035000
1!
b10110010 5
1O

#2040000
0!
0O

#2045000
1!
b10110011 5
1O

#2050000
0!
0O

#2055000
1!
b10110100 5
1O

#2060000
0!
0O

#2065000
1!
b10110101 5
1O

#2070000
0!
0O

#2075000
1!
b10110110 5
1O

#2080000
0!
0O

#2085000
1!
b10110111 5
1O

#2090000
0!
0O

#2095000
1!
b10111000 5
1O

#2100000
0!
0O

#2105000
1!
b10111001 5
1O

#2110000
0!
0O

#2115000
1!
b10111010 5
1O

#2120000
0!
0O

#2125000
1!
b10111011 5
1O

#2130000
0!
0O

#2135000
1!
b10111100 5
1O

#2140000
0!
0O

#2145000
1!
b10111101 5
1O

#2150000
0!
0O

#2155000
1!
b10111110 5
1O

#2160000
0!
0O

#2165000
1!
b10111111 5
1O

#2170000
0!
0O

#2175000
1!
b11000000 5
1O

#2180000
0!
0O

#2185000
1!
b11000001 5
1O

#2190000
0!
0O

#2195000
1!
b11000010 5
1O

#2200000
0!
0O

#2205000
1!
b11000011 5
1O

#2210000
0!
0O

#2215000
1!
b11000100 5
1O

#2220000
0!
0O

#2225000
1!
b11000101 5
1O

#2230000
0!
0O

#2235000
1!
b11000110 5
1O

#2240000
0!
0O

#2245000
1!
b11000111 5
1O

#2250000
0!
0O

#2255000
1!
b11001000 5
1O

#2260000
0!
0O

#2265000
1!
b11001001 5
1O

#2270000
0!
0O

#2275000
1!
b11001010 5
1O

#2280000
0!
0O

#2285000
1!
b11001011 5
1O

#2290000
0!
0O

#2295000
1!
b11001100 5
1O

#2300000
0!
0O

#2305000
1!
b11001101 5
1O

#2310000
0!
0O

#2315000
1!
b11001110 5
1O

#2320000
0!
0O

#2325000
1!
b11001111 5
1O

#2330000
0!
0O

#2335000
1!
b11010000 5
1O

#2340000
0!
0O

#2345000
1!
b11010001 5
1O

#2350000
0!
0O

#2355000
1!
b11010010 5
1O

#2360000
0!
0O

#2365000
1!
b11010011 5
1O

#2370000
0!
0O

#2375000
1!
b11010100 5
1O

#2380000
0!
0O

#2385000
1!
b11010101 5
1O

#2390000
0!
0O

#2395000
1!
b11010110 5
1O

#2400000
0!
0O

#2405000
1!
b11010111 5
1O

#2410000
0!
0O

#2415000
1!
b11011000 5
1O

#2420000
0!
0O

#2425000
1!
b11011001 5
1O

#2430000
0!
0O

#2435000
1!
b11011010 5
1O

#2440000
0!
0O

#2445000
1!
b11011011 5
1O

#2450000
0!
0O

#2455000
1!
b11011100 5
1O

#2460000
0!
0O

#2465000
1!
b11011101 5
1O

#2470000
0!
0O

#2475000
1!
b11011110 5
1O

#2480000
0!
0O

#2485000
1!
b11011111 5
1O

#2490000
0!
0O

#2495000
1!
b11100000 5
1O

#2500000
0!
0O

#2505000
1!
b11100001 5
1O

#2510000
0!
0O

#2515000
1!
b11100010 5
1O

#2520000
0!
0O

#2525000
1!
b11100011 5
1O

#2530000
0!
0O

#2535000
1!
b11100100 5
1O

#2540000
0!
0O

#2545000
1!
b11100101 5
1O

#2550000
0!
0O

#2555000
1!
b11100110 5
1O

#2560000
0!
0O

#2565000
1!
b11100111 5
1O

#2570000
0!
0O

#2575000
1!
b11101000 5
1O

#2580000
0!
0O

#2585000
1!
b11101001 5
1O

#2590000
0!
0O

#2595000
1!
b11101010 5
1O

#2600000
0!
0O

#2605000
1!
b11101011 5
1O

#2610000
0!
0O

#2615000
1!
b11101100 5
1O

#2620000
0!
0O

#2625000
1!
b11101101 5
1O

#2630000
0!
0O

#2635000
1!
b11101110 5
1O

#2640000
0!
0O

#2645000
1!
b11101111 5
1O

#2650000
0!
0O

#2655000
1!
b11110000 5
1O

#2660000
0!
0O

#2665000
1!
b11110001 5
1O

#2670000
0!
0O

#2675000
1!
b11110010 5
1O

#2680000
0!
0O

#2685000
1!
b11110011 5
1O

#2690000
0!
0O

#2695000
1!
b11110100 5
1O

#2700000
0!
0O

#2705000
1!
b11110101 5
1O

#2710000
0!
0O

#2715000
1!
b11110110 5
1O

#2720000
0!
0O

#2725000
1!
b11110111 5
1O

#2730000
0!
0O

#2735000
1!
b11111000 5
1O

#2740000
0!
0O

#2745000
1!
b11111001 5
1O

#2750000
0!
0O

#2755000
1!
b11111010 5
1O

#2760000
0!
0O

#2765000
1!
b11111011 5
1O

#2770000
0!
0O

#2775000
1!
b11111100 5
1O

#2780000
0!
0O

#2785000
1!
b11111101 5
1O

#2790000
0!
0O

#2795000
1!
b11111110 5
1O

#2800000
0!
0O

#2805000
1!
b11111111 5
1O

#2810000
0!
0O

#2815000
1!
b100000000 5
1O

#2820000
0!
0O

#2825000
1!
b100000001 5
1O

#2830000
0!
0O

#2835000
1!
b100000010 5
1O

#2840000
0!
0O

#2845000
1!
b100000011 5
1O

#2850000
0!
0O

#2855000
1!
b100000100 5
1O

#2860000
0!
0O

#2865000
1!
b100000101 5
1O

#2870000
0!
0O

#2875000
1!
b100000110 5
1O

#2880000
0!
0O

#2885000
1!
b100000111 5
1O

#2890000
0!
0O

#2895000
1!
b100001000 5
1O

#2900000
0!
0O

#2905000
1!
b100001001 5
1O

#2910000
0!
0O

