password_lock_system/sim/w25q64_model.sv
`timescale 1ns/1ps
// 仅供仿真的简化 W25Q64 模型，支持工程使用的 9F/05/06/03/20/02 指令。
// mem[0:8191] 模拟两个 4 KiB 扇区；不建模真实擦写延时，状态寄存器始终立即就绪。
module w25q64_model(
 input wire cs_n,input wire sclk,input wire mosi,output reg miso
);
 reg [7:0] mem[0:8191];
 reg [7:0] in_shift,out_shift,command;
 integer bit_count,byte_count,i;
 integer address;
 reg write_enable;
 reg [1:0] id_index;
 // Flash 擦除态为全 1；写入只能执行 1→0，所以页编程使用按位与。
 initial begin for(i=0;i<8192;i=i+1)mem[i]=8'hFF; miso=1;write_enable=0;end
 always @(negedge cs_n) begin
   bit_count=0;byte_count=0;in_shift=0;out_shift=8'hFF;command=0;address=0;id_index=0;miso=1;
 end
 always @(posedge cs_n) begin
   if(command==8'h02)write_enable=0;
 end
 // Mode 0：模型在下降沿更新 MISO，主机将在随后的上升沿采样。
 always @(negedge sclk) if(!cs_n) begin
   miso=out_shift[7];out_shift={out_shift[6:0],1'b1};
 end
 // 上升沿采 MOSI，每收满 8 位后解析命令、地址或数据。
 always @(posedge sclk) if(!cs_n) begin : sample
   reg [7:0] received;
   in_shift={in_shift[6:0],mosi};
   if(bit_count==7) begin
     received=in_shift;bit_count=0;
     if(byte_count==0) begin
       command=received;
       case(received)
         8'h9F: begin out_shift=8'hEF;id_index=0;end
         8'h05: out_shift=8'h00;
         8'h06: write_enable=1;
       endcase
     end else case(command)
       8'h9F: begin
         id_index=id_index+1;
         case(id_index)1:out_shift=8'h40;2:out_shift=8'h17;default:out_shift=8'hFF;endcase
       end
       8'h05: out_shift=8'h00;
       8'h03: begin
         if(byte_count<=3) begin
           address=(address<<8)|received;
           if(byte_count==3)out_shift=mem[address&8191];
         end else begin address=(address+1)&8191;out_shift=mem[address];end
       end
       8'h20: begin
         if(byte_count<=3)address=(address<<8)|received;
         if(byte_count==3 && write_enable) begin
           address=address&13'h1000;
           for(i=0;i<4096;i=i+1)mem[address+i]=8'hFF;
           write_enable=0;
         end
       end
       8'h02: begin
         if(byte_count<=3)address=(address<<8)|received;
         else if(write_enable) begin mem[address&8191]=mem[address&8191]&received;address=address+1;end
       end
     endcase
     byte_count=byte_count+1;
   end else bit_count=bit_count+1;
 end
endmodule

password_lock_system/rtl/spi_byte_master.v
`timescale 1ns/1ps

// SPI Mode 0 单字节主机：空闲时 SCLK=0，上升沿采 MISO，下降沿更新 MOSI，MSB 先传。
// HALF_DIV=2、输入 50 MHz 时 SCLK=12.5 MHz；CS# 由上层 Flash 事务状态机控制。
module spi_byte_master #(
    parameter integer HALF_DIV = 2
) (
    input  wire       clk,
    input  wire       rst,
    input  wire       start,
    input  wire [7:0] tx_data,
    input  wire       miso,
    output reg        sclk,
    output reg        mosi,
    output reg  [7:0] rx_data,
    output reg        busy,
    output reg        done
);
    localparam integer DW = (HALF_DIV <= 2) ? 1 : $clog2(HALF_DIV);
    reg [DW-1:0] div_count;
    reg [7:0] tx_shift;
    reg [7:0] rx_shift;
    // edge_count 统计已经完成的上升沿采样次数，达到 8 表示一个字节接收完毕。
    reg [3:0] edge_count;

    always @(posedge clk) begin
        if (rst) begin
            sclk      <= 1'b0;
            mosi      <= 1'b0;
            rx_data   <= 8'h00;
            busy      <= 1'b0;
            done      <= 1'b0;
            div_count <= {DW{1'b0}};
            tx_shift  <= 8'h00;
            rx_shift  <= 8'h00;
            edge_count <= 4'd0;
        end else begin
            done <= 1'b0;
            if (!busy) begin
                sclk <= 1'b0;
                if (start) begin
                    busy       <= 1'b1;
                    tx_shift   <= tx_data;
                    rx_shift   <= 8'h00;
                    mosi       <= tx_data[7];
                    edge_count <= 4'd0;
                    div_count  <= {DW{1'b0}};
                end
            end else if (div_count == HALF_DIV-1) begin
                div_count <= {DW{1'b0}};
                // 上升沿采样返回位；下降沿移出下一位，符合 Mode 0 时序。
                if (!sclk) begin
                    sclk <= 1'b1;
                    rx_shift <= {rx_shift[6:0], miso};
                    edge_count <= edge_count + 1'b1;
                end else begin
                    sclk <= 1'b0;
                    if (edge_count == 4'd8) begin
                        busy    <= 1'b0;
                        done    <= 1'b1;
                        rx_data <= rx_shift;
                        mosi    <= 1'b0;
                    end else begin
                        tx_shift <= {tx_shift[6:0], 1'b0};
                        mosi     <= tx_shift[6];
                    end
                end
            end else begin
                div_count <= div_count + 1'b1;
            end
        end
    end
endmodule

password_lock_system/rtl/w25q64_password_store.v
`timescale 1ns/1ps

// W25Q64 双扇区掉电安全密码日志：A=0x000000，B=0x001000，每次写入非活动扇区。
// 16 字节记录格式：魔数[4]、代数[4]、密码[2]、密码反码[2]、CRC16[2]、提交标记[2]。
// 只有写后回读校验完全通过，current_password 才更新；断电时旧扇区仍保留有效副本。
module w25q64_password_store #(
    parameter integer CLOCK_HZ = 50_000_000,
    parameter integer SPI_HALF_DIV = 2,
    parameter integer CS_HIGH_CYCLES = 4,
    parameter integer ERASE_TIMEOUT_CYCLES = CLOCK_HZ,
    parameter integer PROGRAM_TIMEOUT_CYCLES = CLOCK_HZ/50
) (
    input  wire        clk,
    input  wire        rst,
    input  wire        save_request,
    input  wire [15:0] save_password,
    input  wire        flash_miso,
    output wire        flash_sclk,
    output wire        flash_mosi,
    output reg         flash_cs_n,
    output wire        flash_wp_n,
    output wire        flash_hold_n,
    output reg         init_done,
    output reg [15:0]  current_password,
    output reg         save_done,
    output reg         save_success,
    output reg         flash_fault
);
    // MAGIC="PLK1"，COMMIT 表示该条记录已完整写成；代数较大的有效记录为最新记录。
    localparam [31:0] MAGIC = 32'h504C4B31;
    localparam [15:0] COMMIT = 16'hA55A;
    localparam [5:0] S_ID=0, S_READ_A=1, S_READ_B=2, S_SELECT=3, S_IDLE=4,
                     S_WREN_ERASE=5, S_ERASE=6, S_POLL_ERASE=7,
                     S_WREN_PROGRAM=8, S_PROGRAM=9, S_POLL_PROGRAM=10,
                     S_VERIFY=11, S_FINISH=12, S_FAIL=13;

    reg [5:0] state;
    reg [5:0] byte_index;
    reg [31:0] timeout_count;
    localparam integer CGW = (CS_HIGH_CYCLES <= 2) ? 1 : $clog2(CS_HIGH_CYCLES + 1);
    reg [CGW-1:0] cs_high_count;
    reg awaiting_byte;
    reg launch_pending;
    reg spi_start;
    reg [7:0] spi_tx;
    wire [7:0] spi_rx;
    wire spi_busy, spi_done;
    reg [127:0] record_a, record_b, verify_record, new_record;
    reg [31:0] generation;
    reg active_bank;
    reg target_bank;
    reg id_valid;
    reg [23:0] jedec_id;
    reg [15:0] requested_password;
    // record_valid 同时检查格式、BCD、反码、CRC 和提交标记，任一不符即视为无效记录。
    wire valid_a = record_valid(record_a);
    wire valid_b = record_valid(record_b);
    wire valid_verify = record_valid(verify_record);
    wire [23:0] target_address = target_bank ? 24'h001000 : 24'h000000;

    // WP# 与 HOLD# 始终拉高，表示不启用硬件写保护和总线暂停。
    assign flash_wp_n   = 1'b1;
    assign flash_hold_n = 1'b1;

    spi_byte_master #(.HALF_DIV(SPI_HALF_DIV)) u_spi (
        .clk(clk), .rst(rst), .start(spi_start), .tx_data(spi_tx),
        .miso(flash_miso), .sclk(flash_sclk), .mosi(flash_mosi),
        .rx_data(spi_rx), .busy(spi_busy), .done(spi_done)
    );

    // 对记录前 12 字节计算 CRC-16/CCITT，多项式 0x1021，初值 0xFFFF。
    function [15:0] crc16_96;
        input [95:0] data;
        integer i;
        reg [15:0] crc;
        begin
            crc = 16'hFFFF;
            for (i=95; i>=0; i=i-1) begin
                if (crc[15] ^ data[i])
                    crc = {crc[14:0],1'b0} ^ 16'h1021;
                else
                    crc = {crc[14:0],1'b0};
            end
            crc16_96 = crc;
        end
    endfunction

    function bcd_valid;
        input [15:0] value;
        begin
            bcd_valid = (value[15:12] <= 9) && (value[11:8] <= 9) &&
                        (value[7:4] <= 9) && (value[3:0] <= 9);
        end
    endfunction

    function record_valid;
        input [127:0] record;
        begin
            record_valid = (record[127:96] == MAGIC) &&
                           bcd_valid(record[63:48]) &&
                           (record[47:32] == ~record[63:48]) &&
                           (record[31:16] == crc16_96(record[127:32])) &&
                           (record[15:0] == COMMIT);
        end
    endfunction

    function [7:0] record_byte;
        input [127:0] record;
        input [4:0] index;
        begin
            case (index)
                0: record_byte=record[127:120]; 1: record_byte=record[119:112];
                2: record_byte=record[111:104]; 3: record_byte=record[103:96];
                4: record_byte=record[95:88];   5: record_byte=record[87:80];
                6: record_byte=record[79:72];   7: record_byte=record[71:64];
                8: record_byte=record[63:56];   9: record_byte=record[55:48];
                10:record_byte=record[47:40];  11: record_byte=record[39:32];
                12:record_byte=record[31:24];  13: record_byte=record[23:16];
                14:record_byte=record[15:8];   default: record_byte=record[7:0];
            endcase
        end
    endfunction

    // 按状态和字节下标产生 SPI 命令流：9F/03/06/20/02/05 分别为读 ID、读、写使能、擦除、页编程、读状态。
    function [7:0] transaction_byte;
        input [5:0] st;
        input [5:0] index;
        begin
            transaction_byte = 8'h00;
            case (st)
                S_ID: transaction_byte = (index == 0) ? 8'h9F : 8'h00;
                S_READ_A, S_READ_B, S_VERIFY: begin
                    case (index)
                        0: transaction_byte=8'h03;
                        1: transaction_byte=(st==S_READ_B || (st==S_VERIFY && target_bank)) ? 8'h00 : 8'h00;
                        2: transaction_byte=(st==S_READ_B || (st==S_VERIFY && target_bank)) ? 8'h10 : 8'h00;
                        3: transaction_byte=8'h00;
                        default: transaction_byte=8'h00;
                    endcase
                end
                S_WREN_ERASE, S_WREN_PROGRAM: transaction_byte=8'h06;
                S_ERASE: begin
                    case(index)
                        0: transaction_byte=8'h20;
                        1: transaction_byte=target_address[23:16];
                        2: transaction_byte=target_address[15:8];
                        default: transaction_byte=target_address[7:0];
                    endcase
                end
                S_PROGRAM: begin
                    case(index)
                        0: transaction_byte=8'h02;
                        1: transaction_byte=target_address[23:16];
                        2: transaction_byte=target_address[15:8];
                        3: transaction_byte=target_address[7:0];
                        default: transaction_byte=record_byte(new_record,index-4);
                    endcase
                end
                S_POLL_ERASE, S_POLL_PROGRAM:
                    transaction_byte=(index==0) ? 8'h05 : 8'h00;
                default: transaction_byte=8'h00;
            endcase
        end
    endfunction

    // 一条 SPI 命令结束：释放 CS#，并保证下一条命令前有足够的片选高电平间隔。
    task finish_transaction;
        begin
            flash_cs_n <= 1'b1;
            byte_index <= 0;
            awaiting_byte <= 1'b0;
            launch_pending <= 1'b0;
            cs_high_count <= CS_HIGH_CYCLES;
        end
    endtask

    always @(posedge clk) begin
        if (rst) begin
            state <= S_ID;
            byte_index <= 0;
            timeout_count <= 0;
            cs_high_count <= CS_HIGH_CYCLES;
            awaiting_byte <= 0;
            launch_pending <= 0;
            spi_start <= 0;
            spi_tx <= 0;
            flash_cs_n <= 1;
            init_done <= 0;
            current_password <= 16'h1234;
            save_done <= 0;
            save_success <= 0;
            flash_fault <= 0;
            record_a <= 0; record_b <= 0; verify_record <= 0; new_record <= 0;
            generation <= 0;
            active_bank <= 0; target_bank <= 1;
            id_valid <= 0; jedec_id <= 0;
            requested_password <= 16'h1234;
        end else begin
            spi_start <= 1'b0;
            save_done <= 1'b0;

            if (cs_high_count != 0)
                cs_high_count <= cs_high_count - 1'b1;

            if ((state == S_POLL_ERASE && timeout_count < ERASE_TIMEOUT_CYCLES) ||
                (state == S_POLL_PROGRAM && timeout_count < PROGRAM_TIMEOUT_CYCLES))
                timeout_count <= timeout_count + 1'b1;

            // 两级启动握手避免在 SPI 主机仍 busy 时重复触发同一字节。
            if (launch_pending && !spi_busy) begin
                spi_start <= 1'b1;
                awaiting_byte <= 1'b1;
                launch_pending <= 1'b0;
            end else if (!awaiting_byte && !launch_pending && !spi_busy &&
                cs_high_count == 0 &&
                state != S_SELECT && state != S_IDLE &&
                state != S_FINISH && state != S_FAIL) begin
                if (flash_cs_n)
                    flash_cs_n <= 1'b0;
                spi_tx <= transaction_byte(state, byte_index);
                launch_pending <= 1'b1;
            end

            // 字节完成后按当前事务收集返回值或推进状态；读记录时前 4 字节是命令和地址。
            if (spi_done && awaiting_byte) begin
                awaiting_byte <= 1'b0;
                case (state)
                    S_ID: begin
                        if (byte_index > 0)
                            jedec_id <= {jedec_id[15:0],spi_rx};
                        if (byte_index == 3) begin
                            finish_transaction;
                            id_valid <= ({jedec_id[15:0],spi_rx} != 24'h000000) &&
                                        ({jedec_id[15:0],spi_rx} != 24'hFFFFFF);
                            state <= S_READ_A;
                        end else byte_index <= byte_index + 1'b1;
                    end
                    S_READ_A: begin
                        if (byte_index >= 4)
                            record_a <= {record_a[119:0],spi_rx};
                        if (byte_index == 19) begin finish_transaction; state <= S_READ_B; end
                        else byte_index <= byte_index + 1'b1;
                    end
                    S_READ_B: begin
                        if (byte_index >= 4)
                            record_b <= {record_b[119:0],spi_rx};
                        if (byte_index == 19) begin finish_transaction; state <= S_SELECT; end
                        else byte_index <= byte_index + 1'b1;
                    end
                    S_WREN_ERASE: begin finish_transaction; state <= S_ERASE; end
                    S_ERASE: begin
                        if (byte_index == 3) begin
                            finish_transaction; state <= S_POLL_ERASE; timeout_count <= 0;
                        end else byte_index <= byte_index + 1'b1;
                    end
                    S_POLL_ERASE: begin
                        if (byte_index == 1) begin
                            finish_transaction;
                            if (!spi_rx[0]) state <= S_WREN_PROGRAM;
                            else if (timeout_count >= ERASE_TIMEOUT_CYCLES-1) state <= S_FAIL;
                        end else byte_index <= byte_index + 1'b1;
                    end
                    S_WREN_PROGRAM: begin finish_transaction; state <= S_PROGRAM; end
                    S_PROGRAM: begin
                        if (byte_index == 19) begin
                            finish_transaction; state <= S_POLL_PROGRAM; timeout_count <= 0;
                        end else byte_index <= byte_index + 1'b1;
                    end
                    S_POLL_PROGRAM: begin
                        if (byte_index == 1) begin
                            finish_transaction;
                            if (!spi_rx[0]) state <= S_VERIFY;
                            else if (timeout_count >= PROGRAM_TIMEOUT_CYCLES-1) state <= S_FAIL;
                        end else byte_index <= byte_index + 1'b1;
                    end
                    S_VERIFY: begin
                        if (byte_index >= 4)
                            verify_record <= {verify_record[119:0],spi_rx};
                        if (byte_index == 19) begin finish_transaction; state <= S_FINISH; end
                        else byte_index <= byte_index + 1'b1;
                    end
                    default: ;
                endcase
            end

            // 非逐字节状态：上电选择最新记录、等待保存请求、校验提交或报告失败。
            case (state)
                S_SELECT: begin
                    // 上电时从两个扇区中选择有效且 generation 最大者；均无效则回退默认密码 1234。
                    flash_cs_n <= 1'b1;
                    flash_fault <= ~id_valid;
                    if (valid_a && valid_b) begin
                        if (record_b[95:64] > record_a[95:64]) begin
                            current_password <= record_b[63:48]; generation <= record_b[95:64]; active_bank <= 1;
                        end else begin
                            current_password <= record_a[63:48]; generation <= record_a[95:64]; active_bank <= 0;
                        end
                    end else if (valid_a) begin
                        current_password <= record_a[63:48]; generation <= record_a[95:64]; active_bank <= 0;
                    end else if (valid_b) begin
                        current_password <= record_b[63:48]; generation <= record_b[95:64]; active_bank <= 1;
                    end else begin
                        current_password <= 16'h1234; generation <= 0; active_bank <= 0;
                    end
                    init_done <= 1'b1;
                    state <= S_IDLE;
                end
                S_IDLE: begin
                    // 锁存管理员新密码，目标切换到另一扇区，然后执行擦除→编程→轮询→回读。
                    flash_cs_n <= 1'b1;
                    if (save_request) begin
                        requested_password <= save_password;
                        target_bank <= ~active_bank;
                        new_record[127:32] <= {MAGIC,generation+1'b1,save_password,~save_password};
                        new_record[31:16] <= crc16_96({MAGIC,generation+1'b1,save_password,~save_password});
                        new_record[15:0] <= COMMIT;
                        verify_record <= 0;
                        timeout_count <= 0;
                        save_success <= 0;
                        flash_fault <= 0;
                        state <= S_WREN_ERASE;
                    end
                end
                S_FINISH: begin
                    // 回读记录必须既“格式有效”又逐位等于 new_record，才对外宣布保存成功。
                    flash_cs_n <= 1'b1;
                    if (valid_verify && verify_record == new_record) begin
                        current_password <= requested_password;
                        generation <= generation + 1'b1;
                        active_bank <= target_bank;
                        save_success <= 1'b1;
                        flash_fault <= 1'b0;
                    end else begin
                        save_success <= 1'b0;
                        flash_fault <= 1'b1;
                    end
                    save_done <= 1'b1;
                    state <= S_IDLE;
                end
                S_FAIL: begin
                    finish_transaction;
                    save_success <= 1'b0;
                    save_done <= 1'b1;
                    flash_fault <= 1'b1;
                    state <= S_IDLE;
                end
                default: ;
            endcase
        end
    end
endmodule

password_lock_system/sim/tb_flash_journal.sv
`timescale 1ns/1ps
// Flash 双扇区日志集成测试：检查片选间隔、两次保存、重启选择最新记录和损坏回退。
module tb_flash_journal;
 reg test_pass=0;
 reg clk=0,rst=1,save=0;reg[15:0]new_password=0;
 wire sclk,mosi,miso,cs,wp,hold,init_done,save_done,save_ok,fault;wire[15:0]password;
 integer cs_high_cycles=0;
 reg enforce_cs_gap=0;
 always #5 clk=~clk;
 always @(posedge clk) begin
   if(cs) cs_high_cycles=cs_high_cycles+1;
 end
 // 每次 CS# 再次拉低前检查高电平至少保持 4 个 clk，验证命令间隔参数生效。
 always @(negedge cs) begin
   if(enforce_cs_gap && cs_high_cycles<4)
     $fatal(1,"flash CS high interval too short: %0d clocks",cs_high_cycles);
   cs_high_cycles=0;
 end
 w25q64_password_store #(.CLOCK_HZ(1000),.SPI_HALF_DIV(2),.CS_HIGH_CYCLES(4),.ERASE_TIMEOUT_CYCLES(2000),.PROGRAM_TIMEOUT_CYCLES(1000)) dut(
  .clk(clk),.rst(rst),.save_request(save),.save_password(new_password),.flash_miso(miso),
  .flash_sclk(sclk),.flash_mosi(mosi),.flash_cs_n(cs),.flash_wp_n(wp),.flash_hold_n(hold),
  .init_done(init_done),.current_password(password),.save_done(save_done),.save_success(save_ok),.flash_fault(fault));
 w25q64_model flash(.cs_n(cs),.sclk(sclk),.mosi(mosi),.miso(miso));
 // do_save 模拟管理员发出单周期保存请求，并等待 Flash 状态机给出完成握手。
 task do_save(input[15:0]p);begin new_password=p;save=1;@(negedge clk);save=0;wait(save_done);@(negedge clk);
   if(!save_ok)begin $display("new=%h verify=%h mem=%h%h%h%h",dut.new_record,dut.verify_record,
      flash.mem[4096],flash.mem[4097],flash.mem[4110],flash.mem[4111]);$fatal(1,"save %h failed",p);end
   if(password!==p)$fatal(1,"save not activated");end endtask
 task reboot;begin rst=1;repeat(4)@(negedge clk);rst=0;wait(init_done);repeat(2)@(negedge clk);end endtask
 initial begin
   repeat(4)@(negedge clk);rst=0;wait(init_done);@(negedge clk);
   if(password!==16'h1234)$fatal(1,"default wrong");
   enforce_cs_gap=1;
   do_save(16'h5678);do_save(16'h2468);reboot();
   if(password!==16'h2468)$fatal(1,"highest generation not selected: %h",password);
   // 第二次更新位于扇区 0；破坏提交标记模拟写入中断，重启后应回退扇区 1 的旧密码。
   flash.mem[15]=8'h00;reboot();
   if(password!==16'h5678)$fatal(1,"did not recover older valid record: %h",password);
   test_pass=1;$display("PASS tb_flash_journal");$finish;
 end
endmodule

simulation_waveforms/08_flash_dual_journal/tb_flash_journal.vcd
$date
   Tue Sep  8 20:51:15 2026
$end

$version
  2023.2
$end

$timescale
  1ps
$end

$scope module tb_flash_journal $end
$var reg 1 )! test_pass $end
$var reg 1 *! clk $end
$var reg 1 +! rst $end
$var reg 1 ,! save $end
$var reg 16 -! new_password [15:0] $end
$var wire 1 A sclk $end
$var wire 1 B mosi $end
$var wire 1 % miso $end
$var wire 1 { cs $end
$var wire 1 D wp $end
$var wire 1 E hold $end
$var wire 1 .! init_done $end
$var wire 1 /! save_done $end
$var wire 1 0! save_ok $end
$var wire 1 1! fault $end
$var wire 16 2! password [15:0] $end
$var integer 32 3! cs_high_cycles [31:0] $end
$var reg 1 4! enforce_cs_gap $end
$scope module dut $end
$var wire 1 ! clk $end
$var wire 1 " rst $end
$var wire 1 ? save_request $end
$var wire 16 @ save_password [15:0] $end
$var wire 1 % flash_miso $end
$var wire 1 A flash_sclk $end
$var wire 1 B flash_mosi $end
$var reg 1 C flash_cs_n $end
$var wire 1 D flash_wp_n $end
$var wire 1 E flash_hold_n $end
$var reg 1 F init_done $end
$var reg 16 G current_password [15:0] $end
$var reg 1 H save_done $end
$var reg 1 I save_success $end
$var reg 1 J flash_fault $end
$var reg 6 K state [5:0] $end
$var reg 6 L byte_index [5:0] $end
$var reg 32 M timeout_count [31:0] $end
$var reg 3 N cs_high_count [2:0] $end
$var reg 1 O awaiting_byte $end
$var reg 1 P launch_pending $end
$var reg 1 Q spi_start $end
$var reg 8 R spi_tx [7:0] $end
$var wire 8 S spi_rx [7:0] $end
$var wire 1 T spi_busy $end
$var wire 1 U spi_done $end
$var reg 128 V record_a [127:0] $end
$var reg 128 W record_b [127:0] $end
$var reg 128 X verify_record [127:0] $end
$var reg 128 Y new_record [127:0] $end
$var reg 32 Z generation [31:0] $end
$var reg 1 [ active_bank $end
$var reg 1 \ target_bank $end
$var reg 1 ] id_valid $end
$var reg 24 ^ jedec_id [23:0] $end
$var reg 16 _ requested_password [15:0] $end
$var wire 1 ` valid_a $end
$var wire 1 a valid_b $end
$var wire 1 b valid_verify $end
$var wire 24 c target_address [23:0] $end
$var parameter 0 d CLOCK_HZ [31:0] $end
$var parameter 0 e SPI_HALF_DIV [31:0] $end
$var parameter 0 f CS_HIGH_CYCLES [31:0] $end
$var parameter 0 g ERASE_TIMEOUT_CYCLES [31:0] $end
$var parameter 0 h PROGRAM_TIMEOUT_CYCLES [31:0] $end
$var parameter 32 i MAGIC [31:0] $end
$var parameter 16 j COMMIT [15:0] $end
$var parameter 6 k S_ID [5:0] $end
$var parameter 6 l S_READ_A [5:0] $end
$var parameter 6 m S_READ_B [5:0] $end
$var parameter 6 n S_SELECT [5:0] $end
$var parameter 6 o S_IDLE [5:0] $end
$var parameter 6 p S_WREN_ERASE [5:0] $end
$var parameter 6 q S_ERASE [5:0] $end
$var parameter 6 r S_POLL_ERASE [5:0] $end
$var parameter 6 s S_WREN_PROGRAM [5:0] $end
$var parameter 6 t S_PROGRAM [5:0] $end
$var parameter 6 u S_POLL_PROGRAM [5:0] $end
$var parameter 6 v S_VERIFY [5:0] $end
$var parameter 6 w S_FINISH [5:0] $end
$var parameter 6 x S_FAIL [5:0] $end
$var parameter 0 y CGW [31:0] $end
$scope module u_spi $end
$var wire 1 ! clk $end
$var wire 1 " rst $end
$var wire 1 # start $end
$var wire 8 $ tx_data [7:0] $end
$var wire 1 % miso $end
$var reg 1 & sclk $end
$var reg 1 ' mosi $end
$var reg 8 ( rx_data [7:0] $end
$var reg 1 ) busy $end
$var reg 1 * done $end
$var reg 1 + div_count [0:0] $end
$var reg 8 , tx_shift [7:0] $end
$var reg 8 - rx_shift [7:0] $end
$var reg 4 . edge_count [3:0] $end
$var parameter 0 / HALF_DIV [31:0] $end
$var parameter 0 0 DW [31:0] $end
$upscope $end
$scope function crc16_96 $end
$var reg 16 1 crc16_96 [15:0] $end
$var reg 96 2 data [95:0] $end
$var integer 32 3 i [31:0] $end
$var reg 16 4 crc [15:0] $end
$upscope $end
$scope function bcd_valid $end
$var reg 1 5 bcd_valid $end
$var reg 16 6 value [15:0] $end
$upscope $end
$scope function record_valid $end
$var reg 1 7 record_valid $end
$var reg 128 8 record [127:0] $end
$upscope $end
$scope function record_byte $end
$var reg 8 9 record_byte [7:0] $end
$var reg 128 : record [127:0] $end
$var reg 5 ; index [4:0] $end
$upscope $end
$scope function transaction_byte $end
$var reg 8 < transaction_byte [7:0] $end
$var reg 6 = st [5:0] $end
$var reg 6 > index [5:0] $end
$upscope $end
$upscope $end
$scope module flash $end
$var wire 1 { cs_n $end
$var wire 1 A sclk $end
$var wire 1 B mosi $end
$var reg 1 | miso $end
$var reg 8 } in_shift [7:0] $end
$var reg 8 ~ out_shift [7:0] $end
$var reg 8 !! command [7:0] $end
$var integer 32 "! bit_count [31:0] $end
$var integer 32 #! byte_count [31:0] $end
$var integer 32 $! i [31:0] $end
$var integer 32 %! address [31:0] $end
$var reg 1 &! write_enable $end
$var reg 2 '! id_index [1:0] $end
$scope begin sample $end
$var reg 8 z received [7:0] $end
$upscope $end
$upscope $end
$scope task do_save $end
$var reg 16 (! p [15:0] $end
$upscope $end
$upscope $end
$enddefinitions $end

#0
$dumpvars
0!
bx !!
1"
bx "!
x#
bx #!
bx $
b10000000000000 $!
1%
bx %!
x&
0&!
x'
bx '!
bx (
bx (!
x)
0)!
x*
0*!
x+
1+!
bx ,
0,!
bx -
b0 -!
bx .
x.!
b10 /
x/!
b1 0
x0!
b0 1
x1!
bx 2
bx 2!
b11111111111111111111111111111111 3
b0 3!
b0 4
04!
x5
bx 6
x7
bx 8
bx 9
bx :
bx ;
bx <
bx =
bx >
0?
b0 @
xA
xB
xC
1D
1E
xF
bx G
xH
xI
xJ
bx K
bx L
bx M
bx N
xO
xP
xQ
bx R
bx S
xT
xU
bx V
bx W
bx X
bx Y
bx Z
x[
x\
x]
bx ^
bx _
x`
xa
xb
b0x000000000000 c
b1111101000 d
b10 e
b100 f
b11111010000 g
b1111101000 h
b1010000010011000100101100110001 i
b1010010101011010 j
b0 k
b1 l
b10 m
b11 n
b100 o
b101 p
b110 q
b111 r
b1000 s
b1001 t
b1010 u
b1011 v
b1100 w
b1101 x
b11 y
bx z
x{
1|
bx }
bx ~
$end

#5000
1!
0#
b0 $
0&
0'
b0 (
0)
0*
1*!
0+
b0 ,
b0 -
b0 .
0.!
0/!
00!
01!
b1001000110100 2!
07
b0 8
0A
0B
1C
0F
b1001000110100 G
0H
0I
0J
b0 K
b0 L
b0 M
b100 N
0O
0P
0Q
b0 R
b0 S
0T
0U
b0 V
b0 W
b0 X
b0 Y
b0 Z
0[
1\
0]
b0 ^
b1001000110100 _
0`
0a
0b
b1000000000000 c
1{

#10000
0!
0*!

#15000
1!
1*!
b1 3!

#20000
0!
0*!

#25000
1!
1*!
b10 3!

#30000
0!
0*!

#35000
1!
1*!
b11 3!

#40000
0!
0"
0*!
0+!

#45000
1!
1*!
b100 3!
b11 N

#50000
0!
0*!

#55000
1!
1*!
b101 3!
b10 N

#60000
0!
0*!

#65000
1!
1*!
b110 3!
b1 N

#70000
0!
0*!

#75000
1!
1*!
b111 3!
b0 N

#80000
0!
0*!

#85000
1!
b0 !!
b0 "!
b0 #!
b10011111 $
b0 %!
b0 '!
1*!
b0 3!
b10011111 <
b0 =
b0 >
0C
1P
b10011111 R
0{
b0 }
b11111111 ~

#90000
0!
0*!

#95000
1!
1#
1*!
1O
0P
1Q

#100000
0!
0*!

#105000
1!
0#
1'
1)
1*!
b10011111 ,
1B
0Q
1T

#110000
0!
0*!

#115000
1!
1*!
1+

#120000
0!
0*!

#125000
1!
b1 "!
1&
1*!
0+
b1 -
b1 .
1A
b1 }

#130000
0!
0*!

#135000
1!
1*!
1+

#140000
0!
0*!

#145000
1!
0&
0'
1*!
0+
b111110 ,
0A
0B

#150000
0!
0*!

#155000
1!
1*!
1+

#160000
0!
0*!

#165000
1!
b10 "!
1&
1*!
0+
b11 -
b10 .
1A
b10 }

#170000
0!
0*!

#175000
1!
1*!
1+

#180000
0!
0*!

#185000
1!
0&
1*!
0+
b1111100 ,
0A

#190000
0!
0*!

#195000
1!
1*!
1+

#200000
0!
0*!

#205000
1!
b11 "!
1&
1*!
0+
b111 -
b11 .
1A
b100 }

#210000
0!
0*!

#215000
1!
1*!
1+

#220000
0!
0*!

#225000
1!
0&
1'
1*!
0+
b11111000 ,
0A
1B

#230000
0!
0*!

#235000
1!
1*!
1+

#240000
0!
0*!

#245000
1!
b100 "!
1&
1*!
0+
b1111 -
b100 .
1A
b1001 }

#250000
0!
0*!

#255000
1!
1*!
1+

#260000
0!
0*!

#265000
1!
0&
1*!
0+
b11110000 ,
0A

#270000
0!
0*!

#275000
1!
1*!
1+

#280000
0!
0*!

#285000
1!
b101 "!
1&
1*!
0+
b11111 -
b101 .
1A
b10011 }

#290000
0!
0*!

#295000
1!
1*!
1+

#300000
0!
0*!

#305000
1!
0&
1*!
0+
b11100000 ,
0A

#310000
0!
0*!

#315000
1!
1*!
1+

#320000
0!
0*!

#325000
1!
b110 "!
1&
1*!
0+
b111111 -
b110 .
1A
b100111 }

#330000
0!
0*!

#335000
1!
1*!
1+

#340000
0!
0*!

#345000
1!
0&
1*!
0+
b11000000 ,
0A

#350000
0!
0*!

#355000
1!
1*!
1+

#360000
0!
0*!

#365000
1!
b111 "!
1&
1*!
0+
b1111111 -
b111 .
1A
b1001111 }

#370000
0!
0*!

#375000
1!
1*!
1+

#380000
0!
0*!

#385000
1!
0&
1*!
0+
b10000000 ,
0A

#390000
0!
0*!

#395000
1!
1*!
1+

#400000
0!
0*!

#405000
1!
b10011111 !!
b0 "!
b1 #!
1&
1*!
0+
b11111111 -
b1000 .
1A
b10011111 z
b10011111 }
b11101111 ~

#410000
0!
0*!

#415000
1!
1*!
1+

#420000
0!
0*!

#425000
1!
0&
0'
b11111111 (
0)
1*
1*!
0+
0A
0B
b11111111 S
0T
1U
b11011111 ~

#430000
0!
0*!

#435000
1!
0*
1*!
b1 L
0O
0U

#440000
0!
0*!

#445000
1!
b0 $
1*!
b0 <
b1 >
1P
b0 R

#450000
0!
0*!

#455000
1!
1#
1*!
1O
0P
1Q

#460000
0!
0*!

#465000
1!
0#
1)
1*!
b0 ,
b0 -
b0 .
0Q
1T

#470000
0!
0*!

#475000
1!
1*!
1+

#480000
0!
0*!

#485000
1!
b1 "!
1&
1*!
0+
b1 -
b1 .
1A
b111110 }

#490000
0!
0*!

#495000
1!
1*!
1+

#500000
0!
0*!

#505000
1!
0&
1*!
0+
0A
b10111111 ~

#510000
0!
0*!

#515000
1!
1*!
1+

#520000
0!
0*!

#525000
1!
b10 "!
1&
1*!
0+
b11 -
b10 .
1A
b1111100 }

#530000
0!
0*!

#535000
1!
1*!
1+

#540000
0!
0*!

#545000
1!
0&
1*!
0+
0A
b1111111 ~

