password_lock_system/rtl/temporary_password_generator.v
`timescale 1ns/1ps

// 易失性 4 位临时密码发生器。LFSR 始终运行，按 KEY3 时才取样生成结果。
// 临时密码不会写入 Flash，复位或断电后 temporary_valid 清零，旧临时密码立即失效。
module temporary_password_generator (
    input  wire        clk,
    input  wire        rst,
    input  wire        generate_event,
    input  wire [15:0] stored_password,
    output reg  [15:0] temporary_password,
    output reg         temporary_valid
);
    reg [15:0] lfsr;
    reg [15:0] random_bcd_candidate;
    reg [15:0] candidate;
    reg [15:0] alternate1;
    reg [15:0] alternate2;

    // 按十进制 BCD 规则加 1（9999 后回到 0000），用于避开不能使用的候选值。
    function [15:0] next_decimal_password;
        input [15:0] value;
        reg [3:0] d3, d2, d1, d0;
        begin
            d3 = value[15:12];
            d2 = value[11:8];
            d1 = value[7:4];
            d0 = value[3:0];
            if (d0 != 4'd9) d0 = d0 + 1'b1;
            else begin
                d0 = 4'd0;
                if (d1 != 4'd9) d1 = d1 + 1'b1;
                else begin
                    d1 = 4'd0;
                    if (d2 != 4'd9) d2 = d2 + 1'b1;
                    else begin
                        d2 = 4'd0;
                        if (d3 != 4'd9) d3 = d3 + 1'b1;
                        else d3 = 4'd0;
                    end
                end
            end
            next_decimal_password = {d3, d2, d1, d0};
        end
    endfunction

    always @(*) begin
        candidate = random_bcd_candidate;
        alternate1 = next_decimal_password(candidate);
        alternate2 = next_decimal_password(alternate1);
    end

    always @(posedge clk) begin
        if (rst) begin
            lfsr               <= 16'h1D3F;
            random_bcd_candidate <= 16'h5831;
            temporary_password <= 16'h0000;
            temporary_valid    <= 1'b0;
        end else begin
            // 16 位非零种子的 LFSR：反馈多项式 x^16+x^14+x^13+x^11+1。
            lfsr <= {lfsr[14:0], lfsr[15] ^ lfsr[13] ^ lfsr[12] ^ lfsr[10]};
            // 拒绝采样：仅接受 4 个半字节都在 0~9 的值，保证显示的是合法 BCD 且分布不受模运算偏置。
            if (lfsr[15:12] <= 9 && lfsr[11:8] <= 9 &&
                lfsr[7:4] <= 9 && lfsr[3:0] <= 9)
                random_bcd_candidate <= lfsr;
            if (generate_event) begin
                // 固定密码和上一次临时密码最多排除两个值，三个连续 BCD 候选必有一个可用。
                if (candidate != stored_password &&
                    (!temporary_valid || candidate != temporary_password))
                    temporary_password <= candidate;
                else if (alternate1 != stored_password &&
                         (!temporary_valid || alternate1 != temporary_password))
                    temporary_password <= alternate1;
                else
                    temporary_password <= alternate2;
                temporary_valid <= 1'b1;
            end
        end
    end
endmodule

password_lock_system/sim/tb_temporary_password_generator.sv
`timescale 1ns/1ps

// 临时密码测试：检查复位失效、4 位十进制、不同于固定/上次密码，以及再次复位清除有效标志。
module tb_temporary_password_generator;
    reg clk=0,rst=1,generate_event=0;
    reg [15:0] stored_password=16'h1234;
    wire [15:0] temporary_password;
    wire temporary_valid;
    reg [15:0] previous_password;
    reg test_pass=0;
    integer i;

    always #5 clk=~clk;
    temporary_password_generator dut(
        .clk(clk),.rst(rst),.generate_event(generate_event),
        .stored_password(stored_password),.temporary_password(temporary_password),
        .temporary_valid(temporary_valid));

    // generate_one 模拟 KEY3 形成一个时钟周期的 generate_event。
    task generate_one;
      begin
        @(negedge clk);generate_event=1;
        @(negedge clk);generate_event=0;
        #1;
      end
    endtask

    // 四个半字节都必须 <=9，否则数码管显示将不是合法十进制密码。
    task check_decimal;
      begin
        if(temporary_password[15:12]>9 || temporary_password[11:8]>9 ||
           temporary_password[7:4]>9 || temporary_password[3:0]>9)
          $fatal(1,"temporary password is not four decimal digits: %h",temporary_password);
      end
    endtask

    // 连续生成 33 次，用回归方式验证替换密码不重复且不等于永久密码。
    initial begin
      repeat(3)@(negedge clk);rst=0;repeat(3)@(negedge clk);
      if(temporary_valid) $fatal(1,"temporary password must be invalid after reset");
      generate_one();
      if(!temporary_valid) $fatal(1,"KEY3 did not validate temporary password");
      check_decimal();
      if(temporary_password==stored_password) $fatal(1,"temporary password equals fixed password");
      previous_password=temporary_password;
      for(i=0;i<32;i=i+1) begin
        repeat(i%3)@(negedge clk);
        generate_one();
        check_decimal();
        if(temporary_password==previous_password)
          $fatal(1,"replacement repeated previous temporary password");
        if(temporary_password==stored_password)
          $fatal(1,"replacement equals fixed password");
        previous_password=temporary_password;
      end
      rst=1;repeat(2)@(negedge clk);rst=0;#1;
      if(temporary_valid) $fatal(1,"reset did not invalidate temporary password");
      test_pass=1;$display("PASS tb_temporary_password_generator");$finish;
    end
endmodule

simulation_waveforms/09_extra_random_password/tb_temporary_password_generator.vcd
$date
   Sun Sep 13 16:29:14 2026
$end

$version
  2023.2
$end

$timescale
  1ps
$end

$scope module tb_temporary_password_generator $end
$var reg 1 2 clk $end
$var reg 1 3 rst $end
$var reg 1 4 generate_event $end
$var reg 16 5 stored_password [15:0] $end
$var wire 16 6 temporary_password [15:0] $end
$var wire 1 7 temporary_valid $end
$var reg 16 8 previous_password [15:0] $end
$var reg 1 9 test_pass $end
$var integer 32 : i [31:0] $end
$scope module dut $end
$var wire 1 ' clk $end
$var wire 1 ( rst $end
$var wire 1 ) generate_event $end
$var wire 16 * stored_password [15:0] $end
$var reg 16 + temporary_password [15:0] $end
$var reg 1 , temporary_valid $end
$var reg 16 - lfsr [15:0] $end
$var reg 16 . random_bcd_candidate [15:0] $end
$var reg 16 / candidate [15:0] $end
$var reg 16 0 alternate1 [15:0] $end
$var reg 16 1 alternate2 [15:0] $end
$scope function next_decimal_password $end
$var reg 16 ! next_decimal_password [15:0] $end
$var reg 16 " value [15:0] $end
$var reg 4 # d3 [3:0] $end
$var reg 4 $ d2 [3:0] $end
$var reg 4 % d1 [3:0] $end
$var reg 4 & d0 [3:0] $end
$upscope $end
$upscope $end
$upscope $end
$enddefinitions $end

#0
$dumpvars
bx !
bx "
bx #
bx $
bx %
bx &
0'
1(
0)
b1001000110100 *
bx +
x,
bx -
bx .
bx /
bx 0
bx 1
02
13
04
b1001000110100 5
bx 6
x7
bx 8
09
bx :
$end

#5000
b101100000110011 !
b101100000110010 "
b101 #
b1000 $
b11 %
b11 &
1'
b0 +
0,
b1110100111111 -
b101100000110001 .
b101100000110001 /
b101100000110010 0
b101100000110011 1
12
b0 6
07

#10000
0'
02

#15000
1'
12

#20000
0'
02

#25000
1'
12

#30000
0'
0(
02
03

#35000
1'
b11101001111110 -
12

#40000
0'
02

#45000
1'
b111010011111100 -
12

#50000
0'
02

#55000
1'
b1110100111111001 -
12

#60000
0'
02

#65000
1'
b1101001111110010 -
12

#70000
0'
1)
02
14

#75000
1'
b101100000110001 +
1,
b1010011111100100 -
12
b101100000110001 6
17

#80000
0'
0)
02
04

#81000
b101100000110001 8
b0 :

#85000
1'
b100111111001001 -
12

#90000
0'
1)
02
14

#95000
1'
b101100000110010 +
b1001111110010011 -
12
b101100000110010 6

#100000
0'
0)
02
04

#101000
b101100000110010 8
b1 :

#105000
1'
b11111100100111 -
12

#110000
0'
02

#115000
1'
b111111001001111 -
12

#120000
0'
1)
02
14

#125000
1'
b101100000110001 +
b1111110010011111 -
12
b101100000110001 6

#130000
0'
0)
02
04

#131000
b101100000110001 8
b10 :

#135000
1'
b1111100100111110 -
12

#140000
0'
02

#145000
1'
b1111001001111101 -
12

#150000
0'
02

#155000
1'
b1110010011111011 -
12

#160000
0'
1)
02
14

#165000
1'
b101100000110010 +
b1100100111110111 -
12
b101100000110010 6

#170000
0'
0)
02
04

#171000
b101100000110010 8
b11 :

#175000
1'
b1001001111101111 -
12

#180000
0'
1)
02
14

#185000
1'
b101100000110001 +
b10011111011110 -
12
b101100000110001 6

#190000
0'
0)
02
04

#191000
b101100000110001 8
b100 :

#195000
1'
b100111110111100 -
12

#200000
0'
02

#205000
1'
b1001111101111001 -
12

#210000
0'
1)
02
14

#215000
1'
b101100000110010 +
b11111011110011 -
12
b101100000110010 6

#220000
0'
0)
02
04

#221000
b101100000110010 8
b101 :

#225000
1'
b111110111100111 -
12

#230000
0'
02

#235000
1'
b1111101111001111 -
12

#240000
0'
02

#245000
1'
b1111011110011111 -
12

#250000
0'
1)
02
14

#255000
1'
b101100000110001 +
b1110111100111110 -
12
b101100000110001 6

#260000
0'
0)
02
04

#261000
b101100000110001 8
b110 :

#265000
1'
b1101111001111101 -
12

#270000
0'
1)
02
14

#275000
1'
b101100000110010 +
b1011110011111011 -
12
b101100000110010 6

#280000
0'
0)
02
04

#281000
b101100000110010 8
b111 :

#285000
1'
b111100111110110 -
12

#290000
0'
02

#295000
1'
b1111001111101100 -
12

#300000
0'
1)
02
14

#305000
1'
b101100000110001 +
b1110011111011001 -
12
b101100000110001 6

#310000
0'
0)
02
04

#311000
b101100000110001 8
b1000 :

#315000
1'
b1100111110110011 -
12

#320000
0'
02

#325000
1'
b1001111101100110 -
12

#330000
0'
02

#335000
1'
b11111011001101 -
12

#340000
0'
1)
02
14

#345000
1'
b101100000110010 +
b111110110011011 -
12
b101100000110010 6

#350000
0'
0)
02
04

#351000
b101100000110010 8
b1001 :

#355000
1'
b1111101100110111 -
12

#360000
0'
1)
02
14

#365000
1'
b101100000110001 +
b1111011001101111 -
12
b101100000110001 6

#370000
0'
0)
02
04

#371000
b101100000110001 8
b1010 :

#375000
1'
b1110110011011110 -
12

#380000
0'
02

#385000
1'
b1101100110111101 -
12

#390000
0'
1)
02
14

#395000
1'
b101100000110010 +
b1011001101111010 -
12
b101100000110010 6

#400000
0'
0)
02
04

#401000
b101100000110010 8
b1011 :

#405000
1'
b110011011110101 -
12

#410000
0'
02

#415000
1'
b1100110111101010 -
12

#420000
0'
02

#425000
1'
b1001101111010100 -
12

#430000
0'
1)
02
14

#435000
1'
b101100000110001 +
b11011110101000 -
12
b101100000110001 6

#440000
0'
0)
02
04

#441000
b101100000110001 8
b1100 :

#445000
1'
b110111101010001 -
12

#450000
0'
1)
02
14

#455000
1'
b101100000110010 +
b1101111010100010 -
12
b101100000110010 6

#460000
0'
0)
02
04

#461000
b101100000110010 8
b1101 :

#465000
1'
b1011110101000101 -
12

#470000
0'
02

#475000
1'
b111101010001010 -
12

#480000
0'
1)
02
14

#485000
1'
b101100000110001 +
b1111010100010100 -
12
b101100000110001 6

#490000
0'
0)
02
04

#491000
b101100000110001 8
b1110 :

#495000
1'
b1110101000101000 -
12

#500000
0'
02

#505000
1'
b1101010001010000 -
12

#510000
0'
02

#515000
1'
b1010100010100001 -
12

#520000
0'
1)
02
14

#525000
1'
b101100000110010 +
b101000101000010 -
12
b101100000110010 6

#530000
0'
0)
02
04

#531000
b101100000110010 8
b1111 :

#535000
b101000101000100 !
b101000101000011 "
b1 $
b100 %
b100 &
1'
b1010001010000101 -
b101000101000010 .
b101000101000010 /
b101000101000011 0
b101000101000100 1
12

#540000
0'
1)
02
14

#545000
1'
b101000101000010 +
b100010100001010 -
12
b101000101000010 6

#550000
0'
0)
02
04

#551000
b101000101000010 8
b10000 :

#555000
1'
b1000101000010101 -
12

#560000
0'
02

#565000
1'
b1010000101011 -
12

#570000
0'
1)
02
14

#575000
1'
b101000101000011 +
b10100001010110 -
12
b101000101000011 6

#580000
0'
0)
02
04

#581000
b101000101000011 8
b10001 :

#585000
b10100001011000 !
b10100001010111 "
b10 #
b1000 $
b101 %
b1000 &
1'
b101000010101101 -
b10100001010110 .
b10100001010110 /
b10100001010111 0
b10100001011000 1
12

#590000
0'
02

#595000
1'
b1010000101011011 -
12

#600000
0'
02

#605000
1'
b100001010110110 -
12

#610000
0'
1)
02
14

#615000
1'
b10100001010110 +
b1000010101101100 -
12
b10100001010110 6

#620000
0'
0)
02
04

#621000
b10100001010110 8
b10010 :

#625000
1'
b101011011000 -
12

#630000
0'
1)
02
14

#635000
1'
b10100001010111 +
b1010110110000 -
12
b10100001010111 6

#640000
0'
0)
02
04

#641000
b10100001010111 8
b10011 :

#645000
1'
b10101101100000 -
12

#650000
0'
02

#655000
1'
b101011011000001 -
12

#660000
0'
1)
02
14

#665000
1'
b10100001010110 +
b1010110110000010 -
12
b10100001010110 6

#670000
0'
0)
02
04

#671000
b10100001010110 8
b10100 :

#675000
1'
b101101100000101 -
12

#680000
0'
02

#685000
1'
b1011011000001011 -
12

#690000
0'
02

#695000
1'
b110110000010110 -
12

#700000
0'
1)
02
14

#705000
1'
b10100001010111 +
b1101100000101100 -
12
b10100001010111 6

#710000
0'
0)
02
04

#711000
b10100001010111 8
b10101 :

#715000
1'
b1011000001011000 -
12

#720000
0'
1)
02
14

#725000
1'
b10100001010110 +
b110000010110001 -
12
b10100001010110 6

#730000
0'
0)
02
04

#731000
b10100001010110 8
b10110 :

#735000
1'
b1100000101100011 -
12

#740000
0'
02

#745000
1'
b1000001011000111 -
12

#750000
0'
1)
02
14

#755000
1'
b10100001010111 +
b10110001111 -
12
b10100001010111 6

#760000
0'
0)
02
04

#761000
b10100001010111 8
b10111 :

#765000
1'
b101100011111 -
12

#770000
0'
02

#775000
1'
b1011000111110 -
12

#780000
0'
02

#785000
1'
b10110001111100 -
12

#790000
0'
1)
02
14

#795000
1'
b10100001010110 +
b101100011111000 -
12
b10100001010110 6

#800000
0'
0)
02
04

#801000
b10100001010110 8
b11000 :

#805000
1'
b1011000111110001 -
12

#810000
0'
1)
02
14

#815000
1'
b10100001010111 +
b110001111100011 -
12
b10100001010111 6

#820000
0'
0)
02
04

#821000
b10100001010111 8
b11001 :

#825000
1'
b1100011111000111 -
12

#830000
0'
02

#835000
1'
b1000111110001110 -
12

#840000
0'
1)
02
14

#845000
1'
b10100001010110 +
b1111100011100 -
12
b10100001010110 6

#850000
0'
0)
02
04

#851000
b10100001010110 8
b11010 :

#855000
1'
b11111000111000 -
12

#860000
0'
02

#865000
1'
b111110001110001 -
12

#870000
0'
02

#875000
1'
b1111100011100011 -
12

#880000
0'
1)
02
14

#885000
1'
b10100001010111 +
b1111000111000111 -
12
b10100001010111 6

#890000
0'
0)
02
04

#891000
b10100001010111 8
b11011 :

#895000
1'
b1110001110001111 -
12

#900000
0'
1)
02
14

#905000
1'
b10100001010110 +
b1100011100011110 -
12
b10100001010110 6

#910000
0'
0)
02
04

#911000
b10100001010110 8
b11100 :

#915000
1'
b1000111000111100 -
12

#920000
0'
02

#925000
1'
b1110001111000 -
12

#930000
0'
1)
02
14

#935000
1'
b10100001010111 +
b11100011110000 -
12
b10100001010111 6

#940000
0'
0)
02
04

#941000
b10100001010111 8
b11101 :

#945000
1'
b111000111100000 -
12

#950000
0'
02

#955000
1'
b1110001111000000 -
12

#960000
0'
02

#965000
1'
b1100011110000000 -
12

#970000
0'
1)
02
14

#975000
1'
b10100001010110 +
b1000111100000000 -
12
b10100001010110 6

#980000
0'
0)
02
04

#981000
b10100001010110 8
b11110 :

#985000
1'
b1111000000000 -
12

#990000
0'
1)
02
14

#995000
1'
b10100001010111 +
b11110000000000 -
12
b10100001010111 6

#1000000
0'
0)
02
04

#1001000
b10100001010111 8
b11111 :

#1005000
1'
b111100000000001 -
12

#1010000
0'
02

#1015000
b111100000000011 !
b111100000000010 "
b111 #
b0 %
b11 &
1'
b1111000000000010 -
b111100000000001 .
b111100000000001 /
b111100000000010 0
b111100000000011 1
12

#1020000
0'
1)
02
14

#1025000
1'
b111100000000001 +
b1110000000000101 -
12
b111100000000001 6

#1030000
0'
0)
02
04

#1031000
1(
13
b111100000000001 8
b100000 :

#1035000
b101100000110011 !
b101100000110010 "
b101 #
b11 %
b11 &
1'
b0 +
0,
b1110100111111 -
b101100000110001 .
b101100000110001 /
b101100000110010 0
b101100000110011 1
12
b0 6
07

#1040000
0'
02

#1045000
1'
12

#1050000
0'
0(
02
03

#1051000
19
