password_lock_system/rtl/uart_rx_byte.v
`timescale 1ns/1ps

// UART 8N1 单字节接收器：两级同步 RX，在每一数据位中点采样，数据按 LSB-first 装入。
// 只有停止位为高时才拉高 valid；起始位或停止位错误的帧会被丢弃。
module uart_rx_byte #(
    parameter integer CLOCK_HZ = 50_000_000,
    parameter integer BAUD     = 115_200
) (
    input  wire       clk,
    input  wire       rst,
    input  wire       rx,
    output reg  [7:0] data,
    output reg        valid
);
    localparam integer CLKS_PER_BIT = (CLOCK_HZ + (BAUD/2)) / BAUD;
    localparam integer HALF_BIT     = CLKS_PER_BIT / 2;
    localparam integer CW = (CLKS_PER_BIT <= 2) ? 1 : $clog2(CLKS_PER_BIT);
    localparam [1:0] RX_IDLE=2'd0,RX_START=2'd1,RX_DATA=2'd2,RX_STOP=2'd3;

    // rx_meta/rx_sync 是跨时钟域同步链；state 控制起始确认、8 位采样和停止位检查。
    reg rx_meta,rx_sync;
    reg [1:0] state;
    reg [CW-1:0] clock_count;
    reg [2:0] bit_index;
    reg [7:0] shift;

    always @(posedge clk) begin
        rx_meta <= rx;
        rx_sync <= rx_meta;
        if (rst) begin
            state       <= RX_IDLE;
            clock_count <= {CW{1'b0}};
            bit_index   <= 3'd0;
            shift       <= 8'd0;
            data        <= 8'd0;
            valid       <= 1'b0;
            rx_meta     <= 1'b1;
            rx_sync     <= 1'b1;
        end else begin
            valid <= 1'b0;
            case (state)
                // 检测下降沿后等待半个比特，在起始位中心再次确认仍为低，过滤短毛刺。
                RX_IDLE: if (!rx_sync) begin
                    clock_count <= HALF_BIT;
                    state <= RX_START;
                end
                RX_START: if (clock_count != 0)
                    clock_count <= clock_count - 1'b1;
                else if (!rx_sync) begin
                    clock_count <= CLKS_PER_BIT-1;
                    bit_index <= 3'd0;
                    state <= RX_DATA;
                end else state <= RX_IDLE;
                // 之后每隔一个完整比特周期在中心采样一次，共采 8 位。
                RX_DATA: if (clock_count != 0)
                    clock_count <= clock_count - 1'b1;
                else begin
                    shift[bit_index] <= rx_sync;
                    clock_count <= CLKS_PER_BIT-1;
                    if (bit_index == 3'd7) state <= RX_STOP;
                    else bit_index <= bit_index + 1'b1;
                end
                RX_STOP: if (clock_count != 0)
                    clock_count <= clock_count - 1'b1;
                else begin
                    if (rx_sync) begin
                        data  <= shift;
                        valid <= 1'b1;
                    end
                    state <= RX_IDLE;
                end
                default: state <= RX_IDLE;
            endcase
        end
    end
endmodule

password_lock_system/rtl/uart_tx_byte.v
`timescale 1ns/1ps

// UART 8N1 单字节发送器：1 位起始(0)、8 位数据 LSB 先发、无校验、1 位停止(1)。
// send 仅在 busy=0 时采纳；done 在完整 10 位帧发送结束时脉冲一个 clk。
module uart_tx_byte #(
    parameter integer CLOCK_HZ = 50_000_000,
    parameter integer BAUD     = 115_200
) (
    input  wire       clk,
    input  wire       rst,
    input  wire       send,
    input  wire [7:0] data,
    output reg        tx,
    output reg        busy,
    output reg        done
);
    // 加 BAUD/2 后做整数除法，相当于对每比特时钟数四舍五入。
    localparam integer CLKS_PER_BIT = (CLOCK_HZ + (BAUD/2)) / BAUD;
    localparam integer CW = (CLKS_PER_BIT <= 2) ? 1 : $clog2(CLKS_PER_BIT);
    reg [CW-1:0] clock_count;
    reg [3:0] bit_index;
    reg [9:0] frame;

    always @(posedge clk) begin
        if (rst) begin
            tx          <= 1'b1;
            busy        <= 1'b0;
            done        <= 1'b0;
            clock_count <= {CW{1'b0}};
            bit_index   <= 4'd0;
            frame       <= 10'h3ff;
        end else begin
            done <= 1'b0;
            if (!busy) begin
                tx <= 1'b1;
                if (send) begin
                    // frame[0] 是起始位，frame[1] 起依次为 data[0]~data[7]，最后为停止位。
                    frame       <= {1'b1,data,1'b0};
                    tx          <= 1'b0;
                    busy        <= 1'b1;
                    clock_count <= CLKS_PER_BIT-1;
                    bit_index   <= 4'd0;
                end
            end else if (clock_count != 0) begin
                clock_count <= clock_count - 1'b1;
            end else if (bit_index == 4'd9) begin
                tx   <= 1'b1;
                busy <= 1'b0;
                done <= 1'b1;
            end else begin
                bit_index   <= bit_index + 1'b1;
                tx          <= frame[bit_index+1'b1];
                clock_count <= CLKS_PER_BIT-1;
            end
        end
    end
endmodule

password_lock_system/rtl/rpi_camera_link.v
`timescale 1ns/1ps

// FPGA 到树莓派的可靠、可读 UART 事件链路。
// 协议：FPGA 发送 ASCII "ALARM\n"，树莓派收到完整命令后立即回复 "ACK\n"。
// 未收到 ACK 时每 RETRY_CYCLES 个系统时钟重发一次；默认 50 MHz 下约为 500 ms。
// 拍照请求被 link_waiting 独立锁存，因此解除蜂鸣报警不会取消尚未确认的拍照请求。
module rpi_camera_link #(
    parameter integer CLOCK_HZ     = 50_000_000,
    parameter integer BAUD         = 115_200,
    parameter integer RETRY_CYCLES = 25_000_000
) (
    input  wire clk,
    input  wire rst,
    input  wire photo_trigger,
    input  wire uart_rx,
    output wire uart_tx,
    output reg  link_waiting
);
    // message_index 指向 ALARM\n 的当前字节；ack_state 用于逐字节匹配 ACK\n。
    reg tx_send;
    reg [7:0] tx_data;
    wire tx_busy,tx_done;
    wire [7:0] rx_data;
    wire rx_valid;
    reg [2:0] message_index;
    reg message_active;
    reg byte_issued;
    reg [31:0] retry_count;
    reg [2:0] ack_state;

    uart_tx_byte #(.CLOCK_HZ(CLOCK_HZ),.BAUD(BAUD)) u_tx(
        .clk(clk),.rst(rst),.send(tx_send),.data(tx_data),
        .tx(uart_tx),.busy(tx_busy),.done(tx_done));
    uart_rx_byte #(.CLOCK_HZ(CLOCK_HZ),.BAUD(BAUD)) u_rx(
        .clk(clk),.rst(rst),.rx(uart_rx),.data(rx_data),.valid(rx_valid));

    // 将消息下标映射为待发送的 ASCII 字节，下标 5 对应换行符 0x0A。
    function [7:0] alarm_byte;
        input [2:0] index;
        begin
            case (index)
                3'd0: alarm_byte = "A";
                3'd1: alarm_byte = "L";
                3'd2: alarm_byte = "A";
                3'd3: alarm_byte = "R";
                3'd4: alarm_byte = "M";
                default: alarm_byte = 8'h0a;
            endcase
        end
    endfunction

    always @(posedge clk) begin
        if (rst) begin
            tx_send        <= 1'b0;
            tx_data        <= 8'd0;
            message_index  <= 3'd0;
            message_active <= 1'b0;
            byte_issued    <= 1'b0;
            retry_count    <= 32'd0;
            ack_state      <= 3'd0;
            link_waiting   <= 1'b0;
        end else begin
            tx_send <= 1'b0;

            // photo_trigger 来自第 4 次密码错误进入报警态时产生的单周期脉冲。
            if (photo_trigger) begin
                link_waiting   <= 1'b1;
                message_active <= 1'b1;
                message_index  <= 3'd0;
                byte_issued    <= 1'b0;
                retry_count    <= 32'd0;
                ack_state      <= 3'd0;
            end

            // 接收端允许从任意字节重新寻找 'A'，避免噪声或错位导致永久失步。
            if (rx_valid) begin
                case (ack_state)
                    3'd0: ack_state <= (rx_data == "A") ? 3'd1 : 3'd0;
                    3'd1: ack_state <= (rx_data == "C") ? 3'd2 :
                                           ((rx_data == "A") ? 3'd1 : 3'd0);
                    3'd2: ack_state <= (rx_data == "K") ? 3'd3 :
                                           ((rx_data == "A") ? 3'd1 : 3'd0);
                    3'd3: begin
                        ack_state <= (rx_data == 8'h0a) ? 3'd4 :
                                     ((rx_data == "A") ? 3'd1 : 3'd0);
                        if (rx_data == 8'h0a) begin
                            link_waiting <= 1'b0;
                            retry_count  <= 32'd0;
                        end
                    end
                    default: ack_state <= 3'd0;
                endcase
            end

            // 每个字节只向 UART 发送器发一次 send 脉冲，等待 tx_done 后再发下一字节。
            if (message_active) begin
                if (!byte_issued && !tx_busy) begin
                    tx_data     <= alarm_byte(message_index);
                    tx_send     <= 1'b1;
                    byte_issued <= 1'b1;
                end
                if (tx_done) begin
                    byte_issued <= 1'b0;
                    if (message_index == 3'd5) begin
                        message_active <= 1'b0;
                        message_index  <= 3'd0;
                        retry_count    <= 32'd0;
                    end else begin
                        message_index <= message_index + 1'b1;
                    end
                end
            // 一帧发完后等待 ACK；超时则从 'A' 开始重发完整命令。
            end else if (link_waiting) begin
                if (retry_count >= RETRY_CYCLES-1) begin
                    retry_count    <= 32'd0;
                    message_active <= 1'b1;
                    message_index  <= 3'd0;
                    byte_issued    <= 1'b0;
                end else retry_count <= retry_count + 1'b1;
            end
        end
    end
endmodule

password_lock_system/sim/tb_rpi_camera_link.sv
`timescale 1ns/1ps

// FPGA↔树莓派 UART 协议测试：触发 ALARM\n、接收 ACK\n 清请求、无 ACK 时自动重发。
module tb_rpi_camera_link;
    localparam integer CLOCK_HZ = 800;
    localparam integer BAUD = 100;
    // 800 Hz/100 baud=每比特 8 个时钟，便于测试任务精确构造 8N1 波形。
    localparam integer CLKS_PER_BIT = 8;
    reg clk=0,rst=1,photo_trigger=0,uart_rx=1;
    wire uart_tx,link_waiting;
    integer tx_starts=0;
    reg test_pass=0;

    always #5 clk=~clk;
    always @(negedge uart_tx) tx_starts = tx_starts + 1;

    rpi_camera_link #(.CLOCK_HZ(CLOCK_HZ),.BAUD(BAUD),.RETRY_CYCLES(200)) dut(
        .clk(clk),.rst(rst),.photo_trigger(photo_trigger),.uart_rx(uart_rx),
        .uart_tx(uart_tx),.link_waiting(link_waiting));

    // 在 uart_rx 上人工发送 1 起始+8 数据+1 停止位，数据按 LSB-first。
    task send_uart_byte(input [7:0] value);
        integer i;
        begin
            uart_rx=0; repeat(CLKS_PER_BIT) @(posedge clk);
            for(i=0;i<8;i=i+1) begin
                uart_rx=value[i]; repeat(CLKS_PER_BIT) @(posedge clk);
            end
            uart_rx=1; repeat(CLKS_PER_BIT) @(posedge clk);
        end
    endtask

    // tx_starts 统计 TX 下降沿，未确认一段时间后应看到新的消息起始沿。
    initial begin
        repeat(5) @(posedge clk); rst=0;
        @(posedge clk); photo_trigger=1;
        @(posedge clk); photo_trigger=0;
        repeat(10) @(posedge clk);
        if(!link_waiting || tx_starts==0) $fatal(1,"alarm request did not start");

        send_uart_byte("A"); send_uart_byte("C");
        send_uart_byte("K"); send_uart_byte(8'h0a);
        repeat(20) @(posedge clk);
        if(link_waiting) $fatal(1,"ACK did not clear pending request");

        @(posedge clk); photo_trigger=1;
        @(posedge clk); photo_trigger=0;
        repeat(900) @(posedge clk);
        if(tx_starts < 3) $fatal(1,"unacknowledged request was not retried");

        test_pass=1;
        $display("PASS tb_rpi_camera_link");
        $finish;
    end
endmodule

simulation_waveforms/10_extra_camera_uart/tb_rpi_camera_link.vcd
$date
   Tue Sep  8 20:48:46 2026
$end

$version
  2023.2
$end

$timescale
  1ps
$end

$scope module tb_rpi_camera_link $end
$var reg 1 V clk $end
$var reg 1 W rst $end
$var reg 1 X photo_trigger $end
$var reg 1 Y uart_rx $end
$var wire 1 D uart_tx $end
$var wire 1 Z link_waiting $end
$var integer 32 [ tx_starts [31:0] $end
$var reg 1 \ test_pass $end
$var parameter 0 ] CLOCK_HZ [31:0] $end
$var parameter 0 ^ BAUD [31:0] $end
$var parameter 0 _ CLKS_PER_BIT [31:0] $end
$scope module dut $end
$var wire 1 ! clk $end
$var wire 1 " rst $end
$var wire 1 C photo_trigger $end
$var wire 1 / uart_rx $end
$var wire 1 D uart_tx $end
$var reg 1 E link_waiting $end
$var reg 1 F tx_send $end
$var reg 8 G tx_data [7:0] $end
$var wire 1 H tx_busy $end
$var wire 1 I tx_done $end
$var wire 8 J rx_data [7:0] $end
$var wire 1 K rx_valid $end
$var reg 3 L message_index [2:0] $end
$var reg 1 M message_active $end
$var reg 1 N byte_issued $end
$var reg 32 O retry_count [31:0] $end
$var reg 3 P ack_state [2:0] $end
$var parameter 0 Q CLOCK_HZ [31:0] $end
$var parameter 0 R BAUD [31:0] $end
$var parameter 0 S RETRY_CYCLES [31:0] $end
$scope module u_tx $end
$var wire 1 ! clk $end
$var wire 1 " rst $end
$var wire 1 # send $end
$var wire 8 $ data [7:0] $end
$var reg 1 % tx $end
$var reg 1 & busy $end
$var reg 1 ' done $end
$var reg 3 ( clock_count [2:0] $end
$var reg 4 ) bit_index [3:0] $end
$var reg 10 * frame [9:0] $end
$var parameter 0 + CLOCK_HZ [31:0] $end
$var parameter 0 , BAUD [31:0] $end
$var parameter 0 - CLKS_PER_BIT [31:0] $end
$var parameter 0 . CW [31:0] $end
$upscope $end
$scope module u_rx $end
$var wire 1 ! clk $end
$var wire 1 " rst $end
$var wire 1 / rx $end
$var reg 8 0 data [7:0] $end
$var reg 1 1 valid $end
$var reg 1 2 rx_meta $end
$var reg 1 3 rx_sync $end
$var reg 2 4 state [1:0] $end
$var reg 3 5 clock_count [2:0] $end
$var reg 3 6 bit_index [2:0] $end
$var reg 8 7 shift [7:0] $end
$var parameter 0 8 CLOCK_HZ [31:0] $end
$var parameter 0 9 BAUD [31:0] $end
$var parameter 0 : CLKS_PER_BIT [31:0] $end
$var parameter 0 ; HALF_BIT [31:0] $end
$var parameter 0 < CW [31:0] $end
$var parameter 2 = RX_IDLE [1:0] $end
$var parameter 2 > RX_START [1:0] $end
$var parameter 2 ? RX_DATA [1:0] $end
$var parameter 2 @ RX_STOP [1:0] $end
$upscope $end
$scope function alarm_byte $end
$var reg 8 A alarm_byte [7:0] $end
$var reg 3 B index [2:0] $end
$upscope $end
$upscope $end
$scope task send_uart_byte $end
$var reg 8 T value [7:0] $end
$var integer 32 U i [31:0] $end
$upscope $end
$upscope $end
$enddefinitions $end

#0
$dumpvars
0!
1"
x#
bx $
x%
x&
x'
bx (
bx )
bx *
b1100100000 +
b1100100 ,
b1000 -
b11 .
1/
bx 0
x1
x2
x3
bx 4
bx 5
bx 6
bx 7
b1100100000 8
b1100100 9
b1000 :
b100 ;
b11 <
b0 =
b1 >
b10 ?
b11 @
bx A
bx B
0C
xD
xE
xF
bx G
xH
xI
bx J
xK
bx L
xM
xN
bx O
bx P
b1100100000 Q
b1100100 R
b11001000 S
bx T
bx U
0V
1W
0X
1Y
xZ
b0 [
0\
b1100100000 ]
b1100100 ^
b1000 _
$end

#5000
1!
0#
b0 $
1%
0&
0'
b0 (
b0 )
b1111111111 *
b0 0
01
12
13
b0 4
b0 5
b0 6
b0 7
1D
0E
0F
b0 G
0H
0I
b0 J
0K
b0 L
0M
0N
b0 O
b0 P
1V
0Z

#10000
0!
0V

#15000
1!
1V

#20000
0!
0V

#25000
1!
1V

#30000
0!
0V

#35000
1!
1V

#40000
0!
0V

#45000
1!
0"
1V
0W

#50000
0!
0V

#55000
1!
1C
1E
1M
1V
1X
1Z

#60000
0!
0V

#65000
1!
1#
b1000001 $
b1000001 A
b0 B
0C
1F
b1000001 G
1N
1V
0X

#70000
0!
0V

#75000
1!
0#
0%
1&
b111 (
b1010000010 *
0D
0F
1H
1V
b1 [

#80000
0!
0V

#85000
1!
b110 (
1V

#90000
0!
0V

#95000
1!
b101 (
1V

#100000
0!
0V

#105000
1!
b100 (
1V

#110000
0!
0V

#115000
1!
b11 (
1V

#120000
0!
0V

#125000
1!
b10 (
1V

#130000
0!
0V

#135000
1!
b1 (
1V

#140000
0!
0V

#145000
1!
b0 (
1V

#150000
0!
0V

#155000
1!
1%
b111 (
b1 )
1D
1V

#160000
0!
0V

#165000
1!
b110 (
0/
02
b1000001 T
1V
0Y

#170000
0!
0V

#175000
1!
b101 (
03
1V

#180000
0!
0V

#185000
1!
b100 (
b1 4
b100 5
1V

#190000
0!
0V

#195000
1!
b11 (
b11 5
1V

#200000
0!
0V

#205000
1!
b10 (
b10 5
1V

#210000
0!
0V

#215000
1!
b1 (
b1 5
1V

#220000
0!
0V

#225000
1!
b0 (
b0 5
1V

#230000
0!
0V

#235000
1!
0%
b111 (
b10 )
b10 4
b111 5
0D
1V
b10 [

#240000
0!
0V

#245000
1!
b110 (
1/
12
b110 5
b0 U
1V
1Y

#250000
0!
0V

#255000
1!
b101 (
13
b101 5
1V

#260000
0!
0V

#265000
1!
b100 (
b100 5
1V

#270000
0!
0V

#275000
1!
b11 (
b11 5
1V

#280000
0!
0V

#285000
1!
b10 (
b10 5
1V

#290000
0!
0V

#295000
1!
b1 (
b1 5
1V

#300000
0!
0V

#305000
1!
b0 (
b0 5
1V

#310000
0!
0V

#315000
1!
b111 (
b11 )
b111 5
b1 6
b1 7
1V

#320000
0!
0V

#325000
1!
b110 (
0/
02
b110 5
b1 U
1V
0Y

#330000
0!
0V

#335000
1!
b101 (
03
b101 5
1V

#340000
0!
0V

#345000
1!
b100 (
b100 5
1V

#350000
0!
0V

#355000
1!
b11 (
b11 5
1V

#360000
0!
0V

#365000
1!
b10 (
b10 5
1V

#370000
0!
0V

#375000
1!
b1 (
b1 5
1V

#380000
0!
0V

#385000
1!
b0 (
b0 5
1V

#390000
0!
0V

#395000
1!
b111 (
b100 )
b111 5
b10 6
1V

#400000
0!
0V

#405000
1!
b110 (
b110 5
b10 U
1V

#410000
0!
0V

#415000
1!
b101 (
b101 5
1V

#420000
0!
0V

#425000
1!
b100 (
b100 5
1V

#430000
0!
0V

#435000
1!
b11 (
b11 5
1V

#440000
0!
0V

#445000
1!
b10 (
b10 5
1V

#450000
0!
0V

#455000
1!
b1 (
b1 5
1V

#460000
0!
0V

#465000
1!
b0 (
b0 5
1V

#470000
0!
0V

#475000
1!
b111 (
b101 )
b111 5
b11 6
1V

#480000
0!
0V

#485000
1!
b110 (
b110 5
b11 U
1V

#490000
0!
0V

#495000
1!
b101 (
b101 5
1V

#500000
0!
0V

#505000
1!
b100 (
b100 5
1V

#510000
0!
0V

#515000
1!
b11 (
b11 5
1V

#520000
0!
0V

#525000
1!
b10 (
b10 5
1V

#530000
0!
0V

#535000
1!
b1 (
b1 5
1V

#540000
0!
0V

#545000
1!
b0 (
b0 5
1V

#550000
0!
0V

#555000
1!
b111 (
b110 )
b111 5
b100 6
1V

#560000
0!
0V

#565000
1!
b110 (
b110 5
b100 U
1V

#570000
0!
0V

#575000
1!
b101 (
b101 5
1V

#580000
0!
0V

#585000
1!
b100 (
b100 5
1V

#590000
0!
0V

#595000
1!
b11 (
b11 5
1V

#600000
0!
0V

#605000
1!
b10 (
b10 5
1V

#610000
0!
0V

#615000
1!
b1 (
b1 5
1V

#620000
0!
0V

#625000
1!
b0 (
b0 5
1V

#630000
0!
0V

#635000
1!
1%
b111 (
b111 )
b111 5
b101 6
1D
1V

#640000
0!
0V

#645000
1!
b110 (
b110 5
b101 U
1V

#650000
0!
0V

#655000
1!
b101 (
b101 5
1V

#660000
0!
0V

#665000
1!
b100 (
b100 5
1V

#670000
0!
0V

#675000
1!
b11 (
b11 5
1V

#680000
0!
0V

#685000
1!
b10 (
b10 5
1V

#690000
0!
0V

#695000
1!
b1 (
b1 5
1V

#700000
0!
0V

#705000
1!
b0 (
b0 5
1V

#710000
0!
0V

#715000
1!
0%
b111 (
b1000 )
b111 5
b110 6
0D
1V
b11 [

#720000
0!
0V

#725000
1!
b110 (
1/
12
b110 5
b110 U
1V
1Y

#730000
0!
0V

#735000
1!
b101 (
13
b101 5
1V

#740000
0!
0V

#745000
1!
b100 (
b100 5
1V

#750000
0!
0V

#755000
1!
b11 (
b11 5
1V

#760000
0!
0V

#765000
1!
b10 (
b10 5
1V

#770000
0!
0V

#775000
1!
b1 (
b1 5
1V

#780000
0!
0V

#785000
1!
b0 (
b0 5
1V

#790000
0!
0V

#795000
1!
1%
b111 (
b1001 )
b111 5
b111 6
b1000001 7
1D
1V

#800000
0!
0V

#805000
1!
b110 (
0/
02
b110 5
b111 U
1V
0Y

#810000
0!
0V

#815000
1!
b101 (
03
b101 5
1V

#820000
0!
0V

#825000
1!
b100 (
b100 5
1V

#830000
0!
0V

#835000
1!
b11 (
b11 5
1V

#840000
0!
0V

#845000
1!
b10 (
b10 5
1V

#850000
0!
0V

#855000
1!
b1 (
b1 5
1V

#860000
0!
0V

#865000
1!
b0 (
b0 5
1V

#870000
0!
0V

#875000
1!
0&
1'
b11 4
b111 5
0H
1I
1V

#880000
0!
0V

#885000
1!
0'
1/
12
b110 5
0I
b1 L
0N
b1000 U
1V
1Y

#890000
0!
0V

#895000
1!
1#
b1001100 $
13
b101 5
b1001100 A
b1 B
1F
b1001100 G
1N
1V

#900000
0!
0V

#905000
1!
0#
0%
1&
b111 (
b0 )
b1010011000 *
b100 5
0D
0F
1H
1V
b100 [

#910000
0!
0V

#915000
1!
b110 (
b11 5
1V

#920000
0!
0V

#925000
1!
b101 (
b10 5
1V

#930000
0!
0V

#935000
1!
b100 (
b1 5
1V

#940000
0!
0V

#945000
1!
b11 (
b0 5
1V

#950000
0!
0V

#955000
1!
b10 (
b1000001 0
11
b0 4
b1000001 J
1K
1V

#960000
0!
0V

#965000
1!
b1 (
0/
01
02
0K
b1 P
b1000011 T
1V
0Y

#970000
0!
0V

#975000
1!
b0 (
03
1V

#980000
0!
0V

#985000
1!
b111 (
b1 )
b1 4
b100 5
1V

#990000
0!
0V

#995000
1!
b110 (
b11 5
1V

#1000000
0!
0V

#1005000
1!
b101 (
b10 5
1V

#1010000
0!
0V

#1015000
1!
b100 (
b1 5
1V

#1020000
0!
0V

#1025000
1!
b11 (
b0 5
1V

#1030000
0!
0V

#1035000
1!
b10 (
b10 4
b111 5
b0 6
1V

#1040000
0!
0V

#1045000
1!
b1 (
1/
12
b110 5
b0 U
1V
1Y

#1050000
0!
0V

#1055000
1!
b0 (
13
b101 5
1V

#1060000
0!
0V

#1065000
1!
b111 (
b10 )
b100 5
1V

#1070000
0!
0V

#1075000
1!
b110 (
b11 5
1V

#1080000
0!
0V

#1085000
1!
b101 (
b10 5
1V

#1090000
0!
0V

#1095000
1!
b100 (
b1 5
1V

#1100000
0!
0V

#1105000
1!
b11 (
b0 5
1V

#1110000
0!
0V

#1115000
1!
b10 (
b111 5
b1 6
1V

#1120000
0!
0V

#1125000
1!
b1 (
b110 5
b1 U
1V

#1130000
0!
0V

#1135000
1!
b0 (
b101 5
1V

#1140000
0!
0V

#1145000
1!
1%
b111 (
b11 )
b100 5
1D
1V

#1150000
0!
0V

#1155000
1!
b110 (
b11 5
1V

#1160000
0!
0V

#1165000
1!
b101 (
b10 5
1V

#1170000
0!
0V

#1175000
1!
b100 (
b1 5
1V

#1180000
0!
0V

#1185000
1!
b11 (
b0 5
1V

#1190000
0!
0V

#1195000
1!
b10 (
b111 5
b10 6
b1000011 7
1V

#1200000
0!
0V

#1205000
1!
b1 (
0/
02
b110 5
b10 U
1V
0Y

#1210000
0!
0V

#1215000
1!
b0 (
03
b101 5
1V

#1220000
0!
0V

#1225000
1!
b111 (
b100 )
b100 5
1V

#1230000
0!
0V

#1235000
1!
b110 (
b11 5
1V

#1240000
0!
0V

#1245000
1!
b101 (
b10 5
1V

#1250000
0!
0V

#1255000
1!
b100 (
b1 5
1V

#1260000
0!
0V

#1265000
1!
b11 (
b0 5
1V

#1270000
0!
0V

#1275000
1!
b10 (
b111 5
b11 6
1V

#1280000
0!
0V

#1285000
1!
b1 (
b110 5
b11 U
1V

#1290000
0!
0V

#1295000
1!
b0 (
b101 5
1V

#1300000
0!
0V

#1305000
1!
0%
b111 (
b101 )
b100 5
0D
1V
b101 [

#1310000
0!
0V

#1315000
1!
b110 (
b11 5
1V

#1320000
0!
0V

#1325000
1!
b101 (
b10 5
1V

#1330000
0!
0V

#1335000
1!
b100 (
b1 5
1V

#1340000
0!
0V

#1345000
1!
b11 (
b0 5
1V

#1350000
0!
0V

#1355000
1!
b10 (
b111 5
b100 6
1V

#1360000
0!
0V

#1365000
1!
b1 (
b110 5
b100 U
1V

#1370000
0!
0V

#1375000
1!
b0 (
b101 5
1V

#1380000
0!
0V

#1385000
1!
b111 (
b110 )
b100 5
1V

#1390000
0!
0V

#1395000
1!
b110 (
b11 5
1V

#1400000
0!
0V

#1405000
1!
b101 (
b10 5
1V

#1410000
0!
0V

#1415000
1!
b100 (
b1 5
1V

#1420000
0!
0V

#1425000
1!
b11 (
b0 5
1V

#1430000
0!
0V

#1435000
1!
b10 (
b111 5
b101 6
1V

#1440000
0!
0V

#1445000
1!
b1 (
b110 5
b101 U
1V

#1450000
0!
0V

#1455000
1!
b0 (
b101 5
1V

#1460000
0!
0V

#1465000
1!
1%
b111 (
b111 )
b100 5
1D
1V

#1470000
0!
0V

#1475000
1!
b110 (
b11 5
1V

#1480000
0!
0V

#1485000
1!
b101 (
b10 5
1V

#1490000
0!
0V

#1495000
1!
b100 (
b1 5
1V

#1500000
0!
0V

#1505000
1!
b11 (
b0 5
1V

#1510000
0!
0V

#1515000
1!
b10 (
b111 5
b110 6
1V

#1520000
0!
0V

#1525000
1!
b1 (
1/
12
b110 5
b110 U
1V
1Y

#1530000
0!
0V

#1535000
1!
b0 (
13
b101 5
1V

#1540000
0!
0V

#1545000
1!
0%
b111 (
b1000 )
b100 5
0D
1V
b110 [

#1550000
0!
0V

#1555000
1!
b110 (
b11 5
1V

#1560000
0!
0V

#1565000
1!
b101 (
b10 5
1V

#1570000
0!
0V

#1575000
1!
b100 (
b1 5
1V

#1580000
0!
0V

#1585000
1!
b11 (
b0 5
1V

#1590000
0!
0V

#1595000
1!
b10 (
b111 5
b111 6
1V

#1600000
0!
0V

#1605000
1!
b1 (
0/
02
b110 5
b111 U
1V
0Y

#1610000
0!
0V

#1615000
1!
b0 (
03
b101 5
1V

#1620000
0!
0V

#1625000
1!
1%
b111 (
b1001 )
b100 5
1D
1V

#1630000
0!
0V

#1635000
1!
b110 (
b11 5
1V

#1640000
0!
0V

#1645000
1!
b101 (
b10 5
1V

#1650000
0!
0V

#1655000
1!
b100 (
b1 5
1V

#1660000
0!
0V

#1665000
1!
b11 (
b0 5
1V

#1670000
0!
0V

#1675000
1!
b10 (
b11 4
b111 5
1V

#1680000
0!
0V

#1685000
1!
b1 (
1/
12
b110 5
b1000 U
1V
1Y

#1690000
0!
0V

#1695000
1!
b0 (
13
b101 5
1V

#1700000
0!
0V

#1705000
1!
0&
1'
b100 5
0H
1I
1V

#1710000
0!
0V

#1715000
1!
0'
b11 5
0I
b10 L
0N
1V

#1720000
0!
0V

#1725000
1!
1#
b1000001 $
b10 5
b1000001 A
b10 B
1F
b1000001 G
1N
1V

#1730000
0!
0V

#1735000
1!
0#
0%
1&
b111 (
b0 )
b1010000010 *
b1 5
0D
0F
1H
1V
b111 [

#1740000
0!
0V

#1745000
1!
b110 (
b0 5
1V

#1750000
0!
0V

#1755000
1!
b101 (
b1000011 0
11
b0 4
b1000011 J
1K
1V

#1760000
0!
0V

#1765000
1!
b100 (
0/
01
02
0K
b10 P
b1001011 T
1V
0Y

#1770000
0!
0V

#1775000
1!
b11 (
03
1V

#1780000
0!
0V

#1785000
1!
b10 (
b1 4
b100 5
1V

#1790000
0!
0V

#1795000
1!
b1 (
b11 5
1V

#1800000
0!
0V

#1805000
1!
b0 (
b10 5
1V

#1810000
0!
0V

#1815000
1!
1%
b111 (
b1 )
b1 5
1D
1V

#1820000
0!
0V

#1825000
1!
b110 (
b0 5
1V

#1830000
0!
0V

#1835000
1!
b101 (
b10 4
b111 5
b0 6
1V

#1840000
0!
0V

#1845000
1!
b100 (
1/
12
b110 5
b0 U
1V
1Y

#1850000
0!
0V

#1855000
1!
b11 (
13
b101 5
1V

#1860000
0!
0V

#1865000
1!
b10 (
b100 5
1V

#1870000
0!
0V

#1875000
1!
b1 (
b11 5
1V

#1880000
0!
0V

#1885000
1!
b0 (
b10 5
1V

#1890000
0!
0V

#1895000
1!
0%
b111 (
b10 )
b1 5
0D
1V
b1000 [

#1900000
0!
0V

#1905000
1!
b110 (
b0 5
1V

#1910000
0!
0V

#1915000
1!
b101 (
b111 5
b1 6
1V

#1920000
0!
0V

#1925000
1!
b100 (
b110 5
b1 U
1V

#1930000
0!
0V

#1935000
1!
b11 (
b101 5
1V

#1940000
0!
0V

#1945000
1!
b10 (
b100 5
1V

#1950000
0!
0V

#1955000
1!
b1 (
b11 5
1V

#1960000
0!
0V

#1965000
1!
b0 (
b10 5
1V

#1970000
0!
0V

#1975000
1!
b111 (
b11 )
b1 5
1V

#1980000
0!
0V

#1985000
1!
b110 (
b0 5
1V

#1990000
0!
0V

#1995000
1!
b101 (
b111 5
b10 6
1V

#2000000
0!
0V

#2005000
1!
b100 (
0/
02
b110 5
b10 U
1V
0Y

#2010000
0!
0V

#2015000
1!
b11 (
03
b101 5
1V

#2020000
0!
0V

#2025000
1!
b10 (
b100 5
1V

#2030000
0!
0V

#2035000
1!
b1 (
b11 5
1V

#2040000
0!
0V

#2045000
1!
b0 (
b10 5
1V

#2050000
0!
0V

#2055000
1!
b111 (
b100 )
b1 5
1V

#2060000
0!
0V

#2065000
1!
b110 (
b0 5
1V

#2070000
0!
0V

#2075000
1!
b101 (
b111 5
b11 6
1V

#2080000
0!
0V

#2085000
1!
b100 (
1/
12
b110 5
b11 U
1V
1Y

#2090000
0!
0V

#2095000
1!
b11 (
13
b101 5
1V

#2100000
0!
0V

#2105000
1!
b10 (
b100 5
1V

#2110000
0!
0V

#2115000
1!
b1 (
b11 5
1V

#2120000
0!
0V

#2125000
1!
b0 (
b10 5
1V

#2130000
0!
0V

#2135000
1!
b111 (
b101 )
b1 5
1V

#2140000
0!
0V

#2145000
1!
b110 (
b0 5
1V

#2150000
0!
0V

#2155000
1!
b101 (
b111 5
b100 6
b1001011 7
1V

#2160000
0!
0V

#2165000
1!
b100 (
0/
02
b110 5
b100 U
1V
0Y

#2170000
0!
0V

#2175000
1!
b11 (
03
b101 5
1V

#2180000
0!
0V

#2185000
1!
b10 (
b100 5
1V

#2190000
0!
0V

#2195000
1!
b1 (
b11 5
1V

#2200000
0!
0V

#2205000
1!
b0 (
b10 5
1V

#2210000
0!
0V

#2215000
1!
b111 (
b110 )
b1 5
1V

#2220000
0!
0V

#2225000
1!
b110 (
b0 5
1V

#2230000
0!
0V

#2235000
1!
b101 (
b111 5
b101 6
1V

#2240000
0!
0V

