password_lock_system/rtl/spi_byte_master.v
`timescale 1ns/1ps

// SPI Mode 0 单字节主机：空闲时 SCLK=0，上升沿采 MISO，下降沿更新 MOSI，MSB 先传。
// HALF_DIV=2、输入 50 MHz 时 SCLK=12.5 MHz；CS# 由上层 Flash 事务状态机控制。
module spi_byte_master #(
    parameter integer HALF_DIV = 2
) (
    input  wire       clk,
    input  wire       rst,
    input  wire       start,
    input  wire [7:0] tx_data,
    input  wire       miso,
    output reg        sclk,
    output reg        mosi,
    output reg  [7:0] rx_data,
    output reg        busy,
    output reg        done
);
    localparam integer DW = (HALF_DIV <= 2) ? 1 : $clog2(HALF_DIV);
    reg [DW-1:0] div_count;
    reg [7:0] tx_shift;
    reg [7:0] rx_shift;
    // edge_count 统计已经完成的上升沿采样次数，达到 8 表示一个字节接收完毕。
    reg [3:0] edge_count;

    always @(posedge clk) begin
        if (rst) begin
            sclk      <= 1'b0;
            mosi      <= 1'b0;
            rx_data   <= 8'h00;
            busy      <= 1'b0;
            done      <= 1'b0;
            div_count <= {DW{1'b0}};
            tx_shift  <= 8'h00;
            rx_shift  <= 8'h00;
            edge_count <= 4'd0;
        end else begin
            done <= 1'b0;
            if (!busy) begin
                sclk <= 1'b0;
                if (start) begin
                    busy       <= 1'b1;
                    tx_shift   <= tx_data;
                    rx_shift   <= 8'h00;
                    mosi       <= tx_data[7];
                    edge_count <= 4'd0;
                    div_count  <= {DW{1'b0}};
                end
            end else if (div_count == HALF_DIV-1) begin
                div_count <= {DW{1'b0}};
                // 上升沿采样返回位；下降沿移出下一位，符合 Mode 0 时序。
                if (!sclk) begin
                    sclk <= 1'b1;
                    rx_shift <= {rx_shift[6:0], miso};
                    edge_count <= edge_count + 1'b1;
                end else begin
                    sclk <= 1'b0;
                    if (edge_count == 4'd8) begin
                        busy    <= 1'b0;
                        done    <= 1'b1;
                        rx_data <= rx_shift;
                        mosi    <= 1'b0;
                    end else begin
                        tx_shift <= {tx_shift[6:0], 1'b0};
                        mosi     <= tx_shift[6];
                    end
                end
            end else begin
                div_count <= div_count + 1'b1;
            end
        end
    end
endmodule

password_lock_system/rtl/w25q64_password_store.v
`timescale 1ns/1ps

// W25Q64 双扇区掉电安全密码日志：A=0x000000，B=0x001000，每次写入非活动扇区。
// 16 字节记录格式：魔数[4]、代数[4]、密码[2]、密码反码[2]、CRC16[2]、提交标记[2]。
// 只有写后回读校验完全通过，current_password 才更新；断电时旧扇区仍保留有效副本。
module w25q64_password_store #(
    parameter integer CLOCK_HZ = 50_000_000,
    parameter integer SPI_HALF_DIV = 2,
    parameter integer CS_HIGH_CYCLES = 4,
    parameter integer ERASE_TIMEOUT_CYCLES = CLOCK_HZ,
    parameter integer PROGRAM_TIMEOUT_CYCLES = CLOCK_HZ/50
) (
    input  wire        clk,
    input  wire        rst,
    input  wire        save_request,
    input  wire [15:0] save_password,
    input  wire        flash_miso,
    output wire        flash_sclk,
    output wire        flash_mosi,
    output reg         flash_cs_n,
    output wire        flash_wp_n,
    output wire        flash_hold_n,
    output reg         init_done,
    output reg [15:0]  current_password,
    output reg         save_done,
    output reg         save_success,
    output reg         flash_fault
);
    // MAGIC="PLK1"，COMMIT 表示该条记录已完整写成；代数较大的有效记录为最新记录。
    localparam [31:0] MAGIC = 32'h504C4B31;
    localparam [15:0] COMMIT = 16'hA55A;
    localparam [5:0] S_ID=0, S_READ_A=1, S_READ_B=2, S_SELECT=3, S_IDLE=4,
                     S_WREN_ERASE=5, S_ERASE=6, S_POLL_ERASE=7,
                     S_WREN_PROGRAM=8, S_PROGRAM=9, S_POLL_PROGRAM=10,
                     S_VERIFY=11, S_FINISH=12, S_FAIL=13;

    reg [5:0] state;
    reg [5:0] byte_index;
    reg [31:0] timeout_count;
    localparam integer CGW = (CS_HIGH_CYCLES <= 2) ? 1 : $clog2(CS_HIGH_CYCLES + 1);
    reg [CGW-1:0] cs_high_count;
    reg awaiting_byte;
    reg launch_pending;
    reg spi_start;
    reg [7:0] spi_tx;
    wire [7:0] spi_rx;
    wire spi_busy, spi_done;
    reg [127:0] record_a, record_b, verify_record, new_record;
    reg [31:0] generation;
    reg active_bank;
    reg target_bank;
    reg id_valid;
    reg [23:0] jedec_id;
    reg [15:0] requested_password;
    // record_valid 同时检查格式、BCD、反码、CRC 和提交标记，任一不符即视为无效记录。
    wire valid_a = record_valid(record_a);
    wire valid_b = record_valid(record_b);
    wire valid_verify = record_valid(verify_record);
    wire [23:0] target_address = target_bank ? 24'h001000 : 24'h000000;

    // WP# 与 HOLD# 始终拉高，表示不启用硬件写保护和总线暂停。
    assign flash_wp_n   = 1'b1;
    assign flash_hold_n = 1'b1;

    spi_byte_master #(.HALF_DIV(SPI_HALF_DIV)) u_spi (
        .clk(clk), .rst(rst), .start(spi_start), .tx_data(spi_tx),
        .miso(flash_miso), .sclk(flash_sclk), .mosi(flash_mosi),
        .rx_data(spi_rx), .busy(spi_busy), .done(spi_done)
    );

    // 对记录前 12 字节计算 CRC-16/CCITT，多项式 0x1021，初值 0xFFFF。
    function [15:0] crc16_96;
        input [95:0] data;
        integer i;
        reg [15:0] crc;
        begin
            crc = 16'hFFFF;
            for (i=95; i>=0; i=i-1) begin
                if (crc[15] ^ data[i])
                    crc = {crc[14:0],1'b0} ^ 16'h1021;
                else
                    crc = {crc[14:0],1'b0};
            end
            crc16_96 = crc;
        end
    endfunction

    function bcd_valid;
        input [15:0] value;
        begin
            bcd_valid = (value[15:12] <= 9) && (value[11:8] <= 9) &&
                        (value[7:4] <= 9) && (value[3:0] <= 9);
        end
    endfunction

    function record_valid;
        input [127:0] record;
        begin
            record_valid = (record[127:96] == MAGIC) &&
                           bcd_valid(record[63:48]) &&
                           (record[47:32] == ~record[63:48]) &&
                           (record[31:16] == crc16_96(record[127:32])) &&
                           (record[15:0] == COMMIT);
        end
    endfunction

    function [7:0] record_byte;
        input [127:0] record;
        input [4:0] index;
        begin
            case (index)
                0: record_byte=record[127:120]; 1: record_byte=record[119:112];
                2: record_byte=record[111:104]; 3: record_byte=record[103:96];
                4: record_byte=record[95:88];   5: record_byte=record[87:80];
                6: record_byte=record[79:72];   7: record_byte=record[71:64];
                8: record_byte=record[63:56];   9: record_byte=record[55:48];
                10:record_byte=record[47:40];  11: record_byte=record[39:32];
                12:record_byte=record[31:24];  13: record_byte=record[23:16];
                14:record_byte=record[15:8];   default: record_byte=record[7:0];
            endcase
        end
    endfunction

    // 按状态和字节下标产生 SPI 命令流：9F/03/06/20/02/05 分别为读 ID、读、写使能、擦除、页编程、读状态。
    function [7:0] transaction_byte;
        input [5:0] st;
        input [5:0] index;
        begin
            transaction_byte = 8'h00;
            case (st)
                S_ID: transaction_byte = (index == 0) ? 8'h9F : 8'h00;
                S_READ_A, S_READ_B, S_VERIFY: begin
                    case (index)
                        0: transaction_byte=8'h03;
                        1: transaction_byte=(st==S_READ_B || (st==S_VERIFY && target_bank)) ? 8'h00 : 8'h00;
                        2: transaction_byte=(st==S_READ_B || (st==S_VERIFY && target_bank)) ? 8'h10 : 8'h00;
                        3: transaction_byte=8'h00;
                        default: transaction_byte=8'h00;
                    endcase
                end
                S_WREN_ERASE, S_WREN_PROGRAM: transaction_byte=8'h06;
                S_ERASE: begin
                    case(index)
                        0: transaction_byte=8'h20;
                        1: transaction_byte=target_address[23:16];
                        2: transaction_byte=target_address[15:8];
                        default: transaction_byte=target_address[7:0];
                    endcase
                end
                S_PROGRAM: begin
                    case(index)
                        0: transaction_byte=8'h02;
                        1: transaction_byte=target_address[23:16];
                        2: transaction_byte=target_address[15:8];
                        3: transaction_byte=target_address[7:0];
                        default: transaction_byte=record_byte(new_record,index-4);
                    endcase
                end
                S_POLL_ERASE, S_POLL_PROGRAM:
                    transaction_byte=(index==0) ? 8'h05 : 8'h00;
                default: transaction_byte=8'h00;
            endcase
        end
    endfunction

    // 一条 SPI 命令结束：释放 CS#，并保证下一条命令前有足够的片选高电平间隔。
    task finish_transaction;
        begin
            flash_cs_n <= 1'b1;
            byte_index <= 0;
            awaiting_byte <= 1'b0;
            launch_pending <= 1'b0;
            cs_high_count <= CS_HIGH_CYCLES;
        end
    endtask

    always @(posedge clk) begin
        if (rst) begin
            state <= S_ID;
            byte_index <= 0;
            timeout_count <= 0;
            cs_high_count <= CS_HIGH_CYCLES;
            awaiting_byte <= 0;
            launch_pending <= 0;
            spi_start <= 0;
            spi_tx <= 0;
            flash_cs_n <= 1;
            init_done <= 0;
            current_password <= 16'h1234;
            save_done <= 0;
            save_success <= 0;
            flash_fault <= 0;
            record_a <= 0; record_b <= 0; verify_record <= 0; new_record <= 0;
            generation <= 0;
            active_bank <= 0; target_bank <= 1;
            id_valid <= 0; jedec_id <= 0;
            requested_password <= 16'h1234;
        end else begin
            spi_start <= 1'b0;
            save_done <= 1'b0;

            if (cs_high_count != 0)
                cs_high_count <= cs_high_count - 1'b1;

            if ((state == S_POLL_ERASE && timeout_count < ERASE_TIMEOUT_CYCLES) ||
                (state == S_POLL_PROGRAM && timeout_count < PROGRAM_TIMEOUT_CYCLES))
                timeout_count <= timeout_count + 1'b1;

            // 两级启动握手避免在 SPI 主机仍 busy 时重复触发同一字节。
            if (launch_pending && !spi_busy) begin
                spi_start <= 1'b1;
                awaiting_byte <= 1'b1;
                launch_pending <= 1'b0;
            end else if (!awaiting_byte && !launch_pending && !spi_busy &&
                cs_high_count == 0 &&
                state != S_SELECT && state != S_IDLE &&
                state != S_FINISH && state != S_FAIL) begin
                if (flash_cs_n)
                    flash_cs_n <= 1'b0;
                spi_tx <= transaction_byte(state, byte_index);
                launch_pending <= 1'b1;
            end

            // 字节完成后按当前事务收集返回值或推进状态；读记录时前 4 字节是命令和地址。
            if (spi_done && awaiting_byte) begin
                awaiting_byte <= 1'b0;
                case (state)
                    S_ID: begin
                        if (byte_index > 0)
                            jedec_id <= {jedec_id[15:0],spi_rx};
                        if (byte_index == 3) begin
                            finish_transaction;
                            id_valid <= ({jedec_id[15:0],spi_rx} != 24'h000000) &&
                                        ({jedec_id[15:0],spi_rx} != 24'hFFFFFF);
                            state <= S_READ_A;
                        end else byte_index <= byte_index + 1'b1;
                    end
                    S_READ_A: begin
                        if (byte_index >= 4)
                            record_a <= {record_a[119:0],spi_rx};
                        if (byte_index == 19) begin finish_transaction; state <= S_READ_B; end
                        else byte_index <= byte_index + 1'b1;
                    end
                    S_READ_B: begin
                        if (byte_index >= 4)
                            record_b <= {record_b[119:0],spi_rx};
                        if (byte_index == 19) begin finish_transaction; state <= S_SELECT; end
                        else byte_index <= byte_index + 1'b1;
                    end
                    S_WREN_ERASE: begin finish_transaction; state <= S_ERASE; end
                    S_ERASE: begin
                        if (byte_index == 3) begin
                            finish_transaction; state <= S_POLL_ERASE; timeout_count <= 0;
                        end else byte_index <= byte_index + 1'b1;
                    end
                    S_POLL_ERASE: begin
                        if (byte_index == 1) begin
                            finish_transaction;
                            if (!spi_rx[0]) state <= S_WREN_PROGRAM;
                            else if (timeout_count >= ERASE_TIMEOUT_CYCLES-1) state <= S_FAIL;
                        end else byte_index <= byte_index + 1'b1;
                    end
                    S_WREN_PROGRAM: begin finish_transaction; state <= S_PROGRAM; end
                    S_PROGRAM: begin
                        if (byte_index == 19) begin
                            finish_transaction; state <= S_POLL_PROGRAM; timeout_count <= 0;
                        end else byte_index <= byte_index + 1'b1;
                    end
                    S_POLL_PROGRAM: begin
                        if (byte_index == 1) begin
                            finish_transaction;
                            if (!spi_rx[0]) state <= S_VERIFY;
                            else if (timeout_count >= PROGRAM_TIMEOUT_CYCLES-1) state <= S_FAIL;
                        end else byte_index <= byte_index + 1'b1;
                    end
                    S_VERIFY: begin
                        if (byte_index >= 4)
                            verify_record <= {verify_record[119:0],spi_rx};
                        if (byte_index == 19) begin finish_transaction; state <= S_FINISH; end
                        else byte_index <= byte_index + 1'b1;
                    end
                    default: ;
                endcase
            end

            // 非逐字节状态：上电选择最新记录、等待保存请求、校验提交或报告失败。
            case (state)
                S_SELECT: begin
                    // 上电时从两个扇区中选择有效且 generation 最大者；均无效则回退默认密码 1234。
                    flash_cs_n <= 1'b1;
                    flash_fault <= ~id_valid;
                    if (valid_a && valid_b) begin
                        if (record_b[95:64] > record_a[95:64]) begin
                            current_password <= record_b[63:48]; generation <= record_b[95:64]; active_bank <= 1;
                        end else begin
                            current_password <= record_a[63:48]; generation <= record_a[95:64]; active_bank <= 0;
                        end
                    end else if (valid_a) begin
                        current_password <= record_a[63:48]; generation <= record_a[95:64]; active_bank <= 0;
                    end else if (valid_b) begin
                        current_password <= record_b[63:48]; generation <= record_b[95:64]; active_bank <= 1;
                    end else begin
                        current_password <= 16'h1234; generation <= 0; active_bank <= 0;
                    end
                    init_done <= 1'b1;
                    state <= S_IDLE;
                end
                S_IDLE: begin
                    // 锁存管理员新密码，目标切换到另一扇区，然后执行擦除→编程→轮询→回读。
                    flash_cs_n <= 1'b1;
                    if (save_request) begin
                        requested_password <= save_password;
                        target_bank <= ~active_bank;
                        new_record[127:32] <= {MAGIC,generation+1'b1,save_password,~save_password};
                        new_record[31:16] <= crc16_96({MAGIC,generation+1'b1,save_password,~save_password});
                        new_record[15:0] <= COMMIT;
                        verify_record <= 0;
                        timeout_count <= 0;
                        save_success <= 0;
                        flash_fault <= 0;
                        state <= S_WREN_ERASE;
                    end
                end
                S_FINISH: begin
                    // 回读记录必须既“格式有效”又逐位等于 new_record，才对外宣布保存成功。
                    flash_cs_n <= 1'b1;
                    if (valid_verify && verify_record == new_record) begin
                        current_password <= requested_password;
                        generation <= generation + 1'b1;
                        active_bank <= target_bank;
                        save_success <= 1'b1;
                        flash_fault <= 1'b0;
                    end else begin
                        save_success <= 1'b0;
                        flash_fault <= 1'b1;
                    end
                    save_done <= 1'b1;
                    state <= S_IDLE;
                end
                S_FAIL: begin
                    finish_transaction;
                    save_success <= 1'b0;
                    save_done <= 1'b1;
                    flash_fault <= 1'b1;
                    state <= S_IDLE;
                end
                default: ;
            endcase
        end
    end
endmodule

password_lock_system/sim/tb_flash_default_fail.sv
`timescale 1ns/1ps
// Flash 异常场景：MISO 永远为 1，模拟芯片缺失/总线断开，验证默认密码与写失败保护。
module tb_flash_default_fail;
 reg test_pass=0;
 reg clk=0,rst=1,save=0;wire sclk,mosi,cs,wp,hold,init_done,save_done,save_ok,fault;wire[15:0]password;
 always #5 clk=~clk;
 w25q64_password_store #(.CLOCK_HZ(1000),.SPI_HALF_DIV(1),.ERASE_TIMEOUT_CYCLES(100),.PROGRAM_TIMEOUT_CYCLES(50)) dut(
  .clk(clk),.rst(rst),.save_request(save),.save_password(16'h5678),.flash_miso(1'b1),
  .flash_sclk(sclk),.flash_mosi(mosi),.flash_cs_n(cs),.flash_wp_n(wp),.flash_hold_n(hold),
  .init_done(init_done),.current_password(password),.save_done(save_done),.save_success(save_ok),.flash_fault(fault));
 // 关键断言：空/不可读 Flash 使用 1234；失败的保存绝不能改变 current_password。
 initial begin repeat(4)@(negedge clk);rst=0;wait(init_done);@(negedge clk);
   if(password!==16'h1234)$fatal(1,"empty flash default %h",password);
   save=1;@(negedge clk);save=0;wait(save_done);@(negedge clk);
   if(save_ok)$fatal(1,"all-ones MISO must not verify save");
   if(password!==16'h1234)$fatal(1,"failed save changed password");
   test_pass=1;$display("PASS tb_flash_default_fail");$finish;end
endmodule

simulation_waveforms/07_flash_default_failure/tb_flash_default_fail.vcd
$date
   Tue Sep  8 20:50:03 2026
$end

$version
  2023.2
$end

$timescale
  1ps
$end

$scope module tb_flash_default_fail $end
$var reg 1 z test_pass $end
$var reg 1 { clk $end
$var reg 1 | rst $end
$var reg 1 } save $end
$var wire 1 A sclk $end
$var wire 1 B mosi $end
$var wire 1 ~ cs $end
$var wire 1 D wp $end
$var wire 1 E hold $end
$var wire 1 !! init_done $end
$var wire 1 "! save_done $end
$var wire 1 #! save_ok $end
$var wire 1 $! fault $end
$var wire 16 %! password [15:0] $end
$scope module dut $end
$var wire 1 ! clk $end
$var wire 1 " rst $end
$var wire 1 ? save_request $end
$var wire 16 @ save_password [15:0] $end
$var wire 1 % flash_miso $end
$var wire 1 A flash_sclk $end
$var wire 1 B flash_mosi $end
$var reg 1 C flash_cs_n $end
$var wire 1 D flash_wp_n $end
$var wire 1 E flash_hold_n $end
$var reg 1 F init_done $end
$var reg 16 G current_password [15:0] $end
$var reg 1 H save_done $end
$var reg 1 I save_success $end
$var reg 1 J flash_fault $end
$var reg 6 K state [5:0] $end
$var reg 6 L byte_index [5:0] $end
$var reg 32 M timeout_count [31:0] $end
$var reg 3 N cs_high_count [2:0] $end
$var reg 1 O awaiting_byte $end
$var reg 1 P launch_pending $end
$var reg 1 Q spi_start $end
$var reg 8 R spi_tx [7:0] $end
$var wire 8 S spi_rx [7:0] $end
$var wire 1 T spi_busy $end
$var wire 1 U spi_done $end
$var reg 128 V record_a [127:0] $end
$var reg 128 W record_b [127:0] $end
$var reg 128 X verify_record [127:0] $end
$var reg 128 Y new_record [127:0] $end
$var reg 32 Z generation [31:0] $end
$var reg 1 [ active_bank $end
$var reg 1 \ target_bank $end
$var reg 1 ] id_valid $end
$var reg 24 ^ jedec_id [23:0] $end
$var reg 16 _ requested_password [15:0] $end
$var wire 1 ` valid_a $end
$var wire 1 a valid_b $end
$var wire 1 b valid_verify $end
$var wire 24 c target_address [23:0] $end
$var parameter 0 d CLOCK_HZ [31:0] $end
$var parameter 0 e SPI_HALF_DIV [31:0] $end
$var parameter 0 f CS_HIGH_CYCLES [31:0] $end
$var parameter 0 g ERASE_TIMEOUT_CYCLES [31:0] $end
$var parameter 0 h PROGRAM_TIMEOUT_CYCLES [31:0] $end
$var parameter 32 i MAGIC [31:0] $end
$var parameter 16 j COMMIT [15:0] $end
$var parameter 6 k S_ID [5:0] $end
$var parameter 6 l S_READ_A [5:0] $end
$var parameter 6 m S_READ_B [5:0] $end
$var parameter 6 n S_SELECT [5:0] $end
$var parameter 6 o S_IDLE [5:0] $end
$var parameter 6 p S_WREN_ERASE [5:0] $end
$var parameter 6 q S_ERASE [5:0] $end
$var parameter 6 r S_POLL_ERASE [5:0] $end
$var parameter 6 s S_WREN_PROGRAM [5:0] $end
$var parameter 6 t S_PROGRAM [5:0] $end
$var parameter 6 u S_POLL_PROGRAM [5:0] $end
$var parameter 6 v S_VERIFY [5:0] $end
$var parameter 6 w S_FINISH [5:0] $end
$var parameter 6 x S_FAIL [5:0] $end
$var parameter 0 y CGW [31:0] $end
$scope module u_spi $end
$var wire 1 ! clk $end
$var wire 1 " rst $end
$var wire 1 # start $end
$var wire 8 $ tx_data [7:0] $end
$var wire 1 % miso $end
$var reg 1 & sclk $end
$var reg 1 ' mosi $end
$var reg 8 ( rx_data [7:0] $end
$var reg 1 ) busy $end
$var reg 1 * done $end
$var reg 1 + div_count [0:0] $end
$var reg 8 , tx_shift [7:0] $end
$var reg 8 - rx_shift [7:0] $end
$var reg 4 . edge_count [3:0] $end
$var parameter 0 / HALF_DIV [31:0] $end
$var parameter 0 0 DW [31:0] $end
$upscope $end
$scope function crc16_96 $end
$var reg 16 1 crc16_96 [15:0] $end
$var reg 96 2 data [95:0] $end
$var integer 32 3 i [31:0] $end
$var reg 16 4 crc [15:0] $end
$upscope $end
$scope function bcd_valid $end
$var reg 1 5 bcd_valid $end
$var reg 16 6 value [15:0] $end
$upscope $end
$scope function record_valid $end
$var reg 1 7 record_valid $end
$var reg 128 8 record [127:0] $end
$upscope $end
$scope function record_byte $end
$var reg 8 9 record_byte [7:0] $end
$var reg 128 : record [127:0] $end
$var reg 5 ; index [4:0] $end
$upscope $end
$scope function transaction_byte $end
$var reg 8 < transaction_byte [7:0] $end
$var reg 6 = st [5:0] $end
$var reg 6 > index [5:0] $end
$upscope $end
$upscope $end
$upscope $end
$enddefinitions $end

#0
$dumpvars
0!
x!!
1"
x"!
x#
x#!
bx $
x$!
1%
bx %!
x&
x'
bx (
x)
x*
x+
bx ,
bx -
bx .
b1 /
b1 0
b0 1
bx 2
b11111111111111111111111111111111 3
b0 4
x5
bx 6
x7
bx 8
bx 9
bx :
bx ;
bx <
bx =
bx >
0?
b101011001111000 @
xA
xB
xC
1D
1E
xF
bx G
xH
xI
xJ
bx K
bx L
bx M
bx N
xO
xP
xQ
bx R
bx S
xT
xU
bx V
bx W
bx X
bx Y
bx Z
x[
x\
x]
bx ^
bx _
x`
xa
xb
b0x000000000000 c
b1111101000 d
b1 e
b100 f
b1100100 g
b110010 h
b1010000010011000100101100110001 i
b1010010101011010 j
b0 k
b1 l
b10 m
b11 n
b100 o
b101 p
b110 q
b111 r
b1000 s
b1001 t
b1010 u
b1011 v
b1100 w
b1101 x
b11 y
0z
0{
1|
0}
x~
$end

#5000
1!
0!!
0"!
0#
0#!
b0 $
0$!
b1001000110100 %!
0&
0'
b0 (
0)
0*
0+
b0 ,
b0 -
b0 .
07
b0 8
0A
0B
1C
0F
b1001000110100 G
0H
0I
0J
b0 K
b0 L
b0 M
b100 N
0O
0P
0Q
b0 R
b0 S
0T
0U
b0 V
b0 W
b0 X
b0 Y
b0 Z
0[
1\
0]
b0 ^
b1001000110100 _
0`
0a
0b
b1000000000000 c
1{
1~

#10000
0!
0{

#15000
1!
1{

#20000
0!
0{

#25000
1!
1{

#30000
0!
0{

#35000
1!
1{

#40000
0!
0"
0{
0|

#45000
1!
b11 N
1{

#50000
0!
0{

#55000
1!
b10 N
1{

#60000
0!
0{

#65000
1!
b1 N
1{

#70000
0!
0{

#75000
1!
b0 N
1{

#80000
0!
0{

#85000
1!
b10011111 $
b10011111 <
b0 =
b0 >
0C
1P
b10011111 R
1{
0~

#90000
0!
0{

#95000
1!
1#
1O
0P
1Q
1{

#100000
0!
0{

#105000
1!
0#
1'
1)
b10011111 ,
1B
0Q
1T
1{

#110000
0!
0{

#115000
1!
1&
b1 -
b1 .
1A
1{

#120000
0!
0{

#125000
1!
0&
0'
b111110 ,
0A
0B
1{

#130000
0!
0{

#135000
1!
1&
b11 -
b10 .
1A
1{

#140000
0!
0{

#145000
1!
0&
b1111100 ,
0A
1{

#150000
0!
0{

#155000
1!
1&
b111 -
b11 .
1A
1{

#160000
0!
0{

#165000
1!
0&
1'
b11111000 ,
0A
1B
1{

#170000
0!
0{

#175000
1!
1&
b1111 -
b100 .
1A
1{

#180000
0!
0{

#185000
1!
0&
b11110000 ,
0A
1{

#190000
0!
0{

#195000
1!
1&
b11111 -
b101 .
1A
1{

#200000
0!
0{

#205000
1!
0&
b11100000 ,
0A
1{

#210000
0!
0{

#215000
1!
1&
b111111 -
b110 .
1A
1{

#220000
0!
0{

#225000
1!
0&
b11000000 ,
0A
1{

#230000
0!
0{

#235000
1!
1&
b1111111 -
b111 .
1A
1{

#240000
0!
0{

#245000
1!
0&
b10000000 ,
0A
1{

#250000
0!
0{

#255000
1!
1&
b11111111 -
b1000 .
1A
1{

#260000
0!
0{

#265000
1!
0&
0'
b11111111 (
0)
1*
0A
0B
b11111111 S
0T
1U
1{

#270000
0!
0{

#275000
1!
0*
b1 L
0O
0U
1{

#280000
0!
0{

#285000
1!
b0 $
b0 <
b1 >
1P
b0 R
1{

#290000
0!
0{

#295000
1!
1#
1O
0P
1Q
1{

#300000
0!
0{

#305000
1!
0#
1)
b0 ,
b0 -
b0 .
0Q
1T
1{

#310000
0!
0{

#315000
1!
1&
b1 -
b1 .
1A
1{

#320000
0!
0{

#325000
1!
0&
0A
1{

#330000
0!
0{

#335000
1!
1&
b11 -
b10 .
1A
1{

#340000
0!
0{

#345000
1!
0&
0A
1{

#350000
0!
0{

#355000
1!
1&
b111 -
b11 .
1A
1{

#360000
0!
0{

#365000
1!
0&
0A
1{

#370000
0!
0{

#375000
1!
1&
b1111 -
b100 .
1A
1{

#380000
0!
0{

#385000
1!
0&
0A
1{

#390000
0!
0{

#395000
1!
1&
b11111 -
b101 .
1A
1{

#400000
0!
0{

#405000
1!
0&
0A
1{

#410000
0!
0{

#415000
1!
1&
b111111 -
b110 .
1A
1{

#420000
0!
0{

#425000
1!
0&
0A
1{

#430000
0!
0{

#435000
1!
1&
b1111111 -
b111 .
1A
1{

#440000
0!
0{

#445000
1!
0&
0A
1{

#450000
0!
0{

#455000
1!
1&
b11111111 -
b1000 .
1A
1{

#460000
0!
0{

#465000
1!
0&
0)
1*
0A
0T
1U
1{

#470000
0!
0{

#475000
1!
0*
b10 L
0O
0U
b11111111 ^
1{

#480000
0!
0{

#485000
1!
b10 >
1P
1{

#490000
0!
0{

#495000
1!
1#
1O
0P
1Q
1{

#500000
0!
0{

#505000
1!
0#
1)
b0 -
b0 .
0Q
1T
1{

#510000
0!
0{

#515000
1!
1&
b1 -
b1 .
1A
1{

#520000
0!
0{

#525000
1!
0&
0A
1{

#530000
0!
0{

#535000
1!
1&
b11 -
b10 .
1A
1{

#540000
0!
0{

#545000
1!
0&
0A
1{

#550000
0!
0{

#555000
1!
1&
b111 -
b11 .
1A
1{

#560000
0!
0{

#565000
1!
0&
0A
1{

#570000
0!
0{

#575000
1!
1&
b1111 -
b100 .
1A
1{

#580000
0!
0{

#585000
1!
0&
0A
1{

#590000
0!
0{

#595000
1!
1&
b11111 -
b101 .
1A
1{

#600000
0!
0{

#605000
1!
0&
0A
1{

#610000
0!
0{

#615000
1!
1&
b111111 -
b110 .
1A
1{

#620000
0!
0{

#625000
1!
0&
0A
1{

#630000
0!
0{

#635000
1!
1&
b1111111 -
b111 .
1A
1{

#640000
0!
0{

#645000
1!
0&
0A
1{

#650000
0!
0{

#655000
1!
1&
b11111111 -
b1000 .
1A
1{

#660000
0!
0{

#665000
1!
0&
0)
1*
0A
0T
1U
1{

#670000
0!
0{

#675000
1!
0*
b11 L
0O
0U
b1111111111111111 ^
1{

#680000
0!
0{

#685000
1!
b11 >
1P
1{

#690000
0!
0{

#695000
1!
1#
1O
0P
1Q
1{

#700000
0!
0{

#705000
1!
0#
1)
b0 -
b0 .
0Q
1T
1{

#710000
0!
0{

#715000
1!
1&
b1 -
b1 .
1A
1{

#720000
0!
0{

#725000
1!
0&
0A
1{

#730000
0!
0{

#735000
1!
1&
b11 -
b10 .
1A
1{

#740000
0!
0{

#745000
1!
0&
0A
1{

#750000
0!
0{

#755000
1!
1&
b111 -
b11 .
1A
1{

#760000
0!
0{

#765000
1!
0&
0A
1{

#770000
0!
0{

#775000
1!
1&
b1111 -
b100 .
1A
1{

#780000
0!
0{

#785000
1!
0&
0A
1{

#790000
0!
0{

#795000
1!
1&
b11111 -
b101 .
1A
1{

#800000
0!
0{

#805000
1!
0&
0A
1{

#810000
0!
0{

#815000
1!
1&
b111111 -
b110 .
1A
1{

#820000
0!
0{

#825000
1!
0&
0A
1{

#830000
0!
0{

#835000
1!
1&
b1111111 -
b111 .
1A
1{

#840000
0!
0{

#845000
1!
0&
0A
1{

#850000
0!
0{

#855000
1!
1&
b11111111 -
b1000 .
1A
1{

#860000
0!
0{

#865000
1!
0&
0)
1*
0A
0T
1U
1{

#870000
0!
0{

#875000
1!
0*
1C
b1 K
b0 L
b100 N
0O
0U
b111111111111111111111111 ^
1{
1~

#880000
0!
0{

#885000
1!
b11 N
1{

#890000
0!
0{

#895000
1!
b10 N
1{

#900000
0!
0{

#905000
1!
b1 N
1{

#910000
0!
0{

#915000
1!
b0 N
1{

#920000
0!
0{

#925000
1!
b11 $
b11 <
b1 =
b0 >
0C
1P
b11 R
1{
0~

#930000
0!
0{

#935000
1!
1#
1O
0P
1Q
1{

#940000
0!
0{

#945000
1!
0#
1)
b11 ,
b0 -
b0 .
0Q
1T
1{

#950000
0!
0{

#955000
1!
1&
b1 -
b1 .
1A
1{

#960000
0!
0{

#965000
1!
0&
b110 ,
0A
1{

#970000
0!
0{

#975000
1!
1&
b11 -
b10 .
1A
1{

#980000
0!
0{

#985000
1!
0&
b1100 ,
0A
1{

#990000
0!
0{

#995000
1!
1&
b111 -
b11 .
1A
1{

#1000000
0!
0{

#1005000
1!
0&
b11000 ,
0A
1{

#1010000
0!
0{

#1015000
1!
1&
b1111 -
b100 .
1A
1{

#1020000
0!
0{

#1025000
1!
0&
b110000 ,
0A
1{

#1030000
0!
0{

#1035000
1!
1&
b11111 -
b101 .
1A
1{

#1040000
0!
0{

#1045000
1!
0&
b1100000 ,
0A
1{

#1050000
0!
0{

#1055000
1!
1&
b111111 -
b110 .
1A
1{

#1060000
0!
0{

#1065000
1!
0&
1'
b11000000 ,
0A
1B
1{

#1070000
0!
0{

#1075000
1!
1&
b1111111 -
b111 .
1A
1{

#1080000
0!
0{

#1085000
1!
0&
b10000000 ,
0A
1{

#1090000
0!
0{

#1095000
1!
1&
b11111111 -
b1000 .
1A
1{

#1100000
0!
0{

#1105000
1!
0&
0'
0)
1*
0A
0B
0T
1U
1{

#1110000
0!
0{

#1115000
1!
0*
b1 L
0O
0U
1{

#1120000
0!
0{

#1125000
1!
b0 $
b0 <
b1 >
1P
b0 R
1{

#1130000
0!
0{

#1135000
1!
1#
1O
0P
1Q
1{

#1140000
0!
0{

#1145000
1!
0#
1)
b0 ,
b0 -
b0 .
0Q
1T
1{

#1150000
0!
0{

#1155000
1!
1&
b1 -
b1 .
1A
1{

#1160000
0!
0{

#1165000
1!
0&
0A
1{

#1170000
0!
0{

#1175000
1!
1&
b11 -
b10 .
1A
1{

#1180000
0!
0{

#1185000
1!
0&
0A
1{

#1190000
0!
0{

#1195000
1!
1&
b111 -
b11 .
1A
1{

#1200000
0!
0{

#1205000
1!
0&
0A
1{

#1210000
0!
0{

#1215000
1!
1&
b1111 -
b100 .
1A
1{

#1220000
0!
0{

#1225000
1!
0&
0A
1{

#1230000
0!
0{

#1235000
1!
1&
b11111 -
b101 .
1A
1{

#1240000
0!
0{

#1245000
1!
0&
0A
1{

#1250000
0!
0{

