password_lock_system/rtl/lock_controller.v
`timescale 1ns/1ps

module lock_controller #(
    parameter integer CLOCK_HZ         = 50_000_000,
    parameter integer LOCK_TIMEOUT_S   = 8,
    parameter integer OPEN_TIMEOUT_S   = 16,
    parameter integer ERROR_DISPLAY_MS = 1000
) (
    input  wire        clk,
    input  wire        rst,
    input  wire        flash_init_done,
    input  wire [15:0] stored_password,
    input  wire        flash_fault,
    input  wire        sw1_event,
    input  wire        admin_event,
    input  wire        alarm_clear_event,
    input  wire        temporary_event,
    input  wire [15:0] temporary_password,
    input  wire        temporary_valid,
    input  wire        key_valid,
    input  wire [3:0]  key_code,
    input  wire        save_done,
    input  wire        save_success,
    output reg         save_request,
    output reg [15:0]  save_password,
    output reg         capture_start,
    output reg         unlocked,
    output reg         alarm_active,
    output reg [3:0]   state,
    output reg [15:0]  entry_digits,
    output reg [2:0]   entry_count,
    output reg [2:0]   error_count,
    output reg         display_fault
);
    localparam [3:0] ST_BOOT  = 4'd0,
                     ST_WAIT  = 4'd1,
                     ST_USER  = 4'd2,
                     ST_ERROR = 4'd3,
                     ST_OPEN  = 4'd4,
                     ST_ADMIN = 4'd5,
                     ST_SAVE  = 4'd6,
                     ST_ALARM = 4'd7,
                     ST_TEMP  = 4'd8;
    localparam integer LOCK_TICKS  = CLOCK_HZ * LOCK_TIMEOUT_S;
    localparam integer OPEN_TICKS  = CLOCK_HZ * OPEN_TIMEOUT_S;
    localparam integer ERROR_TICKS = (CLOCK_HZ / 1000) * ERROR_DISPLAY_MS;
    localparam integer MAX_TICKS = (OPEN_TICKS > LOCK_TICKS) ? OPEN_TICKS : LOCK_TICKS;
    localparam integer MAX_TICKS2 = (MAX_TICKS > ERROR_TICKS) ? MAX_TICKS : ERROR_TICKS;
    localparam integer TW = (MAX_TICKS2 <= 2) ? 1 : $clog2(MAX_TICKS2 + 1);

    reg [3:0] next_state;
    reg [TW-1:0] timer_count;
    wire is_digit = (key_code <= 4'd9);
    wire activity = key_valid && (is_digit || key_code == 4'hA ||
                                  key_code == 4'hB || key_code == 4'hC);

    always @(*) begin
        next_state = state;
        case (state)
            ST_BOOT:  if (flash_init_done) next_state = ST_WAIT;
            ST_WAIT:  if (temporary_event) next_state = ST_TEMP;
                      else if (admin_event) next_state = ST_ADMIN;
                      else if (sw1_event) next_state = ST_USER;
            ST_USER:  if (key_valid && key_code == 4'hC) next_state = ST_WAIT;
                      else if ((timer_count >= LOCK_TICKS-1) && !activity) next_state = ST_WAIT;
                      else if (key_valid && key_code == 4'hA && entry_count == 3'd4) begin
                          if (entry_digits == stored_password ||
                              (temporary_valid && entry_digits == temporary_password))
                              next_state = ST_OPEN;
                          else if (error_count == 3'd3) next_state = ST_ALARM;
                          else next_state = ST_ERROR;
                      end
            ST_ERROR: if (timer_count >= ERROR_TICKS-1) next_state = ST_USER;
            ST_OPEN:  if ((key_valid && key_code == 4'hA) ||
                          (timer_count >= OPEN_TICKS-1)) next_state = ST_WAIT;
                      else if (admin_event) next_state = ST_ADMIN;
            ST_ADMIN: if (key_valid && key_code == 4'hC) next_state = ST_WAIT;
                      else if ((timer_count >= LOCK_TICKS-1) && !activity) next_state = ST_WAIT;
                      else if (key_valid && key_code == 4'hA && entry_count == 3'd4)
                          next_state = ST_SAVE;
            ST_SAVE:  if (save_done) next_state = ST_WAIT;
            // A replacement request wins over timeout or simultaneous input,
            // so the new password always remains visible for a full interval.
            ST_TEMP:  if (temporary_event) next_state = ST_TEMP;
                      else if (sw1_event) next_state = ST_USER;
                      else if (key_valid && (key_code == 4'hA || key_code == 4'hC))
                          next_state = ST_WAIT;
                      else if (timer_count >= LOCK_TICKS-1) next_state = ST_WAIT;
            // KEY2 completes the administrator's alarm handling and starts a
            // clean input session.  No SW1 toggle is required afterward.
            ST_ALARM: if (alarm_clear_event) next_state = ST_USER;
            default: next_state = ST_BOOT;
        endcase
    end

    always @(posedge clk) begin
        if (rst) begin
            state          <= ST_BOOT;
            timer_count    <= {TW{1'b0}};
            entry_digits   <= 16'h0000;
            entry_count    <= 3'd0;
            error_count    <= 3'd0;
            save_request   <= 1'b0;
            save_password  <= 16'h1234;
            capture_start  <= 1'b0;
            display_fault  <= 1'b0;
        end else begin
            state         <= next_state;
            save_request  <= 1'b0;
            capture_start <= 1'b0;

            if (state != next_state) begin
                timer_count <= {TW{1'b0}};
                if (next_state == ST_USER || next_state == ST_ADMIN ||
                    next_state == ST_WAIT) begin
                    entry_digits <= 16'h0000;
                    entry_count  <= 3'd0;
                end
                if (next_state == ST_OPEN)
                    error_count <= 3'd0;
                if (next_state == ST_ERROR)
                    error_count <= error_count + 1'b1;
                if (next_state == ST_ALARM) begin
                    error_count   <= 3'd4;
                    capture_start <= 1'b1;
                end
                // An acknowledged alarm starts a new four-attempt window.
                // Without this reset the three-bit counter would display
                // Err5..Err7 and wrap, which is not a valid attempt policy.
                if (state == ST_ALARM && alarm_clear_event)
                    error_count <= 3'd0;
                if (next_state == ST_SAVE) begin
                    save_password <= entry_digits;
                    save_request  <= 1'b1;
                end
                if (state == ST_SAVE && next_state == ST_WAIT)
                    display_fault <= ~save_success;
            end else begin
                if ((activity || temporary_event) &&
                    (state == ST_USER || state == ST_ADMIN || state == ST_OPEN || state == ST_TEMP))
                    timer_count <= {TW{1'b0}};
                else if (state == ST_USER || state == ST_ADMIN || state == ST_OPEN ||
                         state == ST_ERROR || state == ST_TEMP)
                    timer_count <= timer_count + 1'b1;

                if ((state == ST_USER || state == ST_ADMIN) && key_valid) begin
                    if (is_digit && entry_count < 3'd4) begin
                        entry_digits <= {entry_digits[11:0], key_code};
                        entry_count  <= entry_count + 1'b1;
                    end else if (key_code == 4'hB && entry_count != 0) begin
                        entry_digits <= {4'h0, entry_digits[15:4]};
                        entry_count  <= entry_count - 1'b1;
                    end
                end
            end

            // Starting a new user/admin/temporary-password operation clears a
            // previous save-error indication even when that same event also
            // causes a state transition on this clock edge.
            if (display_fault && (sw1_event || admin_event || temporary_event))
                display_fault <= 1'b0;
            if (flash_fault)
                display_fault <= 1'b1;
        end
    end

    always @(*) begin
        unlocked     = (state == ST_OPEN);
        alarm_active = (state == ST_ALARM);
    end
endmodule

password_lock_system/sim/tb_basic_alarm_policy.sv
`timescale 1ns/1ps

module tb_basic_alarm_policy;
    localparam [3:0] ST_USER=4'd2, ST_ERROR=4'd3, ST_ALARM=4'd7;
    reg test_pass=0;
    reg clk=0,rst=1,init_done=0,sw1=0,admin=0,clear=0,key_valid=0,temp_event=0;
    reg [3:0] key_code=0;
    reg [7:0] scenario=0;
    wire capture_start,alarm_active;
    wire [3:0] state;
    wire [2:0] error_count;
    integer capture_pulses=0;

    always #5 clk=~clk;
    always @(posedge clk) if(capture_start) capture_pulses=capture_pulses+1;
    lock_controller #(.CLOCK_HZ(1000),.LOCK_TIMEOUT_S(1),.OPEN_TIMEOUT_S(2),.ERROR_DISPLAY_MS(2)) dut(
        .clk(clk),.rst(rst),.flash_init_done(init_done),.stored_password(16'h1234),
        .flash_fault(1'b0),.sw1_event(sw1),.admin_event(admin),.alarm_clear_event(clear),
        .temporary_event(temp_event),.temporary_password(16'h2468),.temporary_valid(1'b1),
        .key_valid(key_valid),.key_code(key_code),.save_done(1'b0),.save_success(1'b0),
        .save_request(),.save_password(),.capture_start(capture_start),.unlocked(),
        .alarm_active(alarm_active),.state(state),.entry_digits(),.entry_count(),
        .error_count(error_count),.display_fault());

    task pulse(input integer which); begin
        @(negedge clk);if(which==0)sw1=1;if(which==1)admin=1;if(which==2)clear=1;if(which==3)temp_event=1;
        @(negedge clk);sw1=0;admin=0;clear=0;temp_event=0;
    end endtask
    task key(input [3:0] code); begin @(negedge clk);key_code=code;key_valid=1;@(negedge clk);key_valid=0;end endtask
    task wrong_attempt; begin key(1);key(1);key(1);key(1);key(4'hA);end endtask
    task check(input bit ok,input string message); if(!ok)$fatal(1,"FAIL: %s",message); endtask
    integer n;

    initial begin
        scenario=1;repeat(4)@(negedge clk);rst=0;init_done=1;repeat(2)@(negedge clk);pulse(0);
        for(n=1;n<=3;n=n+1)begin
            scenario=n+1;wrong_attempt();#1;
            check(state==ST_ERROR && error_count==n,"Err1..Err3 sequence incorrect");
            repeat(4)@(negedge clk);check(state==ST_USER,"error display did not return to input");
        end
        scenario=5;wrong_attempt();repeat(2)@(negedge clk);
        check(state==ST_ALARM && alarm_active && error_count==4,"fourth error did not alarm");
        check(capture_pulses==1,"alarm did not emit exactly one photo trigger");
        scenario=6;pulse(3);pulse(1);key(4'hA);repeat(2)@(negedge clk);
        check(state==ST_ALARM,"non-KEY2 input bypassed alarm");
        scenario=7;pulse(2);repeat(2)@(negedge clk);
        check(state==ST_USER && !alarm_active && error_count==0,"KEY2 clear policy failed");
        scenario=8;wrong_attempt();#1;
        check(state==ST_ERROR && error_count==1,"post-alarm count did not restart at Err1");
        test_pass=1;$display("PASS tb_basic_alarm_policy");$finish;
    end
endmodule

simulation_waveforms/03_error_alarm_policy/tb_basic_alarm_policy.vcd
$date
   Tue Sep  8 16:53:26 2026
$end

$version
  2023.2
$end

$timescale
  1ps
$end

$scope module tb_basic_alarm_policy $end
$var reg 1 R test_pass $end
$var reg 1 S clk $end
$var reg 1 T rst $end
$var reg 1 U init_done $end
$var reg 1 V sw1 $end
$var reg 1 W admin $end
$var reg 1 X clear $end
$var reg 1 Y key_valid $end
$var reg 1 Z temp_event $end
$var reg 4 [ key_code [3:0] $end
$var reg 8 \ scenario [7:0] $end
$var wire 1 ] capture_start $end
$var wire 1 ^ alarm_active $end
$var wire 4 _ state [3:0] $end
$var wire 3 ` error_count [2:0] $end
$var integer 32 a capture_pulses [31:0] $end
$var integer 32 b n [31:0] $end
$var parameter 4 c ST_USER [3:0] $end
$var parameter 4 d ST_ERROR [3:0] $end
$var parameter 4 e ST_ALARM [3:0] $end
$scope module dut $end
$var wire 1 ! clk $end
$var wire 1 " rst $end
$var wire 1 # flash_init_done $end
$var wire 16 $ stored_password [15:0] $end
$var wire 1 % flash_fault $end
$var wire 1 & sw1_event $end
$var wire 1 ' admin_event $end
$var wire 1 ( alarm_clear_event $end
$var wire 1 ) temporary_event $end
$var wire 16 * temporary_password [15:0] $end
$var wire 1 + temporary_valid $end
$var wire 1 , key_valid $end
$var wire 4 - key_code [3:0] $end
$var wire 1 % save_done $end
$var wire 1 % save_success $end
$var reg 1 . save_request $end
$var reg 16 / save_password [15:0] $end
$var reg 1 0 capture_start $end
$var reg 1 1 unlocked $end
$var reg 1 2 alarm_active $end
$var reg 4 3 state [3:0] $end
$var reg 16 4 entry_digits [15:0] $end
$var reg 3 5 entry_count [2:0] $end
$var reg 3 6 error_count [2:0] $end
$var reg 1 7 display_fault $end
$var reg 4 8 next_state [3:0] $end
$var reg 11 9 timer_count [10:0] $end
$var wire 1 : is_digit $end
$var wire 1 ; activity $end
$var parameter 0 < CLOCK_HZ [31:0] $end
$var parameter 0 = LOCK_TIMEOUT_S [31:0] $end
$var parameter 0 > OPEN_TIMEOUT_S [31:0] $end
$var parameter 0 ? ERROR_DISPLAY_MS [31:0] $end
$var parameter 4 @ ST_BOOT [3:0] $end
$var parameter 4 A ST_WAIT [3:0] $end
$var parameter 4 B ST_USER [3:0] $end
$var parameter 4 C ST_ERROR [3:0] $end
$var parameter 4 D ST_OPEN [3:0] $end
$var parameter 4 E ST_ADMIN [3:0] $end
$var parameter 4 F ST_SAVE [3:0] $end
$var parameter 4 G ST_ALARM [3:0] $end
$var parameter 4 H ST_TEMP [3:0] $end
$var parameter 0 I LOCK_TICKS [31:0] $end
$var parameter 0 J OPEN_TICKS [31:0] $end
$var parameter 0 K ERROR_TICKS [31:0] $end
$var parameter 0 L MAX_TICKS [31:0] $end
$var parameter 0 M MAX_TICKS2 [31:0] $end
$var parameter 0 N TW [31:0] $end
$upscope $end
$scope task pulse $end
$var integer 32 O which [31:0] $end
$upscope $end
$scope task key $end
$var reg 4 P code [3:0] $end
$upscope $end
$scope task check $end
$var reg 1 Q ok $end
$upscope $end
$upscope $end
$enddefinitions $end

#0
$dumpvars
0!
1"
0#
b1001000110100 $
0%
0&
0'
0(
0)
b10010001101000 *
1+
0,
b0 -
x.
bx /
x0
x1
x2
bx 3
bx 4
bx 5
bx 6
x7
b0 8
bx 9
1:
0;
b1111101000 <
b1 =
b10 >
b10 ?
b0 @
b1 A
b10 B
b11 C
b100 D
b101 E
b110 F
b111 G
b1000 H
b1111101000 I
b11111010000 J
b10 K
b11111010000 L
b11111010000 M
b1011 N
bx O
bx P
0Q
0R
0S
1T
0U
0V
0W
0X
0Y
0Z
b0 [
b1 \
x]
x^
bx _
bx `
b0 a
bx b
b10 c
b11 d
b111 e
$end

#5000
1!
0.
b1001000110100 /
00
01
02
b0 3
b0 4
b0 5
b0 6
07
b0 9
1S
0]
0^
b0 _
b0 `

#10000
0!
0S

#15000
1!
1S

#20000
0!
0S

#25000
1!
1S

#30000
0!
0S

#35000
1!
1S

#40000
0!
0"
1#
b1 8
0S
0T
1U

#45000
1!
b1 3
1S
b1 _

#50000
0!
0S

#55000
1!
1S

#60000
0!
b0 O
0S

#65000
1!
1S

#70000
0!
1&
b10 8
0S
1V

#75000
1!
b10 3
1S
b10 _

#80000
0!
0&
b1 P
0S
0V
b10 \
b1 b

#85000
1!
b1 9
1S

#90000
0!
1,
b1 -
1;
0S
1Y
b1 [

#95000
1!
b1 4
b1 5
b0 9
1S

#100000
0!
0,
0;
0S
0Y

#105000
1!
b1 9
1S

#110000
0!
1,
1;
0S
1Y

#115000
1!
b10001 4
b10 5
b0 9
1S

#120000
0!
0,
0;
0S
0Y

#125000
1!
b1 9
1S

#130000
0!
1,
1;
0S
1Y

#135000
1!
b100010001 4
b11 5
b0 9
1S

#140000
0!
0,
0;
0S
0Y

#145000
1!
b1 9
1S

#150000
0!
1,
1;
0S
1Y

#155000
1!
b1000100010001 4
b100 5
b0 9
1S

#160000
0!
0,
0;
b1010 P
0S
0Y

#165000
1!
b1 9
1S

#170000
0!
1,
b1010 -
b11 8
0:
1;
0S
1Y
b1010 [

#175000
1!
b11 3
b1 6
b0 9
1S
b11 _
b1 `

#180000
0!
0,
0;
0S
0Y

#181000
1Q

#185000
1!
b10 8
b1 9
1S

#190000
0!
0S

#195000
1!
b10 3
b0 4
b0 5
b0 9
1S
b10 _

#200000
0!
0S

#205000
1!
b1 9
1S

#210000
0!
0S

#215000
1!
b10 9
1S

#220000
0!
b1 P
0S
b11 \
b10 b

#225000
1!
b11 9
1S

#230000
0!
1,
b1 -
1:
1;
0S
1Y
b1 [

#235000
1!
b1 4
b1 5
b0 9
1S

#240000
0!
0,
0;
0S
0Y

#245000
1!
b1 9
1S

#250000
0!
1,
1;
0S
1Y

#255000
1!
b10001 4
b10 5
b0 9
1S

#260000
0!
0,
0;
0S
0Y

#265000
1!
b1 9
1S

#270000
0!
1,
1;
0S
1Y

#275000
1!
b100010001 4
b11 5
b0 9
1S

#280000
0!
0,
0;
0S
0Y

#285000
1!
b1 9
1S

#290000
0!
1,
1;
0S
1Y

#295000
1!
b1000100010001 4
b100 5
b0 9
1S

#300000
0!
0,
0;
b1010 P
0S
0Y

#305000
1!
b1 9
1S

#310000
0!
1,
b1010 -
b11 8
0:
1;
0S
1Y
b1010 [

#315000
1!
b11 3
b10 6
b0 9
1S
b11 _
b10 `

#320000
0!
0,
0;
0S
0Y

#325000
1!
b10 8
b1 9
1S

#330000
0!
0S

#335000
1!
b10 3
b0 4
b0 5
b0 9
1S
b10 _

#340000
0!
0S

#345000
1!
b1 9
1S

#350000
0!
0S

#355000
1!
b10 9
1S

#360000
0!
b1 P
0S
b100 \
b11 b

#365000
1!
b11 9
1S

#370000
0!
1,
b1 -
1:
1;
0S
1Y
b1 [

#375000
1!
b1 4
b1 5
b0 9
1S

#380000
0!
0,
0;
0S
0Y

#385000
1!
b1 9
1S

#390000
0!
1,
1;
0S
1Y

#395000
1!
b10001 4
b10 5
b0 9
1S

#400000
0!
0,
0;
0S
0Y

#405000
1!
b1 9
1S

#410000
0!
1,
1;
0S
1Y

#415000
1!
b100010001 4
b11 5
b0 9
1S

#420000
0!
0,
0;
0S
0Y

#425000
1!
b1 9
1S

#430000
0!
1,
1;
0S
1Y

#435000
1!
b1000100010001 4
b100 5
b0 9
1S

#440000
0!
0,
0;
b1010 P
0S
0Y

#445000
1!
b1 9
1S

#450000
0!
1,
b1010 -
b11 8
0:
1;
0S
1Y
b1010 [

#455000
1!
b11 3
b11 6
b0 9
1S
b11 _
b11 `

#460000
0!
0,
0;
0S
0Y

#465000
1!
b10 8
b1 9
1S

#470000
0!
0S

#475000
1!
b10 3
b0 4
b0 5
b0 9
1S
b10 _

#480000
0!
0S

#485000
1!
b1 9
1S

#490000
0!
0S

#495000
1!
b10 9
1S

#500000
0!
b1 P
0S
b101 \
b100 b

#505000
1!
b11 9
1S

#510000
0!
1,
b1 -
1:
1;
0S
1Y
b1 [

#515000
1!
b1 4
b1 5
b0 9
1S

#520000
0!
0,
0;
0S
0Y

#525000
1!
b1 9
1S

#530000
0!
1,
1;
0S
1Y

#535000
1!
b10001 4
b10 5
b0 9
1S

#540000
0!
0,
0;
0S
0Y

#545000
1!
b1 9
1S

#550000
0!
1,
1;
0S
1Y

#555000
1!
b100010001 4
b11 5
b0 9
1S

#560000
0!
0,
0;
0S
0Y

#565000
1!
b1 9
1S

#570000
0!
1,
1;
0S
1Y

#575000
1!
b1000100010001 4
b100 5
b0 9
1S

#580000
0!
0,
0;
b1010 P
0S
0Y

#585000
1!
b1 9
1S

#590000
0!
1,
b1010 -
b111 8
0:
1;
0S
1Y
b1010 [

#595000
1!
10
12
b111 3
b100 6
b0 9
1S
1]
1^
b111 _
b100 `

#600000
0!
0,
0;
0S
0Y

#605000
1!
00
1S
0]
b1 a

#610000
0!
0S

#615000
1!
1S

#620000
0!
b11 O
0S
b110 \

#625000
1!
1S

#630000
0!
1)
0S
1Z

#635000
1!
1S

#640000
0!
0)
b1 O
0S
0Z

#645000
1!
1S

#650000
0!
1'
0S
1W

#655000
1!
1S

#660000
0!
0'
0S
0W

#665000
1!
1S

#670000
0!
1,
1;
0S
1Y

#675000
1!
1S

#680000
0!
0,
0;
0S
0Y

#685000
1!
1S

#690000
0!
0S

#695000
1!
1S

#700000
0!
b10 O
0S
b111 \

#705000
1!
1S

#710000
0!
1(
b10 8
0S
1X

#715000
1!
02
b10 3
b0 4
b0 5
b0 6
1S
0^
b10 _
b0 `

#720000
0!
0(
0S
0X

#725000
1!
b1 9
1S

#730000
0!
0S

#735000
1!
b10 9
1S

#740000
0!
b1 P
0S
b1000 \

#745000
1!
b11 9
1S

#750000
0!
1,
b1 -
1:
1;
0S
1Y
b1 [

#755000
1!
b1 4
b1 5
b0 9
1S

#760000
0!
0,
0;
0S
0Y

#765000
1!
b1 9
1S

#770000
0!
1,
1;
0S
1Y

#775000
1!
b10001 4
b10 5
b0 9
1S

#780000
0!
0,
0;
0S
0Y

#785000
1!
b1 9
1S

#790000
0!
1,
1;
0S
1Y

#795000
1!
b100010001 4
b11 5
b0 9
1S

#800000
0!
0,
0;
0S
0Y

#805000
1!
b1 9
1S

#810000
0!
1,
1;
0S
1Y

#815000
1!
b1000100010001 4
b100 5
b0 9
1S

#820000
0!
0,
0;
b1010 P
0S
0Y

#825000
1!
b1 9
1S

#830000
0!
1,
b1010 -
b11 8
0:
1;
0S
1Y
b1010 [

#835000
1!
b11 3
b1 6
b0 9
1S
b11 _
b1 `

#840000
0!
0,
0;
0S
0Y

#841000
1R
