password_lock_system/rtl/alarm_buzzer.v
`timescale 1ns/1ps

// 报警蜂鸣器：用低频断续节拍包络 2 kHz 音频方波，同时输出同节拍 LED 指示。
// 实板已验证蜂鸣器为高电平有效；端口名 buzzer_n 仅为兼容旧工程命名，不表示低有效。
module alarm_buzzer #(
    parameter integer CLOCK_HZ = 50_000_000,
    parameter integer BEEP_HZ  = 2,
    parameter integer TONE_HZ  = 2_000
) (
    input  wire clk,
    input  wire rst,
    input  wire alarm_active,
    output wire buzzer_n,
    output wire indicator
);
    // 半周期计数值决定节拍与音调；修改 BEEP_HZ/TONE_HZ 即可改变报警听感。
    localparam integer BEEP_HALF_TICKS = CLOCK_HZ / (2 * BEEP_HZ);
    localparam integer TONE_HALF_TICKS = CLOCK_HZ / (2 * TONE_HZ);
    localparam integer BW = (BEEP_HALF_TICKS <= 2) ? 1 : $clog2(BEEP_HALF_TICKS);
    localparam integer TW = (TONE_HALF_TICKS <= 2) ? 1 : $clog2(TONE_HALF_TICKS);

    reg [BW-1:0] beep_count;
    reg [TW-1:0] tone_count;
    reg beep_on;
    reg tone_phase;

    always @(posedge clk) begin
        if (rst || !alarm_active) begin
            beep_count <= {BW{1'b0}};
            tone_count <= {TW{1'b0}};
            beep_on    <= 1'b1;
            tone_phase <= 1'b1;
        end else begin
            // beep_on 每半个低频周期翻转，形成“响一段、停一段”的断续报警。
            if (beep_count == BEEP_HALF_TICKS-1) begin
                beep_count <= {BW{1'b0}};
                beep_on    <= ~beep_on;
            end else begin
                beep_count <= beep_count + 1'b1;
            end

            // 静音阶段复位音频相位；响铃阶段按 TONE_HZ 连续翻转输出。
            if (!beep_on) begin
                tone_count <= {TW{1'b0}};
                tone_phase <= 1'b1;
            end else if (tone_count == TONE_HALF_TICKS-1) begin
                tone_count <= {TW{1'b0}};
                tone_phase <= ~tone_phase;
            end else begin
                tone_count <= tone_count + 1'b1;
            end
        end
    end

    // 未报警或节拍静音时输出低电平；indicator 可直接驱动报警 LED。
    assign buzzer_n = (alarm_active && beep_on) ? tone_phase : 1'b0;
    assign indicator = alarm_active && beep_on;
endmodule

password_lock_system/sim/tb_alarm_buzzer.sv
`timescale 1ns/1ps
// 蜂鸣器自检：将系统频率缩小到 40 Hz，加速观察响铃载波、静音间隔和立即关闭行为。
module tb_alarm_buzzer;
    reg test_pass=0;
    reg clk=0,rst=1,alarm_active=0;
    wire buzzer_n,indicator;
    always #5 clk=~clk;

    // 仿真参数只为缩短运行时间；实机参数仍由顶层实例采用模块默认值。
    alarm_buzzer #(.CLOCK_HZ(40),.BEEP_HZ(2),.TONE_HZ(5)) dut(
        .clk(clk),.rst(rst),.alarm_active(alarm_active),
        .buzzer_n(buzzer_n),.indicator(indicator));

    task check(input bit condition,input string message);
      if(!condition) $fatal(1,"FAIL: %s buzzer_n=%b indicator=%b",message,buzzer_n,indicator);
    endtask

    // test_pass=1 且出现 PASS 文本表示所有断言均通过；$fatal 会让失败测试立即退出。
    initial begin
      repeat(2) @(negedge clk);rst=0;repeat(2)@(negedge clk);
      check(!buzzer_n && !indicator,"idle output is safe and silent");
      alarm_active=1;#1;
      check(buzzer_n && indicator,"alarm begins with an enabled high phase");
      repeat(4) @(posedge clk);#1;
      check(!buzzer_n && indicator,"audible phase contains an audio carrier");
      repeat(6) @(posedge clk);#1;
      check(!buzzer_n && !indicator,"alarm cadence reaches silent phase");
      repeat(10) @(posedge clk);#1;
      check(buzzer_n && indicator,"alarm cadence repeats audible phase");
      alarm_active=0;#1;
      check(!buzzer_n && !indicator,"clearing alarm silences output immediately");
      test_pass=1;$display("PASS tb_alarm_buzzer");$finish;
    end
endmodule

simulation_waveforms/06_alarm_buzzer/tb_alarm_buzzer.vcd
$date
   Tue Sep  8 20:49:40 2026
$end

$version
  2023.2
$end

$timescale
  1ps
$end

$scope module tb_alarm_buzzer $end
$var reg 1 2 test_pass $end
$var reg 1 3 clk $end
$var reg 1 4 rst $end
$var reg 1 5 alarm_active $end
$var wire 1 $ buzzer_n $end
$var wire 1 % indicator $end
$scope module dut $end
$var wire 1 ! clk $end
$var wire 1 " rst $end
$var wire 1 # alarm_active $end
$var wire 1 $ buzzer_n $end
$var wire 1 % indicator $end
$var reg 4 & beep_count [3:0] $end
$var reg 2 ' tone_count [1:0] $end
$var reg 1 ( beep_on $end
$var reg 1 ) tone_phase $end
$var parameter 0 * CLOCK_HZ [31:0] $end
$var parameter 0 + BEEP_HZ [31:0] $end
$var parameter 0 , TONE_HZ [31:0] $end
$var parameter 0 - BEEP_HALF_TICKS [31:0] $end
$var parameter 0 . TONE_HALF_TICKS [31:0] $end
$var parameter 0 / BW [31:0] $end
$var parameter 0 0 TW [31:0] $end
$upscope $end
$scope task check $end
$var reg 1 1 condition $end
$upscope $end
$upscope $end
$enddefinitions $end

#0
$dumpvars
0!
1"
0#
0$
0%
bx &
bx '
x(
x)
b101000 *
b10 +
b101 ,
b1010 -
b100 .
b100 /
b10 0
01
02
03
14
05
$end

#5000
1!
b0 &
b0 '
1(
1)
13

#10000
0!
03

#15000
1!
13

#20000
0!
0"
03
04

#25000
1!
13

#30000
0!
03

#35000
1!
13

#40000
0!
1#
1$
1%
11
03
15

#45000
1!
b1 &
b1 '
13

#50000
0!
03

#55000
1!
b10 &
b10 '
13

#60000
0!
03

#65000
1!
b11 &
b11 '
13

#70000
0!
03

#75000
1!
0$
b100 &
b0 '
0)
13

#80000
0!
03

#85000
1!
b101 &
b1 '
13

#90000
0!
03

#95000
1!
b110 &
b10 '
13

#100000
0!
03

#105000
1!
b111 &
b11 '
13

#110000
0!
03

#115000
1!
1$
b1000 &
b0 '
1)
13

#120000
0!
03

#125000
1!
b1001 &
b1 '
13

#130000
0!
03

#135000
1!
0$
0%
b0 &
b10 '
0(
13

#140000
0!
03

#145000
1!
b1 &
b0 '
13

#150000
0!
03

#155000
1!
b10 &
13

#160000
0!
03

#165000
1!
b11 &
13

#170000
0!
03

#175000
1!
b100 &
13

#180000
0!
03

#185000
1!
b101 &
13

#190000
0!
03

#195000
1!
b110 &
13

#200000
0!
03

#205000
1!
b111 &
13

#210000
0!
03

#215000
1!
b1000 &
13

#220000
0!
03

#225000
1!
b1001 &
13

#230000
0!
03

#235000
1!
1$
1%
b0 &
1(
13

#236000
0#
0$
0%
05

#237000
12
