password_lock_system/rtl/lock_controller.v
`timescale 1ns/1ps

module lock_controller #(
    parameter integer CLOCK_HZ         = 50_000_000,
    parameter integer LOCK_TIMEOUT_S   = 8,
    parameter integer OPEN_TIMEOUT_S   = 16,
    parameter integer ERROR_DISPLAY_MS = 1000
) (
    input  wire        clk,
    input  wire        rst,
    input  wire        flash_init_done,
    input  wire [15:0] stored_password,
    input  wire        flash_fault,
    input  wire        sw1_event,
    input  wire        admin_event,
    input  wire        alarm_clear_event,
    input  wire        temporary_event,
    input  wire [15:0] temporary_password,
    input  wire        temporary_valid,
    input  wire        key_valid,
    input  wire [3:0]  key_code,
    input  wire        save_done,
    input  wire        save_success,
    output reg         save_request,
    output reg [15:0]  save_password,
    output reg         capture_start,
    output reg         unlocked,
    output reg         alarm_active,
    output reg [3:0]   state,
    output reg [15:0]  entry_digits,
    output reg [2:0]   entry_count,
    output reg [2:0]   error_count,
    output reg         display_fault
);
    localparam [3:0] ST_BOOT  = 4'd0,
                     ST_WAIT  = 4'd1,
                     ST_USER  = 4'd2,
                     ST_ERROR = 4'd3,
                     ST_OPEN  = 4'd4,
                     ST_ADMIN = 4'd5,
                     ST_SAVE  = 4'd6,
                     ST_ALARM = 4'd7,
                     ST_TEMP  = 4'd8;
    localparam integer LOCK_TICKS  = CLOCK_HZ * LOCK_TIMEOUT_S;
    localparam integer OPEN_TICKS  = CLOCK_HZ * OPEN_TIMEOUT_S;
    localparam integer ERROR_TICKS = (CLOCK_HZ / 1000) * ERROR_DISPLAY_MS;
    localparam integer MAX_TICKS = (OPEN_TICKS > LOCK_TICKS) ? OPEN_TICKS : LOCK_TICKS;
    localparam integer MAX_TICKS2 = (MAX_TICKS > ERROR_TICKS) ? MAX_TICKS : ERROR_TICKS;
    localparam integer TW = (MAX_TICKS2 <= 2) ? 1 : $clog2(MAX_TICKS2 + 1);

    reg [3:0] next_state;
    reg [TW-1:0] timer_count;
    wire is_digit = (key_code <= 4'd9);
    wire activity = key_valid && (is_digit || key_code == 4'hA ||
                                  key_code == 4'hB || key_code == 4'hC);

    always @(*) begin
        next_state = state;
        case (state)
            ST_BOOT:  if (flash_init_done) next_state = ST_WAIT;
            ST_WAIT:  if (temporary_event) next_state = ST_TEMP;
                      else if (admin_event) next_state = ST_ADMIN;
                      else if (sw1_event) next_state = ST_USER;
            ST_USER:  if (key_valid && key_code == 4'hC) next_state = ST_WAIT;
                      else if ((timer_count >= LOCK_TICKS-1) && !activity) next_state = ST_WAIT;
                      else if (key_valid && key_code == 4'hA && entry_count == 3'd4) begin
                          if (entry_digits == stored_password ||
                              (temporary_valid && entry_digits == temporary_password))
                              next_state = ST_OPEN;
                          else if (error_count == 3'd3) next_state = ST_ALARM;
                          else next_state = ST_ERROR;
                      end
            ST_ERROR: if (timer_count >= ERROR_TICKS-1) next_state = ST_USER;
            ST_OPEN:  if ((key_valid && key_code == 4'hA) ||
                          (timer_count >= OPEN_TICKS-1)) next_state = ST_WAIT;
                      else if (admin_event) next_state = ST_ADMIN;
            ST_ADMIN: if (key_valid && key_code == 4'hC) next_state = ST_WAIT;
                      else if ((timer_count >= LOCK_TICKS-1) && !activity) next_state = ST_WAIT;
                      else if (key_valid && key_code == 4'hA && entry_count == 3'd4)
                          next_state = ST_SAVE;
            ST_SAVE:  if (save_done) next_state = ST_WAIT;
            // A replacement request wins over timeout or simultaneous input,
            // so the new password always remains visible for a full interval.
            ST_TEMP:  if (temporary_event) next_state = ST_TEMP;
                      else if (sw1_event) next_state = ST_USER;
                      else if (key_valid && (key_code == 4'hA || key_code == 4'hC))
                          next_state = ST_WAIT;
                      else if (timer_count >= LOCK_TICKS-1) next_state = ST_WAIT;
            // KEY2 completes the administrator's alarm handling and starts a
            // clean input session.  No SW1 toggle is required afterward.
            ST_ALARM: if (alarm_clear_event) next_state = ST_USER;
            default: next_state = ST_BOOT;
        endcase
    end

    always @(posedge clk) begin
        if (rst) begin
            state          <= ST_BOOT;
            timer_count    <= {TW{1'b0}};
            entry_digits   <= 16'h0000;
            entry_count    <= 3'd0;
            error_count    <= 3'd0;
            save_request   <= 1'b0;
            save_password  <= 16'h1234;
            capture_start  <= 1'b0;
            display_fault  <= 1'b0;
        end else begin
            state         <= next_state;
            save_request  <= 1'b0;
            capture_start <= 1'b0;

            if (state != next_state) begin
                timer_count <= {TW{1'b0}};
                if (next_state == ST_USER || next_state == ST_ADMIN ||
                    next_state == ST_WAIT) begin
                    entry_digits <= 16'h0000;
                    entry_count  <= 3'd0;
                end
                if (next_state == ST_OPEN)
                    error_count <= 3'd0;
                if (next_state == ST_ERROR)
                    error_count <= error_count + 1'b1;
                if (next_state == ST_ALARM) begin
                    error_count   <= 3'd4;
                    capture_start <= 1'b1;
                end
                // An acknowledged alarm starts a new four-attempt window.
                // Without this reset the three-bit counter would display
                // Err5..Err7 and wrap, which is not a valid attempt policy.
                if (state == ST_ALARM && alarm_clear_event)
                    error_count <= 3'd0;
                if (next_state == ST_SAVE) begin
                    save_password <= entry_digits;
                    save_request  <= 1'b1;
                end
                if (state == ST_SAVE && next_state == ST_WAIT)
                    display_fault <= ~save_success;
            end else begin
                if ((activity || temporary_event) &&
                    (state == ST_USER || state == ST_ADMIN || state == ST_OPEN || state == ST_TEMP))
                    timer_count <= {TW{1'b0}};
                else if (state == ST_USER || state == ST_ADMIN || state == ST_OPEN ||
                         state == ST_ERROR || state == ST_TEMP)
                    timer_count <= timer_count + 1'b1;

                if ((state == ST_USER || state == ST_ADMIN) && key_valid) begin
                    if (is_digit && entry_count < 3'd4) begin
                        entry_digits <= {entry_digits[11:0], key_code};
                        entry_count  <= entry_count + 1'b1;
                    end else if (key_code == 4'hB && entry_count != 0) begin
                        entry_digits <= {4'h0, entry_digits[15:4]};
                        entry_count  <= entry_count - 1'b1;
                    end
                end
            end

            // Starting a new user/admin/temporary-password operation clears a
            // previous save-error indication even when that same event also
            // causes a state transition on this clock edge.
            if (display_fault && (sw1_event || admin_event || temporary_event))
                display_fault <= 1'b0;
            if (flash_fault)
                display_fault <= 1'b1;
        end
    end

    always @(*) begin
        unlocked     = (state == ST_OPEN);
        alarm_active = (state == ST_ALARM);
    end
endmodule

password_lock_system/sim/tb_basic_admin_save.sv
`timescale 1ns/1ps

module tb_basic_admin_save;
    localparam [3:0] ST_WAIT=4'd1, ST_ADMIN=4'd5, ST_SAVE=4'd6;
    reg test_pass=0;
    reg clk=0,rst=1,init_done=0,admin=0,sw1=0,key_valid=0;
    reg save_done=0,save_success=0;
    reg [3:0] key_code=0;
    reg [7:0] scenario=0;
    wire save_request,display_fault;
    wire [15:0] save_password,entry_digits;
    wire [3:0] state;
    wire [2:0] entry_count;

    always #5 clk=~clk;
    lock_controller #(.CLOCK_HZ(1000),.LOCK_TIMEOUT_S(1),.OPEN_TIMEOUT_S(2),.ERROR_DISPLAY_MS(2)) dut(
        .clk(clk),.rst(rst),.flash_init_done(init_done),.stored_password(16'h1234),
        .flash_fault(1'b0),.sw1_event(sw1),.admin_event(admin),.alarm_clear_event(1'b0),
        .temporary_event(1'b0),.temporary_password(16'h0000),.temporary_valid(1'b0),
        .key_valid(key_valid),.key_code(key_code),.save_done(save_done),.save_success(save_success),
        .save_request(save_request),.save_password(save_password),.capture_start(),.unlocked(),
        .alarm_active(),.state(state),.entry_digits(entry_digits),.entry_count(entry_count),
        .error_count(),.display_fault(display_fault));

    task pulse_admin; begin @(negedge clk);admin=1;@(negedge clk);admin=0;end endtask
    task pulse_sw1; begin @(negedge clk);sw1=1;@(negedge clk);sw1=0;end endtask
    task key(input [3:0] code); begin @(negedge clk);key_code=code;key_valid=1;@(negedge clk);key_valid=0;end endtask
    task digits(input [15:0] value); begin key(value[15:12]);key(value[11:8]);key(value[7:4]);key(value[3:0]);end endtask
    task check(input bit ok,input string message); if(!ok)$fatal(1,"FAIL: %s",message); endtask

    initial begin
        scenario=1;repeat(4)@(negedge clk);rst=0;init_done=1;repeat(2)@(negedge clk);
        scenario=2;pulse_admin();check(state==ST_ADMIN,"KEY1 did not enter SET");
        digits(16'h5678);key(4'hA);#1;
        check(state==ST_SAVE && save_request && save_password==16'h5678,"save request incorrect");
        scenario=3;@(negedge clk);save_success=1;save_done=1;@(negedge clk);save_done=0;save_success=0;
        repeat(2)@(negedge clk);check(state==ST_WAIT && !display_fault,"successful save did not return PASS");

        scenario=4;pulse_admin();digits(16'h2468);key(4'hA);#1;
        check(state==ST_SAVE && save_password==16'h2468,"second save request incorrect");
        @(negedge clk);save_done=1;save_success=0;@(negedge clk);save_done=0;
        repeat(2)@(negedge clk);check(state==ST_WAIT && display_fault,"failed save did not show FErr");
        pulse_sw1();check(!display_fault,"new operation did not clear FErr");

        scenario=5;key(4'hC);repeat(2)@(negedge clk);pulse_admin();repeat(1005)@(negedge clk);
        check(state==ST_WAIT,"SET inactivity timeout failed");
        test_pass=1;$display("PASS tb_basic_admin_save");$finish;
    end
endmodule

simulation_waveforms/02_admin_password_save/tb_basic_admin_save.vcd
$date
   Tue Sep  8 16:53:03 2026
$end

$version
  2023.2
$end

$timescale
  1ps
$end

$scope module tb_basic_admin_save $end
$var reg 1 Q test_pass $end
$var reg 1 R clk $end
$var reg 1 S rst $end
$var reg 1 T init_done $end
$var reg 1 U admin $end
$var reg 1 V sw1 $end
$var reg 1 W key_valid $end
$var reg 1 X save_done $end
$var reg 1 Y save_success $end
$var reg 4 Z key_code [3:0] $end
$var reg 8 [ scenario [7:0] $end
$var wire 1 \ save_request $end
$var wire 1 ] display_fault $end
$var wire 16 ^ save_password [15:0] $end
$var wire 16 _ entry_digits [15:0] $end
$var wire 4 ` state [3:0] $end
$var wire 3 a entry_count [2:0] $end
$var parameter 4 b ST_WAIT [3:0] $end
$var parameter 4 c ST_ADMIN [3:0] $end
$var parameter 4 d ST_SAVE [3:0] $end
$scope module dut $end
$var wire 1 ! clk $end
$var wire 1 " rst $end
$var wire 1 # flash_init_done $end
$var wire 16 $ stored_password [15:0] $end
$var wire 1 % flash_fault $end
$var wire 1 & sw1_event $end
$var wire 1 ' admin_event $end
$var wire 1 % alarm_clear_event $end
$var wire 1 % temporary_event $end
$var wire 16 ( temporary_password [15:0] $end
$var wire 1 % temporary_valid $end
$var wire 1 ) key_valid $end
$var wire 4 * key_code [3:0] $end
$var wire 1 + save_done $end
$var wire 1 , save_success $end
$var reg 1 - save_request $end
$var reg 16 . save_password [15:0] $end
$var reg 1 / capture_start $end
$var reg 1 0 unlocked $end
$var reg 1 1 alarm_active $end
$var reg 4 2 state [3:0] $end
$var reg 16 3 entry_digits [15:0] $end
$var reg 3 4 entry_count [2:0] $end
$var reg 3 5 error_count [2:0] $end
$var reg 1 6 display_fault $end
$var reg 4 7 next_state [3:0] $end
$var reg 11 8 timer_count [10:0] $end
$var wire 1 9 is_digit $end
$var wire 1 : activity $end
$var parameter 0 ; CLOCK_HZ [31:0] $end
$var parameter 0 < LOCK_TIMEOUT_S [31:0] $end
$var parameter 0 = OPEN_TIMEOUT_S [31:0] $end
$var parameter 0 > ERROR_DISPLAY_MS [31:0] $end
$var parameter 4 ? ST_BOOT [3:0] $end
$var parameter 4 @ ST_WAIT [3:0] $end
$var parameter 4 A ST_USER [3:0] $end
$var parameter 4 B ST_ERROR [3:0] $end
$var parameter 4 C ST_OPEN [3:0] $end
$var parameter 4 D ST_ADMIN [3:0] $end
$var parameter 4 E ST_SAVE [3:0] $end
$var parameter 4 F ST_ALARM [3:0] $end
$var parameter 4 G ST_TEMP [3:0] $end
$var parameter 0 H LOCK_TICKS [31:0] $end
$var parameter 0 I OPEN_TICKS [31:0] $end
$var parameter 0 J ERROR_TICKS [31:0] $end
$var parameter 0 K MAX_TICKS [31:0] $end
$var parameter 0 L MAX_TICKS2 [31:0] $end
$var parameter 0 M TW [31:0] $end
$upscope $end
$scope task key $end
$var reg 4 N code [3:0] $end
$upscope $end
$scope task digits $end
$var reg 16 O value [15:0] $end
$upscope $end
$scope task check $end
$var reg 1 P ok $end
$upscope $end
$upscope $end
$enddefinitions $end

#0
$dumpvars
0!
1"
0#
b1001000110100 $
0%
0&
0'
b0 (
0)
b0 *
0+
0,
x-
bx .
x/
x0
x1
bx 2
bx 3
bx 4
bx 5
x6
b0 7
bx 8
19
0:
b1111101000 ;
b1 <
b10 =
b10 >
b0 ?
b1 @
b10 A
b11 B
b100 C
b101 D
b110 E
b111 F
b1000 G
b1111101000 H
b11111010000 I
b10 J
b11111010000 K
b11111010000 L
b1011 M
bx N
bx O
0P
0Q
0R
1S
0T
0U
0V
0W
0X
0Y
b0 Z
b1 [
x\
x]
bx ^
bx _
bx `
bx a
b1 b
b101 c
b110 d
$end

#5000
1!
0-
b1001000110100 .
0/
00
01
b0 2
b0 3
b0 4
b0 5
06
b0 8
1R
0\
0]
b1001000110100 ^
b0 _
b0 `
b0 a

#10000
0!
0R

#15000
1!
1R

#20000
0!
0R

#25000
1!
1R

#30000
0!
0R

#35000
1!
1R

#40000
0!
0"
1#
b1 7
0R
0S
1T

#45000
1!
b1 2
1R
b1 `

#50000
0!
0R

#55000
1!
1R

#60000
0!
0R
b10 [

#65000
1!
1R

#70000
0!
1'
b101 7
0R
1U

#75000
1!
b101 2
1R
b101 `

#80000
0!
0'
b101 N
b101011001111000 O
1P
0R
0U

#85000
1!
b1 8
1R

#90000
0!
1)
b101 *
1:
0R
1W
b101 Z

#95000
1!
b101 3
b1 4
b0 8
1R
b101 _
b1 a

#100000
0!
0)
0:
b110 N
0R
0W

#105000
1!
b1 8
1R

#110000
0!
1)
b110 *
1:
0R
1W
b110 Z

#115000
1!
b1010110 3
b10 4
b0 8
1R
b1010110 _
b10 a

#120000
0!
0)
0:
b111 N
0R
0W

#125000
1!
b1 8
1R

#130000
0!
1)
b111 *
1:
0R
1W
b111 Z

#135000
1!
b10101100111 3
b11 4
b0 8
1R
b10101100111 _
b11 a

#140000
0!
0)
0:
b1000 N
0R
0W

#145000
1!
b1 8
1R

#150000
0!
1)
b1000 *
1:
0R
1W
b1000 Z

#155000
1!
b101011001111000 3
b100 4
b0 8
1R
b101011001111000 _
b100 a

#160000
0!
0)
0:
b1010 N
0R
0W

#165000
1!
b1 8
1R

#170000
0!
1)
b1010 *
b110 7
09
1:
0R
1W
b1010 Z

#175000
1!
1-
b101011001111000 .
b110 2
b0 8
1R
1\
b101011001111000 ^
b110 `

#180000
0!
0)
0:
0R
0W

#181000
b11 [

#185000
1!
0-
1R
0\

#190000
0!
1+
1,
b1 7
0R
1X
1Y

#195000
1!
b1 2
b0 3
b0 4
1R
b0 _
b1 `
b0 a

#200000
0!
0+
0,
0R
0X
0Y

#205000
1!
1R

#210000
0!
0R

#215000
1!
1R

#220000
0!
0R
b100 [

#225000
1!
1R

#230000
0!
1'
b101 7
0R
1U

#235000
1!
b101 2
1R
b101 `

#240000
0!
0'
b10 N
b10010001101000 O
0R
0U

#245000
1!
b1 8
1R

#250000
0!
1)
b10 *
19
1:
0R
1W
b10 Z

#255000
1!
b10 3
b1 4
b0 8
1R
b10 _
b1 a

#260000
0!
0)
0:
b100 N
0R
0W

#265000
1!
b1 8
1R

#270000
0!
1)
b100 *
1:
0R
1W
b100 Z

#275000
1!
b100100 3
b10 4
b0 8
1R
b100100 _
b10 a

#280000
0!
0)
0:
b110 N
0R
0W

#285000
1!
b1 8
1R

#290000
0!
1)
b110 *
1:
0R
1W
b110 Z

#295000
1!
b1001000110 3
b11 4
b0 8
1R
b1001000110 _
b11 a

#300000
0!
0)
0:
b1000 N
0R
0W

#305000
1!
b1 8
1R

#310000
0!
1)
b1000 *
1:
0R
1W
b1000 Z

#315000
1!
b10010001101000 3
b100 4
b0 8
1R
b10010001101000 _
b100 a

#320000
0!
0)
0:
b1010 N
0R
0W

#325000
1!
b1 8
1R

#330000
0!
1)
b1010 *
b110 7
09
1:
0R
1W
b1010 Z

#335000
1!
1-
b10010001101000 .
b110 2
b0 8
1R
1\
b10010001101000 ^
b110 `

#340000
0!
0)
0:
0R
0W

#345000
1!
0-
1R
0\

#350000
0!
1+
b1 7
0R
1X

#355000
1!
b1 2
b0 3
b0 4
16
1R
1]
b0 _
b1 `
b0 a

#360000
0!
0+
0R
0X

#365000
1!
1R

#370000
0!
0R

#375000
1!
1R

#380000
0!
0R

#385000
1!
1R

#390000
0!
1&
b10 7
0R
1V

#395000
1!
b10 2
06
1R
0]
b10 `

#400000
0!
0&
b1100 N
0R
0V
b101 [

#405000
1!
b1 8
1R

#410000
0!
1)
b1100 *
b1 7
1:
0R
1W
b1100 Z

#415000
1!
b1 2
b0 8
1R
b1 `

#420000
0!
0)
0:
0R
0W

#425000
1!
1R

#430000
0!
0R

#435000
1!
1R

#440000
0!
0R

#445000
1!
1R

#450000
0!
1'
b101 7
0R
1U

#455000
1!
b101 2
1R
b101 `

#460000
0!
0'
0R
0U

#465000
1!
b1 8
1R

#470000
0!
0R

#475000
1!
b10 8
1R

#480000
0!
0R

#485000
1!
b11 8
1R

#490000
0!
0R

#495000
1!
b100 8
1R

#500000
0!
0R

#505000
1!
b101 8
1R

#510000
0!
0R

#515000
1!
b110 8
1R

#520000
0!
0R

#525000
1!
b111 8
1R

#530000
0!
0R

#535000
1!
b1000 8
1R

#540000
0!
0R

#545000
1!
b1001 8
1R

#550000
0!
0R

#555000
1!
b1010 8
1R

#560000
0!
0R

#565000
1!
b1011 8
1R

#570000
0!
0R

#575000
1!
b1100 8
1R

#580000
0!
0R

#585000
1!
b1101 8
1R

#590000
0!
0R

#595000
1!
b1110 8
1R

#600000
0!
0R

#605000
1!
b1111 8
1R

#610000
0!
0R

#615000
1!
b10000 8
1R

#620000
0!
0R

#625000
1!
b10001 8
1R

#630000
0!
0R

#635000
1!
b10010 8
1R

#640000
0!
0R

#645000
1!
b10011 8
1R

#650000
0!
0R

#655000
1!
b10100 8
1R

#660000
0!
0R

#665000
1!
b10101 8
1R

#670000
0!
0R

#675000
1!
b10110 8
1R

#680000
0!
0R

#685000
1!
b10111 8
1R

#690000
0!
0R

#695000
1!
b11000 8
1R

#700000
0!
0R

#705000
1!
b11001 8
1R

#710000
0!
0R

#715000
1!
b11010 8
1R

#720000
0!
0R

#725000
1!
b11011 8
1R

#730000
0!
0R

#735000
1!
b11100 8
1R

#740000
0!
0R

#745000
1!
b11101 8
1R

#750000
0!
0R

#755000
1!
b11110 8
1R

#760000
0!
0R

#765000
1!
b11111 8
1R

#770000
0!
0R

#775000
1!
b100000 8
1R

#780000
0!
0R

#785000
1!
b100001 8
1R

#790000
0!
0R

#795000
1!
b100010 8
1R

#800000
0!
0R

#805000
1!
b100011 8
1R

#810000
0!
0R

#815000
1!
b100100 8
1R

#820000
0!
0R

#825000
1!
b100101 8
1R

#830000
0!
0R

#835000
1!
b100110 8
1R

#840000
0!
0R

#845000
1!
b100111 8
1R

#850000
0!
0R

#855000
1!
b101000 8
1R

#860000
0!
0R

#865000
1!
b101001 8
1R

#870000
0!
0R

#875000
1!
b101010 8
1R

#880000
0!
0R

#885000
1!
b101011 8
1R

#890000
0!
0R

#895000
1!
b101100 8
1R

#900000
0!
0R

#905000
1!
b101101 8
1R

#910000
0!
0R

#915000
1!
b101110 8
1R

#920000
0!
0R

#925000
1!
b101111 8
1R

#930000
0!
0R

#935000
1!
b110000 8
1R

#940000
0!
0R

#945000
1!
b110001 8
1R

#950000
0!
0R

#955000
1!
b110010 8
1R

#960000
0!
0R

#965000
1!
b110011 8
1R

#970000
0!
0R

#975000
1!
b110100 8
1R

#980000
0!
0R

#985000
1!
b110101 8
1R

#990000
0!
0R

#995000
1!
b110110 8
1R

#1000000
0!
0R

#1005000
1!
b110111 8
1R

#1010000
0!
0R

#1015000
1!
b111000 8
1R

#1020000
0!
0R

#1025000
1!
b111001 8
1R

#1030000
0!
0R

#1035000
1!
b111010 8
1R

#1040000
0!
0R

#1045000
1!
b111011 8
1R

#1050000
0!
0R

#1055000
1!
b111100 8
1R

#1060000
0!
0R

#1065000
1!
b111101 8
1R

#1070000
0!
0R

#1075000
1!
b111110 8
1R

#1080000
0!
0R

#1085000
1!
b111111 8
1R

#1090000
0!
0R

#1095000
1!
b1000000 8
1R

#1100000
0!
0R

#1105000
1!
b1000001 8
1R

#1110000
0!
0R

#1115000
1!
b1000010 8
1R

#1120000
0!
0R

#1125000
1!
b1000011 8
1R

#1130000
0!
0R

#1135000
1!
b1000100 8
1R

#1140000
0!
0R

#1145000
1!
b1000101 8
1R

#1150000
0!
0R

#1155000
1!
b1000110 8
1R

#1160000
0!
0R

#1165000
1!
b1000111 8
1R

#1170000
0!
0R

#1175000
1!
b1001000 8
1R

#1180000
0!
0R

#1185000
1!
b1001001 8
1R

#1190000
0!
0R

#1195000
1!
b1001010 8
1R

#1200000
0!
0R

#1205000
1!
b1001011 8
1R

#1210000
0!
0R

#1215000
1!
b1001100 8
1R

#1220000
0!
0R

#1225000
1!
b1001101 8
1R

#1230000
0!
0R

#1235000
1!
b1001110 8
1R

#1240000
0!
0R

#1245000
1!
b1001111 8
1R

#1250000
0!
0R

#1255000
1!
b1010000 8
1R

#1260000
0!
0R

#1265000
1!
b1010001 8
1R

#1270000
0!
0R

#1275000
1!
b1010010 8
1R

#1280000
0!
0R

#1285000
1!
b1010011 8
1R

#1290000
0!
0R

#1295000
1!
b1010100 8
1R

#1300000
0!
0R

#1305000
1!
b1010101 8
1R

#1310000
0!
0R

#1315000
1!
b1010110 8
1R

#1320000
0!
0R

#1325000
1!
b1010111 8
1R

#1330000
0!
0R

#1335000
1!
b1011000 8
1R

#1340000
0!
0R

#1345000
1!
b1011001 8
1R

#1350000
0!
0R

#1355000
1!
b1011010 8
1R

#1360000
0!
0R

#1365000
1!
b1011011 8
1R

#1370000
0!
0R

#1375000
1!
b1011100 8
1R

#1380000
0!
0R

#1385000
1!
b1011101 8
1R

#1390000
0!
0R

#1395000
1!
b1011110 8
1R

#1400000
0!
0R

#1405000
1!
b1011111 8
1R

#1410000
0!
0R

#1415000
1!
b1100000 8
1R

#1420000
0!
0R

#1425000
1!
b1100001 8
1R

#1430000
0!
0R

#1435000
1!
b1100010 8
1R

#1440000
0!
0R

#1445000
1!
b1100011 8
1R

#1450000
0!
0R

#1455000
1!
b1100100 8
1R

#1460000
0!
0R

#1465000
1!
b1100101 8
1R

#1470000
0!
0R

#1475000
1!
b1100110 8
1R

#1480000
0!
0R

#1485000
1!
b1100111 8
1R

#1490000
0!
0R

#1495000
1!
b1101000 8
1R

#1500000
0!
0R

#1505000
1!
b1101001 8
1R

#1510000
0!
0R

#1515000
1!
b1101010 8
1R

#1520000
0!
0R

#1525000
1!
b1101011 8
1R

#1530000
0!
0R

#1535000
1!
b1101100 8
1R

#1540000
0!
0R

#1545000
1!
b1101101 8
1R

#1550000
0!
0R

#1555000
1!
b1101110 8
1R

#1560000
0!
0R

#1565000
1!
b1101111 8
1R

#1570000
0!
0R

#1575000
1!
b1110000 8
1R

#1580000
0!
0R

#1585000
1!
b1110001 8
1R

#1590000
0!
0R

#1595000
1!
b1110010 8
1R

#1600000
0!
0R

#1605000
1!
b1110011 8
1R

#1610000
0!
0R

#1615000
1!
b1110100 8
1R

#1620000
0!
0R

#1625000
1!
b1110101 8
1R

#1630000
0!
0R

#1635000
1!
b1110110 8
1R

#1640000
0!
0R

#1645000
1!
b1110111 8
1R

#1650000
0!
0R

#1655000
1!
b1111000 8
1R

#1660000
0!
0R

#1665000
1!
b1111001 8
1R

#1670000
0!
0R

#1675000
1!
b1111010 8
1R

#1680000
0!
0R

#1685000
1!
b1111011 8
1R

#1690000
0!
0R

#1695000
1!
b1111100 8
1R

#1700000
0!
0R

#1705000
1!
b1111101 8
1R

#1710000
0!
0R

#1715000
1!
b1111110 8
1R

#1720000
0!
0R

#1725000
1!
b1111111 8
1R

#1730000
0!
0R

#1735000
1!
b10000000 8
1R

#1740000
0!
0R

#1745000
1!
b10000001 8
1R

#1750000
0!
0R

#1755000
1!
b10000010 8
1R

#1760000
0!
0R

#1765000
1!
b10000011 8
1R

#1770000
0!
0R

#1775000
1!
b10000100 8
1R

#1780000
0!
0R

#1785000
1!
b10000101 8
1R

#1790000
0!
0R

#1795000
1!
b10000110 8
1R

#1800000
0!
0R

#1805000
1!
b10000111 8
1R

#1810000
0!
0R

#1815000
1!
b10001000 8
1R

#1820000
0!
0R

#1825000
1!
b10001001 8
1R

#1830000
0!
0R

#1835000
1!
b10001010 8
1R

#1840000
0!
0R

#1845000
1!
b10001011 8
1R

#1850000
0!
0R

#1855000
1!
b10001100 8
1R

#1860000
0!
0R

#1865000
1!
b10001101 8
1R

#1870000
0!
0R

#1875000
1!
b10001110 8
1R

#1880000
0!
0R

#1885000
1!
b10001111 8
1R

#1890000
0!
0R

#1895000
1!
b10010000 8
1R

#1900000
0!
0R

#1905000
1!
b10010001 8
1R

#1910000
0!
0R

#1915000
1!
b10010010 8
1R

#1920000
0!
0R

#1925000
1!
b10010011 8
1R

#1930000
0!
0R

#1935000
1!
b10010100 8
1R

#1940000
0!
0R

#1945000
1!
b10010101 8
1R

#1950000
0!
0R

#1955000
1!
b10010110 8
1R

#1960000
0!
0R

#1965000
1!
b10010111 8
1R

#1970000
0!
0R

#1975000
1!
b10011000 8
1R

#1980000
0!
0R

#1985000
1!
b10011001 8
1R

#1990000
0!
0R

#1995000
1!
b10011010 8
1R

#2000000
0!
0R

#2005000
1!
b10011011 8
1R

#2010000
0!
0R

#2015000
1!
b10011100 8
1R

#2020000
0!
0R

#2025000
1!
b10011101 8
1R

#2030000
0!
0R

#2035000
1!
b10011110 8
1R

#2040000
0!
0R

#2045000
1!
b10011111 8
1R

#2050000
0!
0R

#2055000
1!
b10100000 8
1R

#2060000
0!
0R

#2065000
1!
b10100001 8
1R

#2070000
0!
0R

#2075000
1!
b10100010 8
1R

#2080000
0!
0R

#2085000
1!
b10100011 8
1R

#2090000
0!
0R

#2095000
1!
b10100100 8
1R

#2100000
0!
0R

#2105000
1!
b10100101 8
1R

#2110000
0!
0R

#2115000
1!
b10100110 8
1R

#2120000
0!
0R

#2125000
1!
b10100111 8
1R

#2130000
0!
0R

#2135000
1!
b10101000 8
1R

#2140000
0!
0R

#2145000
1!
b10101001 8
1R

#2150000
0!
0R

#2155000
1!
b10101010 8
1R

#2160000
0!
0R

#2165000
1!
b10101011 8
1R

#2170000
0!
0R

#2175000
1!
b10101100 8
1R

#2180000
0!
0R

#2185000
1!
b10101101 8
1R

#2190000
0!
0R

#2195000
1!
b10101110 8
1R

#2200000
0!
0R

#2205000
1!
b10101111 8
1R

#2210000
0!
0R

#2215000
1!
b10110000 8
1R

#2220000
0!
0R

#2225000
1!
b10110001 8
1R

#2230000
0!
0R

#2235000
1!
b10110010 8
1R

#2240000
0!
0R

#2245000
1!
b10110011 8
1R

#2250000
0!
0R

#2255000
1!
b10110100 8
1R

#2260000
0!
0R

#2265000
1!
b10110101 8
1R

#2270000
0!
0R

#2275000
1!
b10110110 8
1R

#2280000
0!
0R

#2285000
1!
b10110111 8
1R

#2290000
0!
0R

#2295000
1!
b10111000 8
1R

#2300000
0!
0R

#2305000
1!
b10111001 8
1R

#2310000
0!
0R

#2315000
1!
b10111010 8
1R

#2320000
0!
0R

#2325000
1!
b10111011 8
1R

#2330000
0!
0R

#2335000
1!
b10111100 8
1R

#2340000
0!
0R

#2345000
1!
b10111101 8
1R

#2350000
0!
0R

#2355000
1!
b10111110 8
1R

#2360000
0!
0R

#2365000
1!
b10111111 8
1R

#2370000
0!
0R

#2375000
1!
b11000000 8
1R

#2380000
0!
0R

#2385000
1!
b11000001 8
1R

#2390000
0!
0R

#2395000
1!
b11000010 8
1R

#2400000
0!
0R

#2405000
1!
b11000011 8
1R

#2410000
0!
0R

#2415000
1!
b11000100 8
1R

#2420000
0!
0R

#2425000
1!
b11000101 8
1R

#2430000
0!
0R

#2435000
1!
b11000110 8
1R

#2440000
0!
0R

#2445000
1!
b11000111 8
1R

#2450000
0!
0R

#2455000
1!
b11001000 8
1R

#2460000
0!
0R

#2465000
1!
b11001001 8
1R

#2470000
0!
0R

#2475000
1!
b11001010 8
1R

#2480000
0!
0R

#2485000
1!
b11001011 8
1R

#2490000
0!
0R

#2495000
1!
b11001100 8
1R

#2500000
0!
0R

#2505000
1!
b11001101 8
1R

#2510000
0!
0R

#2515000
1!
b11001110 8
1R

#2520000
0!
0R

#2525000
1!
b11001111 8
1R

#2530000
0!
0R

#2535000
1!
b11010000 8
1R

#2540000
0!
0R

#2545000
1!
b11010001 8
1R

#2550000
0!
0R

#2555000
1!
b11010010 8
1R

#2560000
0!
0R

#2565000
1!
b11010011 8
1R

#2570000
0!
0R

#2575000
1!
b11010100 8
1R

#2580000
0!
0R

#2585000
1!
b11010101 8
1R

#2590000
0!
0R

#2595000
1!
b11010110 8
1R

#2600000
0!
0R

#2605000
1!
b11010111 8
1R

#2610000
0!
0R

#2615000
1!
b11011000 8
1R

#2620000
0!
0R

#2625000
1!
b11011001 8
1R

#2630000
0!
0R

#2635000
1!
b11011010 8
1R

#2640000
0!
0R

#2645000
1!
b11011011 8
1R

#2650000
0!
0R

#2655000
1!
b11011100 8
1R

#2660000
0!
0R

#2665000
1!
b11011101 8
1R

#2670000
0!
0R

#2675000
1!
b11011110 8
1R

#2680000
0!
0R

#2685000
1!
b11011111 8
1R

#2690000
0!
0R

#2695000
1!
b11100000 8
1R

#2700000
0!
0R

#2705000
1!
b11100001 8
1R

#2710000
0!
0R

#2715000
1!
b11100010 8
1R

#2720000
0!
0R

#2725000
1!
b11100011 8
1R

#2730000
0!
0R

#2735000
1!
b11100100 8
1R

#2740000
0!
0R

#2745000
1!
b11100101 8
1R

#2750000
0!
0R

#2755000
1!
b11100110 8
1R

#2760000
0!
0R

#2765000
1!
b11100111 8
1R

