password_lock_system/rtl/sevenseg_display.v
`timescale 1ns/1ps

// 8 位共阳数码管显示控制：先按系统状态组合出 8 个字符，再以 8 kHz 总扫描率轮流点亮。
// seg_n 和 digit_sel 都是低有效；人眼利用视觉暂留看到 8 位同时显示。
module sevenseg_display #(
    parameter integer CLOCK_HZ = 50_000_000
) (
    input  wire        clk,
    input  wire        rst,
    input  wire [3:0]  state,
    input  wire [15:0] entry_digits,
    input  wire [2:0]  entry_count,
    input  wire [2:0]  error_count,
    input  wire [15:0] temporary_password,
    input  wire        display_fault,
    output reg  [7:0]  seg_n,
    output reg  [7:0]  digit_sel
);
    // 状态编码必须与 lock_controller 一致；字符编码 0~9 直接表示数字，0x10 以上表示字母/空白。
    localparam [3:0] ST_BOOT=0, ST_WAIT=1, ST_USER=2, ST_ERROR=3,
                     ST_OPEN=4, ST_ADMIN=5, ST_SAVE=6, ST_ALARM=7,
                     ST_TEMP=8;
    localparam [4:0] CH_BLANK=5'h10, CH_P=5'h11, CH_A=5'h12, CH_S=5'h13,
                     CH_E=5'h14, CH_T=5'h15, CH_R=5'h16, CH_O=5'h17,
                     CH_N=5'h18, CH_L=5'h19, CH_F=5'h1A, CH_I=5'h1B,
                     CH_U=5'h1C, CH_M=5'h1D;
    reg [18:0] refresh_count;
    reg [2:0] scan;
    reg [4:0] chars [0:7];
    integer i;

    // 字符到 a~g、dp 八段低有效码的查找表；默认全 1 表示熄灭。
    function [7:0] encode;
        input [4:0] ch;
        begin
            case (ch)
                0: encode=8'b11000000; 1: encode=8'b11111001;
                2: encode=8'b10100100; 3: encode=8'b10110000;
                4: encode=8'b10011001; 5: encode=8'b10010010;
                6: encode=8'b10000010; 7: encode=8'b11111000;
                8: encode=8'b10000000; 9: encode=8'b10010000;
                CH_P: encode=8'b10001100; CH_A: encode=8'b10001000;
                CH_S: encode=8'b10010010; CH_E: encode=8'b10000110;
                CH_T: encode=8'b10000111; CH_R: encode=8'b10101111;
                CH_O: encode=8'b11000000; CH_N: encode=8'b10101011;
                CH_L: encode=8'b11000111; CH_F: encode=8'b10001110;
                CH_I: encode=8'b11111001;
                CH_U: encode=8'b11000001;
                CH_M: encode=8'b10101010;
                default: encode=8'b11111111;
            endcase
        end
    endfunction

    // 显示优先级：Flash 故障 FErr 最高，其次按状态显示；非 TEMP 状态再覆盖右侧输入数字。
    always @(*) begin
        for (i=0; i<8; i=i+1) chars[i]=CH_BLANK;
        if (display_fault) begin
            chars[7]=CH_F; chars[6]=CH_E; chars[5]=CH_R; chars[4]=CH_R;
        end else case (state)
            ST_BOOT: begin chars[7]=CH_I; chars[6]=CH_N; chars[5]=CH_I; chars[4]=CH_T; end
            ST_WAIT: begin chars[7]=CH_P; chars[6]=CH_A; chars[5]=CH_S; chars[4]=CH_S; end
            ST_USER: begin chars[7]=CH_P; chars[6]=CH_A; chars[5]=CH_S; chars[4]=CH_S; end
            ST_ERROR: begin chars[7]=CH_E; chars[6]=CH_R; chars[5]=CH_R; chars[4]={2'b00,error_count}; end
            ST_OPEN: begin chars[7]=CH_O; chars[6]=CH_P; chars[5]=CH_E; chars[4]=CH_N; end
            ST_ADMIN: begin chars[7]=CH_S; chars[6]=CH_E; chars[5]=CH_T; chars[4]=CH_BLANK; end
            ST_SAVE: begin chars[7]=CH_S; chars[6]=CH_A; chars[5]=CH_U; chars[4]=CH_E; end
            ST_ALARM: begin chars[7]=CH_A; chars[6]=CH_L; chars[5]=CH_A; chars[4]=CH_R; end
            ST_TEMP: begin
                chars[7]=CH_T; chars[6]=CH_E; chars[5]=CH_M; chars[4]=CH_P;
                chars[3]=temporary_password[15:12];
                chars[2]=temporary_password[11:8];
                chars[1]=temporary_password[7:4];
                chars[0]=temporary_password[3:0];
            end
            default: ;
        endcase
        if (state != ST_TEMP) begin
            if (entry_count > 0) chars[0] = entry_digits[3:0];
            if (entry_count > 1) chars[1] = entry_digits[7:4];
            if (entry_count > 2) chars[2] = entry_digits[11:8];
            if (entry_count > 3) chars[3] = entry_digits[15:12];
        end
    end

    // 每 CLOCK_HZ/8000 个系统时钟切换一位，因此每位刷新约 1 kHz。
    always @(posedge clk) begin
        if (rst) begin
            refresh_count <= 0;
            scan <= 0;
        end else if (refresh_count == CLOCK_HZ/8000-1) begin
            refresh_count <= 0;
            scan <= scan + 1'b1;
        end else refresh_count <= refresh_count + 1'b1;
    end

    always @(*) begin
        // 位选低有效：每个扫描时隙只有一位为 0，段码对应当前 chars[scan]。
        digit_sel = ~(8'b00000001 << scan);
        seg_n = encode(chars[scan]);
    end
endmodule

password_lock_system/sim/tb_sevenseg_display.sv
`timescale 1ns/1ps

module tb_sevenseg_display;
    localparam [4:0] CH_BLANK=5'h10, CH_P=5'h11, CH_A=5'h12, CH_S=5'h13,
                     CH_E=5'h14, CH_T=5'h15, CH_R=5'h16, CH_O=5'h17,
                     CH_N=5'h18, CH_L=5'h19, CH_F=5'h1A, CH_I=5'h1B,
                     CH_U=5'h1C, CH_M=5'h1D;
    reg clk=0,rst=1;
    reg [3:0] state=0;
    reg [15:0] entry_digits=16'h1234;
    reg [2:0] entry_count=0,error_count=3;
    reg display_fault=0;
    reg [15:0] temporary_password=16'h2468;
    reg [7:0] scenario=0;
    wire [7:0] seg_n,digit_sel;
    reg test_pass=0;
    integer i;

    sevenseg_display #(.CLOCK_HZ(8000)) dut(
        .clk(clk),.rst(rst),.state(state),.entry_digits(entry_digits),
        .entry_count(entry_count),.error_count(error_count),
        .temporary_password(temporary_password),.display_fault(display_fault),
        .seg_n(seg_n),.digit_sel(digit_sel));

    always #5 clk=~clk;

    function integer count_zeroes(input [7:0] value);
        integer bit_index;
        begin
            count_zeroes=0;
            for(bit_index=0;bit_index<8;bit_index=bit_index+1)
                if(value[bit_index]===1'b0)count_zeroes=count_zeroes+1;
        end
    endfunction

    task check_word(input [4:0] c7,input [4:0] c6,input [4:0] c5,input [4:0] c4);
        if(dut.chars[7]!==c7 || dut.chars[6]!==c6 || dut.chars[5]!==c5 || dut.chars[4]!==c4)
            $fatal(1,"status word mismatch state=%0d",state);
    endtask

    initial begin
        repeat(2)@(posedge clk);rst=0;
        for(i=0;i<16;i=i+1)begin
            @(negedge clk);
            if(count_zeroes(digit_sel)!=1)$fatal(1,"digit select is not one-hot active-low");
        end

        scenario=1;state=0;#1;check_word(CH_I,CH_N,CH_I,CH_T);
        scenario=2;state=1;#1;check_word(CH_P,CH_A,CH_S,CH_S);
        scenario=3;state=2;entry_count=4;#1;check_word(CH_P,CH_A,CH_S,CH_S);
        if(dut.chars[3]!==1 || dut.chars[2]!==2 || dut.chars[1]!==3 || dut.chars[0]!==4)
            $fatal(1,"entered password digits are not displayed");
        scenario=4;entry_count=0;state=3;#1;check_word(CH_E,CH_R,CH_R,5'd3);
        scenario=5;state=4;#1;check_word(CH_O,CH_P,CH_E,CH_N);
        scenario=6;state=5;#1;check_word(CH_S,CH_E,CH_T,CH_BLANK);
        scenario=7;state=6;#1;check_word(CH_S,CH_A,CH_U,CH_E);
        scenario=8;state=7;#1;check_word(CH_A,CH_L,CH_A,CH_R);
        scenario=9;state=8;#1;check_word(CH_T,CH_E,CH_M,CH_P);
        if(dut.chars[3]!==2 || dut.chars[2]!==4 || dut.chars[1]!==6 || dut.chars[0]!==8)
            $fatal(1,"temporary password digits are not displayed");
        scenario=10;display_fault=1;#1;check_word(CH_F,CH_E,CH_R,CH_R);
        test_pass=1;$display("PASS tb_sevenseg_display");$finish;
    end
endmodule

simulation_waveforms/05_seven_segment/tb_sevenseg_display.vcd
$date
   Tue Sep  8 16:54:09 2026
$end

$version
  2023.2
$end

$timescale
  1ps
$end

$scope module tb_sevenseg_display $end
$var reg 1 O clk $end
$var reg 1 P rst $end
$var reg 4 Q state [3:0] $end
$var reg 16 R entry_digits [15:0] $end
$var reg 3 S entry_count [2:0] $end
$var reg 3 T error_count [2:0] $end
$var reg 1 U display_fault $end
$var reg 16 V temporary_password [15:0] $end
$var reg 8 W scenario [7:0] $end
$var wire 8 X seg_n [7:0] $end
$var wire 8 Y digit_sel [7:0] $end
$var reg 1 Z test_pass $end
$var integer 32 [ i [31:0] $end
$var parameter 5 \ CH_BLANK [4:0] $end
$var parameter 5 ] CH_P [4:0] $end
$var parameter 5 ^ CH_A [4:0] $end
$var parameter 5 _ CH_S [4:0] $end
$var parameter 5 ` CH_E [4:0] $end
$var parameter 5 a CH_T [4:0] $end
$var parameter 5 b CH_R [4:0] $end
$var parameter 5 c CH_O [4:0] $end
$var parameter 5 d CH_N [4:0] $end
$var parameter 5 e CH_L [4:0] $end
$var parameter 5 f CH_F [4:0] $end
$var parameter 5 g CH_I [4:0] $end
$var parameter 5 h CH_U [4:0] $end
$var parameter 5 i CH_M [4:0] $end
$scope module dut $end
$var wire 1 # clk $end
$var wire 1 $ rst $end
$var wire 4 % state [3:0] $end
$var wire 16 & entry_digits [15:0] $end
$var wire 3 ' entry_count [2:0] $end
$var wire 3 ( error_count [2:0] $end
$var wire 16 ) temporary_password [15:0] $end
$var wire 1 * display_fault $end
$var reg 8 + seg_n [7:0] $end
$var reg 8 , digit_sel [7:0] $end
$var reg 19 - refresh_count [18:0] $end
$var reg 3 . scan [2:0] $end
$var integer 32 / i [31:0] $end
$var parameter 0 0 CLOCK_HZ [31:0] $end
$var parameter 4 1 ST_BOOT [3:0] $end
$var parameter 4 2 ST_WAIT [3:0] $end
$var parameter 4 3 ST_USER [3:0] $end
$var parameter 4 4 ST_ERROR [3:0] $end
$var parameter 4 5 ST_OPEN [3:0] $end
$var parameter 4 6 ST_ADMIN [3:0] $end
$var parameter 4 7 ST_SAVE [3:0] $end
$var parameter 4 8 ST_ALARM [3:0] $end
$var parameter 4 9 ST_TEMP [3:0] $end
$var parameter 5 : CH_BLANK [4:0] $end
$var parameter 5 ; CH_P [4:0] $end
$var parameter 5 < CH_A [4:0] $end
$var parameter 5 = CH_S [4:0] $end
$var parameter 5 > CH_E [4:0] $end
$var parameter 5 ? CH_T [4:0] $end
$var parameter 5 @ CH_R [4:0] $end
$var parameter 5 A CH_O [4:0] $end
$var parameter 5 B CH_N [4:0] $end
$var parameter 5 C CH_L [4:0] $end
$var parameter 5 D CH_F [4:0] $end
$var parameter 5 E CH_I [4:0] $end
$var parameter 5 F CH_U [4:0] $end
$var parameter 5 G CH_M [4:0] $end
$scope function encode $end
$var reg 8 ! encode [7:0] $end
$var reg 5 " ch [4:0] $end
$upscope $end
$upscope $end
$scope function count_zeroes $end
$var integer 32 H count_zeroes [31:0] $end
$var reg 8 I value [7:0] $end
$var integer 32 J bit_index [31:0] $end
$upscope $end
$scope task check_word $end
$var reg 5 K c7 [4:0] $end
$var reg 5 L c6 [4:0] $end
$var reg 5 M c5 [4:0] $end
$var reg 5 N c4 [4:0] $end
$upscope $end
$upscope $end
$enddefinitions $end

#0
$dumpvars
b11111111 !
bx "
0#
1$
b0 %
b1001000110100 &
b0 '
b11 (
b10010001101000 )
0*
b11111111 +
bx ,
bx -
bx .
b1000 /
b1111101000000 0
b0 1
b1 2
b10 3
b11 4
b100 5
b101 6
b110 7
b111 8
b1000 9
b10000 :
b10001 ;
b10010 <
b10011 =
b10100 >
b10101 ?
b10110 @
b10111 A
b11000 B
b11001 C
b11010 D
b11011 E
b11100 F
b11101 G
bx H
bx I
bx J
bx K
bx L
bx M
bx N
0O
1P
b0 Q
b1001000110100 R
b0 S
b11 T
0U
b10010001101000 V
b0 W
b11111111 X
bx Y
0Z
bx [
b10000 \
b10001 ]
b10010 ^
b10011 _
b10100 `
b10101 a
b10110 b
b10111 c
b11000 d
b11001 e
b11010 f
b11011 g
b11100 h
b11101 i
$end

#5000
b10000 "
1#
b11111110 ,
b0 -
b0 .
1O
b11111110 Y

#10000
0#
0O

#15000
1#
0$
b11111101 ,
b1 .
1O
0P
b11111101 Y
b0 [

#20000
0#
b1 H
b11111101 I
b1000 J
0O
b1 [

#25000
1#
b11111011 ,
b10 .
1O
b11111011 Y

#30000
0#
b1 H
b11111011 I
b1000 J
0O
b10 [

#35000
1#
b11110111 ,
b11 .
1O
b11110111 Y

#40000
0#
b1 H
b11110111 I
b1000 J
0O
b11 [

#45000
b10000111 !
b10101 "
1#
b10000111 +
b11101111 ,
b100 .
1O
b10000111 X
b11101111 Y

#50000
0#
b1 H
b11101111 I
b1000 J
0O
b100 [

#55000
b11111001 !
b11011 "
1#
b11111001 +
b11011111 ,
b101 .
1O
b11111001 X
b11011111 Y

#60000
0#
b1 H
b11011111 I
b1000 J
0O
b101 [

#65000
b10101011 !
b11000 "
1#
b10101011 +
b10111111 ,
b110 .
1O
b10101011 X
b10111111 Y

#70000
0#
b1 H
b10111111 I
b1000 J
0O
b110 [

#75000
b11111001 !
b11011 "
1#
b11111001 +
b1111111 ,
b111 .
1O
b11111001 X
b1111111 Y

#80000
0#
b1 H
b1111111 I
b1000 J
0O
b111 [

#85000
b11111111 !
b10000 "
1#
b11111111 +
b11111110 ,
b0 .
1O
b11111111 X
b11111110 Y

#90000
0#
b1 H
b11111110 I
b1000 J
0O
b1000 [

#95000
1#
b11111101 ,
b1 .
1O
b11111101 Y

#100000
0#
b1 H
b11111101 I
b1000 J
0O
b1001 [

#105000
1#
b11111011 ,
b10 .
1O
b11111011 Y

#110000
0#
b1 H
b11111011 I
b1000 J
0O
b1010 [

#115000
1#
b11110111 ,
b11 .
1O
b11110111 Y

#120000
0#
b1 H
b11110111 I
b1000 J
0O
b1011 [

#125000
b10000111 !
b10101 "
1#
b10000111 +
b11101111 ,
b100 .
1O
b10000111 X
b11101111 Y

#130000
0#
b1 H
b11101111 I
b1000 J
0O
b1100 [

#135000
b11111001 !
b11011 "
1#
b11111001 +
b11011111 ,
b101 .
1O
b11111001 X
b11011111 Y

#140000
0#
b1 H
b11011111 I
b1000 J
0O
b1101 [

#145000
b10101011 !
b11000 "
1#
b10101011 +
b10111111 ,
b110 .
1O
b10101011 X
b10111111 Y

#150000
0#
b1 H
b10111111 I
b1000 J
0O
b1110 [

#155000
b11111001 !
b11011 "
1#
b11111001 +
b1111111 ,
b111 .
1O
b11111001 X
b1111111 Y

#160000
0#
b1 H
b1111111 I
b1000 J
0O
b1111 [

#165000
b11111111 !
b10000 "
1#
b11111111 +
b11111110 ,
b0 .
1O
b11111111 X
b11111110 Y

#170000
0#
b1 H
b11111110 I
b1000 J
0O
b1 W
b10000 [

#171000
b1 %
b1000 /
b11011 K
b11000 L
b11011 M
b10101 N
b1 Q
b10 W

#172000
b10011001 !
b100 "
b10 %
b100 '
b10011001 +
b1000 /
b10001 K
b10010 L
b10011 M
b10011 N
b10 Q
b100 S
b11 W
b10011001 X

#173000
b11111111 !
b10000 "
b11 %
b0 '
b11111111 +
b1000 /
b11 Q
b0 S
b100 W
b11111111 X

#174000
b100 %
b1000 /
b10100 K
b10110 L
b10110 M
b11 N
b100 Q
b101 W

#175000
1#
b101 %
b11111101 ,
b1 .
b1000 /
b10111 K
b10001 L
b10100 M
b11000 N
1O
b101 Q
b110 W
b11111101 Y

#176000
b110 %
b1000 /
b10011 K
b10100 L
b10101 M
b10000 N
b110 Q
b111 W

#177000
b111 %
b1000 /
b10010 L
b11100 M
b10100 N
b111 Q
b1000 W

#178000
b10000010 !
b110 "
b1000 %
b10000010 +
b1000 /
b10010 K
b11001 L
b10010 M
b10110 N
b1000 Q
b1001 W
b10000010 X

#179000
b11111111 !
b10000 "
1*
b11111111 +
b1000 /
b10101 K
b10100 L
b11101 M
b10001 N
1U
b1010 W
b11111111 X

#180000
0#
b11010 K
b10110 M
b10110 N
0O
1Z
