password_lock_system/rtl/tick_enable.v
`timescale 1ns/1ps

// 通用分频使能脉冲发生器：每 DIVISOR 个 clk 输出一个周期宽的 tick。
// tick 只作为时序逻辑的 clock-enable 使用，不生成新的时钟域。
module tick_enable #(
    parameter integer CLOCK_HZ = 50_000_000,
    parameter integer TICK_HZ  = 1_000
) (
    input  wire clk,
    input  wire rst,
    output reg  tick
);
    // 要求 CLOCK_HZ 能满足目标频率精度；当前键盘参数 50 MHz/1 kHz 可整除。
    localparam integer DIVISOR = CLOCK_HZ / TICK_HZ;
    localparam integer WIDTH = (DIVISOR <= 2) ? 1 : $clog2(DIVISOR);
    reg [WIDTH-1:0] count;

    always @(posedge clk) begin
        if (rst) begin
            count <= {WIDTH{1'b0}};
            tick  <= 1'b0;
        end else if (count == DIVISOR-1) begin
            count <= {WIDTH{1'b0}};
            tick  <= 1'b1;
        end else begin
            count <= count + 1'b1;
            tick  <= 1'b0;
        end
    end
endmodule

password_lock_system/rtl/keypad_scanner.v
`timescale 1ns/1ps

// 4×4 矩阵键盘扫描器：四列依次拉低，通过 row_n 读取当前列的四个按键。
// 默认每列 1 ms，完整扫描需 4 ms；连续 5 次完整扫描相同后才确认，约等于 20 ms 消抖。
// 长按只产生一次 event_valid；检测到多键同时按下后，必须全部释放才重新允许触发。
module keypad_scanner #(
    parameter integer CLOCK_HZ       = 50_000_000,
    parameter integer COLUMN_TICK_HZ = 1_000,
    parameter integer DEBOUNCE_SCANS = 5
) (
    input  wire       clk,
    input  wire       rst,
    input  wire [3:0] row_n,
    output reg  [3:0] col_n,
    output reg        event_valid,
    output reg  [3:0] event_code
);
    wire column_tick;
    reg [1:0] column_index;
    reg [15:0] sampled_keys;
    reg [15:0] candidate;
    reg [3:0] stable_scans;
    reg armed;
    reg blocked_multi;
    reg [15:0] complete_sample;
    integer i;
    integer key_count;

    // column_tick 是时钟使能脉冲，不是新时钟，所有寄存器仍由 sys_clk 驱动。
    tick_enable #(.CLOCK_HZ(CLOCK_HZ), .TICK_HZ(COLUMN_TICK_HZ)) u_tick (
        .clk(clk), .rst(rst), .tick(column_tick)
    );

    // 16 位 one-hot 位置到键值的接线映射；A/B/C/D/E/F 保留为功能键编码。
    function [3:0] decode_key;
        input [15:0] onehot;
        begin
            case (onehot)
                16'h0001: decode_key = 4'h1;
                16'h0002: decode_key = 4'h4;
                16'h0004: decode_key = 4'h7;
                16'h0008: decode_key = 4'hE;
                16'h0010: decode_key = 4'h2;
                16'h0020: decode_key = 4'h5;
                16'h0040: decode_key = 4'h8;
                16'h0080: decode_key = 4'h0;
                16'h0100: decode_key = 4'h3;
                16'h0200: decode_key = 4'h6;
                16'h0400: decode_key = 4'h9;
                16'h0800: decode_key = 4'hF;
                16'h1000: decode_key = 4'hA;
                16'h2000: decode_key = 4'hB;
                16'h4000: decode_key = 4'hC;
                16'h8000: decode_key = 4'hD;
                default:  decode_key = 4'hF;
            endcase
        end
    endfunction

    // 列输出低有效，每个扫描时隙只允许一列为 0。
    always @(*) begin
        col_n = 4'b1111;
        case (column_index)
            2'd0: col_n = 4'b1110;
            2'd1: col_n = 4'b1101;
            2'd2: col_n = 4'b1011;
            2'd3: col_n = 4'b0111;
        endcase
    end

    always @(posedge clk) begin
        if (rst) begin
            column_index <= 2'd0;
            sampled_keys <= 16'h0000;
            candidate     <= 16'h0000;
            stable_scans  <= 4'd0;
            armed         <= 1'b1;
            blocked_multi <= 1'b0;
            event_valid   <= 1'b0;
            event_code    <= 4'h0;
            complete_sample <= 16'h0000;
        end else begin
            event_valid <= 1'b0;
            if (column_tick) begin
                sampled_keys[column_index*4 + 0] <= ~row_n[0];
                sampled_keys[column_index*4 + 1] <= ~row_n[1];
                sampled_keys[column_index*4 + 2] <= ~row_n[2];
                sampled_keys[column_index*4 + 3] <= ~row_n[3];
                // 第 4 列采完后拼成一次完整的 16 键快照，再统一做消抖和按键数判断。
                if (column_index == 2'd3) begin
                    complete_sample = sampled_keys;
                    complete_sample[12] = ~row_n[0];
                    complete_sample[13] = ~row_n[1];
                    complete_sample[14] = ~row_n[2];
                    complete_sample[15] = ~row_n[3];
                    key_count = 0;
                    for (i = 0; i < 16; i = i + 1)
                        key_count = key_count + complete_sample[i];

                    if (complete_sample == candidate) begin
                        if (stable_scans < DEBOUNCE_SCANS)
                            stable_scans <= stable_scans + 1'b1;
                    end else begin
                        candidate    <= complete_sample;
                        stable_scans <= 4'd1;
                    end

                    // 稳定释放时重新 armed；多键时锁死；单键且已 armed 时输出一次事件。
                    if ((stable_scans == DEBOUNCE_SCANS-1) &&
                        (complete_sample == candidate)) begin
                        if (key_count == 0) begin
                            armed         <= 1'b1;
                            blocked_multi <= 1'b0;
                        end else if (key_count > 1) begin
                            armed         <= 1'b0;
                            blocked_multi <= 1'b1;
                        end else if (armed && !blocked_multi) begin
                            event_valid <= 1'b1;
                            event_code  <= decode_key(complete_sample);
                            armed       <= 1'b0;
                        end
                    end
                    column_index <= 2'd0;
                end else begin
                    column_index <= column_index + 1'b1;
                end
            end
        end
    end
endmodule

password_lock_system/sim/tb_keypad_scanner.sv
`timescale 1ns/1ps
module tb_keypad_scanner;
    reg test_pass=0;
    reg clk=0,rst=1;
    reg [15:0] pressed_keys=0;
    reg [3:0] expected_code=0;
    reg [7:0] scenario=0;
    reg [3:0] row_n;
    wire [3:0] col_n;
    wire event_valid;
    wire [3:0] event_code;
    integer events=0;
    integer i;

    always #5 clk=~clk;
    always @(*) begin
        case(col_n)
            4'b1110: row_n=~pressed_keys[3:0];
            4'b1101: row_n=~pressed_keys[7:4];
            4'b1011: row_n=~pressed_keys[11:8];
            4'b0111: row_n=~pressed_keys[15:12];
            default: row_n=4'b1111;
        endcase
    end

    keypad_scanner #(.CLOCK_HZ(4000),.COLUMN_TICK_HZ(1000),.DEBOUNCE_SCANS(2)) dut(
       .clk(clk),.rst(rst),.row_n(row_n),.col_n(col_n),
       .event_valid(event_valid),.event_code(event_code));

    always @(posedge clk) if(event_valid) begin
        if(event_code!==expected_code)
            $fatal(1,"wrong key code expected=%h actual=%h scenario=%0d",expected_code,event_code,scenario);
        events=events+1;
    end

    function [3:0] expected_for_bit(input integer bit_index);
        case(bit_index)
             0:expected_for_bit=4'h1;  1:expected_for_bit=4'h4;
             2:expected_for_bit=4'h7;  3:expected_for_bit=4'hE;
             4:expected_for_bit=4'h2;  5:expected_for_bit=4'h5;
             6:expected_for_bit=4'h8;  7:expected_for_bit=4'h0;
             8:expected_for_bit=4'h3;  9:expected_for_bit=4'h6;
            10:expected_for_bit=4'h9; 11:expected_for_bit=4'hF;
            12:expected_for_bit=4'hA; 13:expected_for_bit=4'hB;
            14:expected_for_bit=4'hC; default:expected_for_bit=4'hD;
        endcase
    endfunction

    task release_all; begin pressed_keys=0;repeat(80)@(negedge clk);end endtask

    initial begin
        repeat(4)@(negedge clk);rst=0;

        scenario=1;expected_code=4'hA;pressed_keys=16'h1000;
        repeat(200)@(negedge clk);
        if(events!=1)$fatal(1,"long press generated %0d events",events);
        release_all();

        scenario=2;pressed_keys=16'h0021;
        repeat(120)@(negedge clk);
        if(events!=1)$fatal(1,"multi-key sample generated an event");
        release_all();

        for(i=0;i<16;i=i+1) begin
            scenario=8'd16+i;
            expected_code=expected_for_bit(i);
            pressed_keys=16'h0001<<i;
            repeat(80)@(negedge clk);
            release_all();
            if(events!=i+2)$fatal(1,"key %0d event missing events=%0d",i,events);
        end
        test_pass=1;$display("PASS tb_keypad_scanner");$finish;
    end
endmodule

simulation_waveforms/04_matrix_keypad/tb_keypad_scanner.vcd
$date
   Sun Sep 13 16:27:05 2026
$end

$version
  2023.2
$end

$timescale
  1ps
$end

$scope module tb_keypad_scanner $end
$var reg 1 > test_pass $end
$var reg 1 ? clk $end
$var reg 1 @ rst $end
$var reg 16 A pressed_keys [15:0] $end
$var reg 4 B expected_code [3:0] $end
$var reg 8 C scenario [7:0] $end
$var reg 4 D row_n [3:0] $end
$var wire 4 E col_n [3:0] $end
$var wire 1 F event_valid $end
$var wire 4 G event_code [3:0] $end
$var integer 32 H events [31:0] $end
$var integer 32 I i [31:0] $end
$scope module dut $end
$var wire 1 ! clk $end
$var wire 1 " rst $end
$var wire 4 + row_n [3:0] $end
$var reg 4 , col_n [3:0] $end
$var reg 1 - event_valid $end
$var reg 4 . event_code [3:0] $end
$var wire 1 / column_tick $end
$var reg 2 0 column_index [1:0] $end
$var reg 16 1 sampled_keys [15:0] $end
$var reg 16 2 candidate [15:0] $end
$var reg 4 3 stable_scans [3:0] $end
$var reg 1 4 armed $end
$var reg 1 5 blocked_multi $end
$var reg 16 6 complete_sample [15:0] $end
$var integer 32 7 i [31:0] $end
$var integer 32 8 key_count [31:0] $end
$var parameter 0 9 CLOCK_HZ [31:0] $end
$var parameter 0 : COLUMN_TICK_HZ [31:0] $end
$var parameter 0 ; DEBOUNCE_SCANS [31:0] $end
$scope module u_tick $end
$var wire 1 ! clk $end
$var wire 1 " rst $end
$var reg 1 # tick $end
$var reg 2 $ count [1:0] $end
$var parameter 0 % CLOCK_HZ [31:0] $end
$var parameter 0 & TICK_HZ [31:0] $end
$var parameter 0 ' DIVISOR [31:0] $end
$var parameter 0 ( WIDTH [31:0] $end
$upscope $end
$scope function decode_key $end
$var reg 4 ) decode_key [3:0] $end
$var reg 16 * onehot [15:0] $end
$upscope $end
$upscope $end
$scope function expected_for_bit $end
$var reg 4 < expected_for_bit [3:0] $end
$var integer 32 = bit_index [31:0] $end
$upscope $end
$upscope $end
$enddefinitions $end

#0
$dumpvars
0!
1"
x#
bx $
b111110100000 %
b1111101000 &
b100 '
b10 (
bx )
bx *
bx +
bx ,
x-
bx .
x/
bx 0
bx 1
bx 2
bx 3
x4
x5
bx 6
bx 7
bx 8
b111110100000 9
b1111101000 :
b10 ;
bx <
bx =
0>
0?
1@
b0 A
b0 B
b0 C
bx D
bx E
xF
bx G
b0 H
bx I
$end

#5000
1!
0#
b0 $
b1111 +
b1110 ,
0-
b0 .
0/
b0 0
b0 1
b0 2
b0 3
14
05
b0 6
1?
b1111 D
b1110 E
0F
b0 G

#10000
0!
0?

#15000
1!
1?

#20000
0!
0?

#25000
1!
1?

#30000
0!
0?

#35000
1!
1?

#40000
0!
0"
0?
0@
b1000000000000 A
b1010 B
b1 C

#45000
1!
b1 $
1?

#50000
0!
0?

#55000
1!
b10 $
1?

#60000
0!
0?

#65000
1!
b11 $
1?

#70000
0!
0?

#75000
1!
1#
b0 $
1/
1?

#80000
0!
0?

#85000
1!
0#
b1 $
b1101 ,
0/
b1 0
1?
b1101 E

#90000
0!
0?

#95000
1!
b10 $
1?

#100000
0!
0?

#105000
1!
b11 $
1?

#110000
0!
0?

#115000
1!
1#
b0 $
1/
1?

#120000
0!
0?

#125000
1!
0#
b1 $
b1011 ,
0/
b10 0
1?
b1011 E

#130000
0!
0?

#135000
1!
b10 $
1?

#140000
0!
0?

#145000
1!
b11 $
1?

#150000
0!
0?

#155000
1!
1#
b0 $
1/
1?

#160000
0!
0?

#165000
1!
0#
b1 $
b1110 +
b111 ,
0/
b11 0
1?
b1110 D
b111 E

#170000
0!
0?

#175000
1!
b10 $
1?

#180000
0!
0?

#185000
1!
b11 $
1?

#190000
0!
0?

#195000
1!
1#
b0 $
1/
1?

#200000
0!
0?

#205000
1!
0#
b1 $
b1111 +
b1110 ,
0/
b0 0
b1000000000000 1
b1000000000000 2
b1 3
b1000000000000 6
b10000 7
b1 8
1?
b1111 D
b1110 E

#210000
0!
0?

#215000
1!
b10 $
1?

#220000
0!
0?

#225000
1!
b11 $
1?

#230000
0!
0?

#235000
1!
1#
b0 $
1/
1?

#240000
0!
0?

#245000
1!
0#
b1 $
b1101 ,
0/
b1 0
1?
b1101 E

#250000
0!
0?

#255000
1!
b10 $
1?

#260000
0!
0?

#265000
1!
b11 $
1?

#270000
0!
0?

#275000
1!
1#
b0 $
1/
1?

#280000
0!
0?

#285000
1!
0#
b1 $
b1011 ,
0/
b10 0
1?
b1011 E

#290000
0!
0?

#295000
1!
b10 $
1?

#300000
0!
0?

#305000
1!
b11 $
1?

#310000
0!
0?

#315000
1!
1#
b0 $
1/
1?

#320000
0!
0?

#325000
1!
0#
b1 $
b1110 +
b111 ,
0/
b11 0
1?
b1110 D
b111 E

#330000
0!
0?

#335000
1!
b10 $
1?

#340000
0!
0?

#345000
1!
b11 $
1?

#350000
0!
0?

#355000
1!
1#
b0 $
1/
1?

#360000
0!
0?

#365000
1!
0#
b1 $
b1010 )
b1000000000000 *
b1111 +
b1110 ,
1-
b1010 .
0/
b0 0
b10 3
04
b10000 7
b1 8
1?
b1111 D
b1110 E
1F
b1010 G

#370000
0!
0?

#375000
1!
b10 $
0-
1?
0F
b1 H

#380000
0!
0?

#385000
1!
b11 $
1?

#390000
0!
0?

#395000
1!
1#
b0 $
1/
1?

#400000
0!
0?

#405000
1!
0#
b1 $
b1101 ,
0/
b1 0
1?
b1101 E

#410000
0!
0?

#415000
1!
b10 $
1?

#420000
0!
0?

#425000
1!
b11 $
1?

#430000
0!
0?

#435000
1!
1#
b0 $
1/
1?

#440000
0!
0?

#445000
1!
0#
b1 $
b1011 ,
0/
b10 0
1?
b1011 E

#450000
0!
0?

#455000
1!
b10 $
1?

#460000
0!
0?

#465000
1!
b11 $
1?

#470000
0!
0?

#475000
1!
1#
b0 $
1/
1?

#480000
0!
0?

#485000
1!
0#
b1 $
b1110 +
b111 ,
0/
b11 0
1?
b1110 D
b111 E

#490000
0!
0?

#495000
1!
b10 $
1?

#500000
0!
0?

#505000
1!
b11 $
1?

#510000
0!
0?

#515000
1!
1#
b0 $
1/
1?

#520000
0!
0?

#525000
1!
0#
b1 $
b1111 +
b1110 ,
0/
b0 0
b10000 7
b1 8
1?
b1111 D
b1110 E

#530000
0!
0?

#535000
1!
b10 $
1?

#540000
0!
0?

#545000
1!
b11 $
1?

#550000
0!
0?

#555000
1!
1#
b0 $
1/
1?

#560000
0!
0?

#565000
1!
0#
b1 $
b1101 ,
0/
b1 0
1?
b1101 E

#570000
0!
0?

#575000
1!
b10 $
1?

#580000
0!
0?

#585000
1!
b11 $
1?

#590000
0!
0?

#595000
1!
1#
b0 $
1/
1?

#600000
0!
0?

#605000
1!
0#
b1 $
b1011 ,
0/
b10 0
1?
b1011 E

#610000
0!
0?

#615000
1!
b10 $
1?

#620000
0!
0?

#625000
1!
b11 $
1?

#630000
0!
0?

#635000
1!
1#
b0 $
1/
1?

#640000
0!
0?

#645000
1!
0#
b1 $
b1110 +
b111 ,
0/
b11 0
1?
b1110 D
b111 E

#650000
0!
0?

#655000
1!
b10 $
1?

#660000
0!
0?

#665000
1!
b11 $
1?

#670000
0!
0?

#675000
1!
1#
b0 $
1/
1?

#680000
0!
0?

#685000
1!
0#
b1 $
b1111 +
b1110 ,
0/
b0 0
b10000 7
b1 8
1?
b1111 D
b1110 E

#690000
0!
0?

#695000
1!
b10 $
1?

#700000
0!
0?

#705000
1!
b11 $
1?

#710000
0!
0?

#715000
1!
1#
b0 $
1/
1?

#720000
0!
0?

#725000
1!
0#
b1 $
b1101 ,
0/
b1 0
1?
b1101 E

#730000
0!
0?

#735000
1!
b10 $
1?

#740000
0!
0?

#745000
1!
b11 $
1?

#750000
0!
0?

#755000
1!
1#
b0 $
1/
1?

#760000
0!
0?

#765000
1!
0#
b1 $
b1011 ,
0/
b10 0
1?
b1011 E

#770000
0!
0?

#775000
1!
b10 $
1?

#780000
0!
0?

#785000
1!
b11 $
1?

#790000
0!
0?

#795000
1!
1#
b0 $
1/
1?

#800000
0!
0?

#805000
1!
0#
b1 $
b1110 +
b111 ,
0/
b11 0
1?
b1110 D
b111 E

#810000
0!
0?

#815000
1!
b10 $
1?

#820000
0!
0?

#825000
1!
b11 $
1?

#830000
0!
0?

#835000
1!
1#
b0 $
1/
1?

#840000
0!
0?

#845000
1!
0#
b1 $
b1111 +
b1110 ,
0/
b0 0
b10000 7
b1 8
1?
b1111 D
b1110 E

#850000
0!
0?

#855000
1!
b10 $
1?

#860000
0!
0?

#865000
1!
b11 $
1?

#870000
0!
0?

#875000
1!
1#
b0 $
1/
1?

#880000
0!
0?

#885000
1!
0#
b1 $
b1101 ,
0/
b1 0
1?
b1101 E

#890000
0!
0?

#895000
1!
b10 $
1?

#900000
0!
0?

#905000
1!
b11 $
1?

#910000
0!
0?

#915000
1!
1#
b0 $
1/
1?

#920000
0!
0?

#925000
1!
0#
b1 $
b1011 ,
0/
b10 0
1?
b1011 E

#930000
0!
0?

#935000
1!
b10 $
1?

#940000
0!
0?

#945000
1!
b11 $
1?

#950000
0!
0?

#955000
1!
1#
b0 $
1/
1?

#960000
0!
0?

#965000
1!
0#
b1 $
b1110 +
b111 ,
0/
b11 0
1?
b1110 D
b111 E

#970000
0!
0?

#975000
1!
b10 $
1?

#980000
0!
0?

#985000
1!
b11 $
1?

#990000
0!
0?

#995000
1!
1#
b0 $
1/
1?

#1000000
0!
0?

#1005000
1!
0#
b1 $
b1111 +
b1110 ,
0/
b0 0
b10000 7
b1 8
1?
b1111 D
b1110 E

#1010000
0!
0?

#1015000
1!
b10 $
1?

#1020000
0!
0?

#1025000
1!
b11 $
1?

#1030000
0!
0?

#1035000
1!
1#
b0 $
1/
1?

#1040000
0!
0?

#1045000
1!
0#
b1 $
b1101 ,
0/
b1 0
1?
b1101 E

#1050000
0!
0?

#1055000
1!
b10 $
1?

#1060000
0!
0?

#1065000
1!
b11 $
1?

#1070000
0!
0?

#1075000
1!
1#
b0 $
1/
1?

#1080000
0!
0?

#1085000
1!
0#
b1 $
b1011 ,
0/
b10 0
1?
b1011 E

#1090000
0!
0?

#1095000
1!
b10 $
1?

#1100000
0!
0?

#1105000
1!
b11 $
1?

#1110000
0!
0?

#1115000
1!
1#
b0 $
1/
1?

#1120000
0!
0?

#1125000
1!
0#
b1 $
b1110 +
b111 ,
0/
b11 0
1?
b1110 D
b111 E

#1130000
0!
0?

#1135000
1!
b10 $
1?

#1140000
0!
0?

#1145000
1!
b11 $
1?

#1150000
0!
0?

#1155000
1!
1#
b0 $
1/
1?

#1160000
0!
0?

#1165000
1!
0#
b1 $
b1111 +
b1110 ,
0/
b0 0
b10000 7
b1 8
1?
b1111 D
b1110 E

#1170000
0!
0?

#1175000
1!
b10 $
1?

#1180000
0!
0?

#1185000
1!
b11 $
1?

#1190000
0!
0?

#1195000
1!
1#
b0 $
1/
1?

#1200000
0!
0?

#1205000
1!
0#
b1 $
b1101 ,
0/
b1 0
1?
b1101 E

#1210000
0!
0?

#1215000
1!
b10 $
1?

#1220000
0!
0?

#1225000
1!
b11 $
1?

#1230000
0!
0?

#1235000
1!
1#
b0 $
1/
1?

#1240000
0!
0?

#1245000
1!
0#
b1 $
b1011 ,
0/
b10 0
1?
b1011 E

#1250000
0!
0?

#1255000
1!
b10 $
1?

#1260000
0!
0?

#1265000
1!
b11 $
1?

#1270000
0!
0?

#1275000
1!
1#
b0 $
1/
1?

#1280000
0!
0?

#1285000
1!
0#
b1 $
b1110 +
b111 ,
0/
b11 0
1?
b1110 D
b111 E

#1290000
0!
0?

#1295000
1!
b10 $
1?

#1300000
0!
0?

#1305000
1!
b11 $
1?

#1310000
0!
0?

#1315000
1!
1#
b0 $
1/
1?

#1320000
0!
0?

#1325000
1!
0#
b1 $
b1111 +
b1110 ,
0/
b0 0
b10000 7
b1 8
1?
b1111 D
b1110 E

#1330000
0!
0?

#1335000
1!
b10 $
1?

#1340000
0!
0?

#1345000
1!
b11 $
1?

#1350000
0!
0?

#1355000
1!
1#
b0 $
1/
1?

#1360000
0!
0?

#1365000
1!
0#
b1 $
b1101 ,
0/
b1 0
1?
b1101 E

#1370000
0!
0?

#1375000
1!
b10 $
1?

#1380000
0!
0?

#1385000
1!
b11 $
1?

#1390000
0!
0?

#1395000
1!
1#
b0 $
1/
1?

#1400000
0!
0?

#1405000
1!
0#
b1 $
b1011 ,
0/
b10 0
1?
b1011 E

#1410000
0!
0?

#1415000
1!
b10 $
1?

#1420000
0!
0?

#1425000
1!
b11 $
1?

#1430000
0!
0?

#1435000
1!
1#
b0 $
1/
1?

#1440000
0!
0?

#1445000
1!
0#
b1 $
b1110 +
b111 ,
0/
b11 0
1?
b1110 D
b111 E

#1450000
0!
0?

#1455000
1!
b10 $
1?

#1460000
0!
0?

#1465000
1!
b11 $
1?

#1470000
0!
0?

#1475000
1!
1#
b0 $
1/
1?

#1480000
0!
0?

#1485000
1!
0#
b1 $
b1111 +
b1110 ,
0/
b0 0
b10000 7
b1 8
1?
b1111 D
b1110 E

#1490000
0!
0?

#1495000
1!
b10 $
1?

#1500000
0!
0?

#1505000
1!
b11 $
1?

#1510000
0!
0?

#1515000
1!
1#
b0 $
1/
1?

#1520000
0!
0?

#1525000
1!
0#
b1 $
b1101 ,
0/
b1 0
1?
b1101 E

#1530000
0!
0?

#1535000
1!
b10 $
1?

#1540000
0!
0?

#1545000
1!
b11 $
1?

#1550000
0!
0?

#1555000
1!
1#
b0 $
1/
1?

#1560000
0!
0?

#1565000
1!
0#
b1 $
b1011 ,
0/
b10 0
1?
b1011 E

#1570000
0!
0?

#1575000
1!
b10 $
1?

#1580000
0!
0?

#1585000
1!
b11 $
1?

#1590000
0!
0?

#1595000
1!
1#
b0 $
1/
1?

#1600000
0!
0?

#1605000
1!
0#
b1 $
b1110 +
b111 ,
0/
b11 0
1?
b1110 D
b111 E

#1610000
0!
0?

#1615000
1!
b10 $
1?

#1620000
0!
0?

#1625000
1!
b11 $
1?

#1630000
0!
0?

#1635000
1!
1#
b0 $
1/
1?

#1640000
0!
0?

#1645000
1!
0#
b1 $
b1111 +
b1110 ,
0/
b0 0
b10000 7
b1 8
1?
b1111 D
b1110 E

#1650000
0!
0?

#1655000
1!
b10 $
1?

#1660000
0!
0?

#1665000
1!
b11 $
1?

#1670000
0!
0?

#1675000
1!
1#
b0 $
1/
1?

#1680000
0!
0?

#1685000
1!
0#
b1 $
b1101 ,
0/
b1 0
1?
b1101 E

#1690000
0!
0?

#1695000
1!
b10 $
1?

#1700000
0!
0?

#1705000
1!
b11 $
1?

#1710000
0!
0?

#1715000
1!
1#
b0 $
1/
1?

#1720000
0!
0?

#1725000
1!
0#
b1 $
b1011 ,
0/
b10 0
1?
b1011 E

#1730000
0!
0?

#1735000
1!
b10 $
1?

#1740000
0!
0?

#1745000
1!
b11 $
1?

#1750000
0!
0?

#1755000
1!
1#
b0 $
1/
1?

#1760000
0!
0?

#1765000
1!
0#
b1 $
b1110 +
b111 ,
0/
b11 0
1?
b1110 D
b111 E

#1770000
0!
0?

#1775000
1!
b10 $
1?

#1780000
0!
0?

#1785000
1!
b11 $
1?

#1790000
0!
0?

#1795000
1!
1#
b0 $
1/
1?

#1800000
0!
0?

#1805000
1!
0#
b1 $
b1111 +
b1110 ,
0/
b0 0
b10000 7
b1 8
1?
b1111 D
b1110 E

#1810000
0!
0?

#1815000
1!
b10 $
1?

#1820000
0!
0?

#1825000
1!
b11 $
1?

#1830000
0!
0?

#1835000
1!
1#
b0 $
1/
1?

#1840000
0!
0?

#1845000
1!
0#
b1 $
b1101 ,
0/
b1 0
1?
b1101 E

#1850000
0!
0?

#1855000
1!
b10 $
1?

#1860000
0!
0?

#1865000
1!
b11 $
1?

#1870000
0!
0?

#1875000
1!
1#
b0 $
1/
1?

#1880000
0!
0?

#1885000
1!
0#
b1 $
b1011 ,
0/
b10 0
1?
b1011 E

#1890000
0!
0?

#1895000
1!
b10 $
1?

#1900000
0!
0?

#1905000
1!
b11 $
1?

#1910000
0!
0?

#1915000
1!
1#
b0 $
1/
1?

#1920000
0!
0?

#1925000
1!
0#
b1 $
b1110 +
b111 ,
0/
b11 0
1?
b1110 D
b111 E

#1930000
0!
0?

#1935000
1!
b10 $
1?

#1940000
0!
0?

#1945000
1!
b11 $
1?

#1950000
0!
0?

#1955000
1!
1#
b0 $
1/
1?

#1960000
0!
0?

#1965000
1!
0#
b1 $
b1111 +
b1110 ,
0/
b0 0
b10000 7
b1 8
1?
b1111 D
b1110 E

#1970000
0!
0?

#1975000
1!
b10 $
1?

#1980000
0!
0?

#1985000
1!
b11 $
1?

#1990000
0!
0?

#1995000
1!
1#
b0 $
1/
1?

#2000000
0!
0?

#2005000
1!
0#
b1 $
b1101 ,
0/
b1 0
1?
b1101 E

#2010000
0!
0?

#2015000
1!
b10 $
1?

#2020000
0!
0?

#2025000
1!
b11 $
1?

#2030000
0!
0?

#2035000
1!
1#
b0 $
1/
1?

#2040000
0!
0?
b0 A

#2045000
1!
0#
b1 $
b1011 ,
0/
b10 0
1?
b1011 E

#2050000
0!
0?

#2055000
1!
b10 $
1?

#2060000
0!
0?

#2065000
1!
b11 $
1?

#2070000
0!
0?

#2075000
1!
1#
b0 $
1/
1?

#2080000
0!
0?

#2085000
1!
0#
b1 $
b111 ,
0/
b11 0
1?
b111 E

#2090000
0!
0?

#2095000
1!
b10 $
1?

#2100000
0!
0?

#2105000
1!
b11 $
1?

#2110000
0!
0?

#2115000
1!
1#
b0 $
1/
1?

#2120000
0!
0?

#2125000
1!
0#
b1 $
b1110 ,
0/
b0 0
b0 1
b0 2
b1 3
b0 6
b10000 7
b0 8
1?
b1110 E

#2130000
0!
0?

#2135000
1!
b10 $
1?

#2140000
0!
0?

#2145000
1!
b11 $
1?

#2150000
0!
0?

#2155000
1!
1#
b0 $
1/
1?

#2160000
0!
0?

#2165000
1!
0#
b1 $
b1101 ,
0/
b1 0
1?
b1101 E

#2170000
0!
0?

#2175000
1!
b10 $
1?

#2180000
0!
0?

#2185000
1!
b11 $
1?

#2190000
0!
0?

#2195000
1!
1#
b0 $
1/
1?

#2200000
0!
0?

#2205000
1!
0#
b1 $
b1011 ,
0/
b10 0
1?
b1011 E

#2210000
0!
0?

#2215000
1!
b10 $
1?

#2220000
0!
0?

#2225000
1!
b11 $
1?

#2230000
0!
0?

#2235000
1!
1#
b0 $
1/
1?

#2240000
0!
0?

#2245000
1!
0#
b1 $
b111 ,
0/
b11 0
1?
b111 E

#2250000
0!
0?

#2255000
1!
b10 $
1?

#2260000
0!
0?

#2265000
1!
b11 $
1?

#2270000
0!
0?

#2275000
1!
1#
b0 $
1/
1?

#2280000
0!
0?

#2285000
1!
0#
b1 $
b1110 ,
0/
b0 0
b10 3
14
b10000 7
1?
b1110 E

#2290000
0!
0?

#2295000
1!
b10 $
1?

#2300000
0!
0?

#2305000
1!
b11 $
1?

#2310000
0!
0?

#2315000
1!
1#
b0 $
1/
1?

#2320000
0!
0?

#2325000
1!
0#
b1 $
b1101 ,
0/
b1 0
1?
b1101 E

#2330000
0!
0?

#2335000
1!
b10 $
1?

#2340000
0!
0?

#2345000
1!
b11 $
1?

#2350000
0!
0?

#2355000
1!
1#
b0 $
1/
1?

#2360000
0!
0?

#2365000
1!
0#
b1 $
b1011 ,
0/
b10 0
1?
b1011 E

#2370000
0!
0?

#2375000
1!
b10 $
1?

#2380000
0!
0?

#2385000
1!
b11 $
1?

#2390000
0!
0?

#2395000
1!
1#
b0 $
1/
1?

#2400000
0!
0?

#2405000
1!
0#
b1 $
b111 ,
0/
b11 0
1?
b111 E

#2410000
0!
0?

#2415000
1!
b10 $
1?

#2420000
0!
0?

#2425000
1!
b11 $
1?

#2430000
0!
0?

#2435000
1!
1#
b0 $
1/
1?

#2440000
0!
0?

#2445000
1!
0#
b1 $
b1110 ,
0/
b0 0
b10000 7
1?
b1110 E

#2450000
0!
0?

#2455000
1!
b10 $
1?

#2460000
0!
0?

#2465000
1!
b11 $
1?

#2470000
0!
0?

#2475000
1!
1#
b0 $
1/
1?

#2480000
0!
0?

#2485000
1!
0#
b1 $
b1101 ,
0/
b1 0
1?
b1101 E

#2490000
0!
0?

#2495000
1!
b10 $
1?

#2500000
0!
0?

#2505000
1!
b11 $
1?

#2510000
0!
0?

#2515000
1!
1#
b0 $
1/
1?

#2520000
0!
0?

#2525000
1!
0#
b1 $
b1011 ,
0/
b10 0
1?
b1011 E

#2530000
0!
0?

#2535000
1!
b10 $
1?

#2540000
0!
0?

#2545000
1!
b11 $
1?

#2550000
0!
0?

#2555000
1!
1#
b0 $
1/
1?

#2560000
0!
0?

#2565000
1!
0#
b1 $
b111 ,
0/
b11 0
1?
b111 E

#2570000
0!
0?

#2575000
1!
b10 $
1?

#2580000
0!
0?

#2585000
1!
b11 $
1?

#2590000
0!
0?

#2595000
1!
1#
b0 $
1/
1?

#2600000
0!
0?

#2605000
1!
0#
b1 $
b1110 ,
0/
b0 0
b10000 7
1?
b1110 E

#2610000
0!
0?

#2615000
1!
b10 $
1?

#2620000
0!
0?

#2625000
1!
b11 $
1?

#2630000
0!
0?

#2635000
1!
1#
b0 $
1/
1?

#2640000
0!
0?

#2645000
1!
0#
b1 $
b1101 ,
0/
b1 0
1?
b1101 E

#2650000
0!
0?

#2655000
1!
b10 $
1?

#2660000
0!
0?

#2665000
1!
b11 $
1?

#2670000
0!
0?

#2675000
1!
1#
b0 $
1/
1?

#2680000
0!
0?

#2685000
1!
0#
b1 $
b1011 ,
0/
b10 0
1?
b1011 E

#2690000
0!
0?

#2695000
1!
b10 $
1?

#2700000
0!
0?

#2705000
1!
b11 $
1?

#2710000
0!
0?

#2715000
1!
1#
b0 $
1/
1?

#2720000
0!
0?

#2725000
1!
0#
b1 $
b111 ,
0/
b11 0
1?
b111 E

#2730000
0!
0?

#2735000
1!
b10 $
1?

#2740000
0!
0?

#2745000
1!
b11 $
1?

#2750000
0!
0?

#2755000
1!
1#
b0 $
1/
1?

#2760000
0!
0?

#2765000
1!
0#
b1 $
b1110 ,
0/
b0 0
b10000 7
1?
b1110 E

#2770000
0!
0?

#2775000
1!
b10 $
1?

#2780000
0!
0?

#2785000
1!
b11 $
1?

#2790000
0!
0?

